Workbook

Sheet 测算表
B2: 原政策考核
B3: 序号 | C3: 年份 | D3: 月份 | E3: 市场分布 | F3: 队号 | G3: 钻机类型 | H3: 井号 | I3: 区块 | J3: 井别 | K3: 井型 | L3: 开次 | M3: 实际井深（米） | N3: 搬迁周期（天） | O3: 建井周期 | P3: 柴油 | Q3: 机油 | R3: 一般材料 | S3: 设备修理 | T3: 井控材料 | U3: 材料运费 | V3: 生活污水拉运量 | W3: 增效工时 | Y3: 队号 | Z3: 周期兑现（B类） | AA3: 材料预算 | AB3: 小计
B4: 1 | C4: 2025 | D4: 1月 | E4: 大港 | F4: 70520 | G4: ZJ70D | H4: 板111-28 | I4: 板桥 | J4: 开发井 | K4: 定向井 | L4: 2 | M4: 2925 | N4: 7 | O4: 25.5 | P4: 66.117333 | Q4: 1.07 | R4: 68221.627 | S4: 19891.667 | T4: 0 | U4: 1.16 | Y4: 70520 | Z4: =O4*10*120+O4*28*80 -> 87720 | AA4: =P4/2.67*10000+Q4*20000+R4+S4+T4+U4*400+V4*100+W4*50 -> 357607.76 | AB4: =SUM(Z4:AA4) -> 445327.76
B5: 2 | C5: 2025 | D5: 3月 | E5: 大港 | F5: 70520 | G5: ZJ70D | H5: 板172X1 | I5: 板桥 | J5: 开发井 | K5: 定向井 | L5: 2 | M5: 2915 | N5: 5.7916667 | O5: 26 | P5: 71.4725 | Q5: 1.11 | R5: 66804.98 | S5: 18900 | T5: 0 | U5: 60 | V5: 24 | W5: 1.2 | Y5: 70520 | Z5: =O5*10*120+O5*28*80 -> 89440 | AA5: =P5/2.67*10000+Q5*20000+R5+S5+T5+U5*400+V5*100+W5*50 -> 402052.25 | AB5: =SUM(Z5:AA5) -> 491492.25
B6: 3 | C6: 2025 | D6: 4月 | E6: 大港 | F6: 50537 | G6: ZJ50J | H6: 板61-37H | I6: 板桥 | J6: 开发井 | K6: 水平井 | L6: 3 | M6: 2382 | N6: 5.5 | O6: 18.25 | P6: 44.533333 | Q6: 0.48 | R6: 46112.8 | S6: 17233.333 | T6: 0 | U6: 0.92 | V6: 46 | W6: 18.4 | Y6: 50537 | Z6: =O6*10*120+O6*28*80 -> 62780 | AA6: =P6/2.67*10000+Q6*20000+R6+S6+T6+U6*400+V6*100+W6*50 -> 245625.64 | AB6: =SUM(Z6:AA6) -> 308405.64
B7: 4 | C7: 2025 | D7: 5月 | E7: 大港 | F7: 50537 | G7: ZJ50J | H7: 板180X1 | I7: 板桥 | J7: 评价井 | K7: 定向井 | L7: 2 | M7: 3523 | N7: 5.8125 | O7: 26.5 | P7: 76.266667 | Q7: 0.78 | R7: 67987.8 | S7: 28200 | T7: 0 | U7: 78 | V7: 31.2 | W7: 1.56 | Y7: 50537 | Z7: =O7*10*120+O7*28*80 -> 91160 | AA7: =P7/2.67*10000+Q7*20000+R7+S7+T7+U7*400+V7*100+W7*50 -> 431828.75 | AB7: =SUM(Z7:AA7) -> 522988.75
B8: 5 | C8: 2025 | D8: 5月 | E8: 大港 | F8: 50537 | G8: ZJ50J | H8: 板60-47H | I8: 板桥 | J8: 开发井 | K8: 水平井 | L8: 2 | M8: 2314 | N8: 4 | O8: 19.5 | P8: 51.2 | Q8: 0.52 | R8: 37500 | S8: 18800 | T8: 0 | U8: 1 | V8: 50 | W8: 20 | Y8: 50537 | Z8: =O8*10*120+O8*28*80 -> 67080 | AA8: =P8/2.67*10000+Q8*20000+R8+S8+T8+U8*400+V8*100+W8*50 -> 264860.3 | AB8: =SUM(Z8:AA8) -> 331940.3
B9: 6 | C9: 2025 | D9: 5月 | E9: 大港 | F9: 70520 | G9: ZJ70D | H9: 南港13-18 | I9: 唐东 | J9: 开发井 | K9: 定向井 | L9: 3 | M9: 4210 | N9: 6.7916667 | O9: 41.5 | P9: 142.25833 | Q9: 2.16 | R9: 129471.63 | S9: 36750 | T9: 0 | U9: 117 | V9: 46.8 | W9: 2.34 | Y9: 70520 | Z9: =O9*10*120+O9*28*80 -> 142760 | AA9: =P9/2.67*10000+Q9*20000+R9+S9+T9+U9*400+V9*100+W9*50 -> 793821.37 | AB9: =SUM(Z9:AA9) -> 936581.37
B10: 7 | C10: 2025 | D10: 6月 | E10: 大港 | F10: 50537 | G10: ZJ50J | H10: 板61-36H | I10: 板桥 | J10: 开发井 | K10: 水平井 | L10: 2 | M10: 2850 | N10: 4 | O10: 20.5 | P10: 53.783333 | Q10: 0.55 | R10: 40000 | S10: 20053.333 | T10: 0 | U10: 1.06 | V10: 53 | W10: 21.2 | Y10: 50537 | Z10: =O10*10*120+O10*28*80 -> 70520 | AA10: =P10/2.67*10000+Q10*20000+R10+S10+T10+U10*400+V10*100+W10*50 -> 279273.04 | AB10: =SUM(Z10:AA10) -> 349793.04
B11: 8 | C11: 2025 | D11: 7月 | E11: 大港 | F11: 50537 | G11: ZJ50J | H11: 板60-48H | I11: 板桥 | J11: 开发井 | K11: 水平井 | L11: 2 | M11: 2278 | N11: 8.5833333 | O11: 17.5 | P11: 44.1 | Q11: 0.45 | R11: 32500 | S11: 16293.333 | T11: 0 | U11: 0.86 | V11: 43 | W11: 17.2 | Y11: 50537 | Z11: =O11*10*120+O11*28*80 -> 60200 | AA11: =P11/2.67*10000+Q11*20000+R11+S11+T11+U11*400+V11*100+W11*50 -> 228465.87 | AB11: =SUM(Z11:AA11) -> 288665.87
B12: 9 | C12: 2025 | D12: 7月 | E12: 大港 | F12: 70520 | G12: ZJ70D | H12: 唐东9X9 | I12: 唐东 | J12: 评价井 | K12: 定向井 | L12: 3 | M12: 3945 | N12: 5.75 | O12: 31.5 | P12: 90.991667 | Q12: 1.66 | R12: 83333.333 | S12: 26250 | T12: 0 | U12: 83 | V12: 33.2 | W12: 1.66 | Y12: 70520 | Z12: =O12*10*120+O12*28*80 -> 108360 | AA12: =P12/2.67*10000+Q12*20000+R12+S12+T12+U12*400+V12*100+W12*50 -> 520179.09 | AB12: =SUM(Z12:AA12) -> 628539.09
B13: 10 | C13: 2025 | D13: 10月 | E13: 大港 | F13: 70520 | G13: ZJ70D | H13: 唐东20X5 | I13: 唐东 | J13: 评价井 | K13: 定向井 | L13: 3 | M13: 5580 | N13: 16.333333 | O13: 42 | P13: 553612 | Q13: 0.66 | R13: 95000 | S13: 29925 | T13: 0 | U13: 118.33333 | V13: 47.333333 | W13: 2.3666667 | Y13: 70520 | Z13: =O13*10*120+O13*28*80 -> 144480 | AA13: =P13+Q13*20000+R13+S13+T13+U13*400+V13*100+W13*50 -> 743922 | AB13: =SUM(Z13:AA13) -> 888402
AA14: =SUM(AA4:AA13) -> 4267636.1 | AB14: =SUM(AB4:AB13) -> 5192136.1
B16: 新政策考核 | O16: =(P16+Q16)/M27/2 -> 0
B17: 序号 | C17: 年份 | D17: 月份 | E17: 市场分布 | F17: 队号 | G17: 钻机类型 | H17: 井号 | I17: 区块 | J17: 井别 | K17: 井型 | L17: 开次 | M17: 实际井深（米） | N17: 工序 | O17: 米费 | P17: 一般材料 | Q17: 能耗 | R17: 润滑油 | S17: 项修 | T17: 生产水 | U17: 生活污水 | V17: 土工膜 | Y17: 队号 | Z17: 周期兑现 | AA17: 材料预算 | AB17: 小计 | AC17: 总计 | AD17: 增加材料考核项
B18: 1 | C18: 2025 | D18: 1月 | E18: 大港 | F18: 70520 | G18: ZJ70D | H18: 板111-28 | I18: 板桥 | J18: 开发井 | K18: 定向井 | L18: 2 | M18: 2925 | N18: ='[1]05工序定额'!$E$9+'[1]05工序定额'!$E$5+'[1]05工序定额'!$E$13+'[1]05工序定额'!$E$14 -> 0 | O18: ='[1]06米费定额 '!$E$5*M18*38 -> 47607.076 | P18: ='[1]07一般材料定额'!$F$5*M18 -> 62056.826 | Q18: ='[1]08能耗定额'!$G$5*M18 -> 286679.25 | R18: =M18*'[1]09润滑油定额 '!$E$5*'[1]14钻机挂钩系数'!$D$7 -> 21045.69 | S18: =M18*'[1]10项修定额'!$E$5*'[1]14钻机挂钩系数'!$E$7 -> 10951.205 | T18: =M18*'[1]11生产水定额'!$E$5 -> 13460.312 | U18: ='[1]12生活污水定额'!$E$5*M18 -> 7300.803 | V18: ='[1]13土工膜定额'!$G$6 -> 12546 | Y18: 70520 | Z18: =N18+O18 -> 47607.076 | AA18: =P18+Q18+R18+S18 -> 380732.97 | AB18: =Z18+AA18 -> 428340.05 | AC18: =Z18+AD18+AA18 -> 461647.16 | AD18: =T18+U18+V18 -> 33307.115
B19: 2 | C19: 2025 | D19: 3月 | E19: 大港 | F19: 70520 | G19: ZJ70D | H19: 板172X1 | I19: 板桥 | J19: 开发井 | K19: 定向井 | L19: 2 | M19: 2915 | N19: ='[1]05工序定额'!$E$9+'[1]05工序定额'!$E$5+'[1]05工序定额'!$E$13+'[1]05工序定额'!$E$14 -> 0 | O19: ='[1]06米费定额 '!$E$5*M19*38 -> 47444.317 | P19: ='[1]07一般材料定额'!$F$5*M19 -> 61844.666 | Q19: ='[1]08能耗定额'!$G$5*M19 -> 285699.15 | R19: =M19*'[1]09润滑油定额 '!$E$5*'[1]14钻机挂钩系数'!$D$7 -> 20973.739 | S19: =M19*'[1]10项修定额'!$E$5*'[1]14钻机挂钩系数'!$E$7 -> 10913.765 | T19: =M19*'[1]11生产水定额'!$E$5 -> 13414.293 | U19: ='[1]12生活污水定额'!$E$5*M19 -> 7275.843 | V19: ='[1]13土工膜定额'!$G$6 -> 12546 | Y19: 70520 | Z19: =N19+O19 -> 47444.317 | AA19: =P19+Q19+R19+S19 -> 379431.32 | AB19: =Z19+AA19 -> 426875.64 | AC19: =Z19+AD19+AA19 -> 460111.77 | AD19: =T19+U19+V19 -> 33236.136
B20: 3 | C20: 2025 | D20: 4月 | E20: 大港 | F20: 50537 | G20: ZJ50J | H20: 板61-37H | I20: 板桥 | J20: 开发井 | K20: 水平井 | L20: 3 | M20: 2382 | N20: ='[1]05工序定额'!$E$5+'[1]05工序定额'!$E$8+'[1]05工序定额'!$E$13 -> #VALUE! | O20: =M20*'[1]06米费定额 '!$E$33*38 -> 34687.033 | P20: =M20*'[1]07一般材料定额'!$E$33 -> 39895.833 | Q20: =M20*'[1]08能耗定额'!$G$25 -> 239581.56 | R20: ='[1]09润滑油定额 '!$E$33*M20*'[1]14钻机挂钩系数'!$D$5 -> 7682.3323 | S20: =M20*'[1]10项修定额'!$E$33*'[1]14钻机挂钩系数'!$E$5 -> 7181.25 | T20: =M20*'[1]11生产水定额'!$E$33 -> 10169.057 | U20: =M20*'[1]12生活污水定额'!$E$33 -> 5319.4444 | V20: ='[1]13土工膜定额'!$G$5 -> 11500.5 | Y20: 50537 | Z20: =N20+O20 -> #VALUE! | AA20: =P20+Q20+R20+S20 -> 294340.98 | AB20: =Z20+AA20 -> #VALUE! | AC20: =Z20+AD20+AA20 -> #VALUE! | AD20: =T20+U20+V20 -> 26989.002
B21: 4 | C21: 2025 | D21: 5月 | E21: 大港 | F21: 50537 | G21: ZJ50J | H21: 板180X1 | I21: 板桥 | J21: 评价井 | K21: 定向井 | L21: 2 | M21: 3523 | N21: ='[1]05工序定额'!$E$5+'[1]05工序定额'!$E$8+'[1]05工序定额'!$E$13 -> #VALUE! | O21: ='[1]06米费定额 '!$E$5*M21*38 -> 57340.079 | P21: ='[1]07一般材料定额'!$F$5*M21 -> 74743.999 | Q21: ='[1]08能耗定额'!$G$5*M21 -> 345289.23 | R21: =M21*'[1]09润滑油定额 '!$E$5*'[1]14钻机挂钩系数'!$D$5 -> 12699.43 | S21: =M21*'[1]10项修定额'!$E$5*'[1]14钻机挂钩系数'!$E$5 -> 11871.106 | T21: =M21*'[1]11生产水定额'!$E$5 -> 16212.198 | U21: ='[1]12生活污水定额'!$E$5*M21 -> 8793.4117 | V21: ='[1]13土工膜定额'!$G$5 -> 11500.5 | Y21: 50537 | Z21: =N21+O21 -> #VALUE! | AA21: =P21+Q21+R21+S21 -> 444603.76 | AB21: =Z21+AA21 -> #VALUE! | AC21: =Z21+AD21+AA21 -> #VALUE! | AD21: =T21+U21+V21 -> 36506.109
B22: 5 | C22: 2025 | D22: 5月 | E22: 大港 | F22: 50537 | G22: ZJ50J | H22: 板60-47H | I22: 板桥 | J22: 开发井 | K22: 水平井 | L22: 2 | M22: 2314 | N22: ='[1]05工序定额'!$E$5+'[1]05工序定额'!$E$8+'[1]05工序定额'!$E$13 -> #VALUE! | O22: =M22*38*'[1]06米费定额 '!$E$20 -> 30773.427 | P22: =M22*'[1]07一般材料定额'!$E$20 -> 35394.538 | Q22: =M22*'[1]08能耗定额'!$G$20 -> 189053.8 | R22: =M22*'[1]09润滑油定额 '!$E$20*'[1]14钻机挂钩系数'!$D$5 -> 6815.5639 | S22: =M22*'[1]10项修定额'!$E$20*'[1]14钻机挂钩系数'!$E$5 -> 6371.0168 | T22: =M22*'[1]11生产水定额'!$E$20 -> 10648.501 | U22: =M22*'[1]12生活污水定额'!$E$20 -> 4719.2717 | V22: ='[1]13土工膜定额'!$G$5 -> 11500.5 | Y22: 50537 | Z22: =N22+O22 -> #VALUE! | AA22: =P22+Q22+R22+S22 -> 237634.92 | AB22: =Z22+AA22 -> #VALUE! | AC22: =Z22+AD22+AA22 -> #VALUE! | AD22: =T22+U22+V22 -> 26868.273
B23: 6 | C23: 2025 | D23: 5月 | E23: 大港 | F23: 70520 | G23: ZJ70D | H23: 南港13-18 | I23: 唐东 | J23: 开发井 | K23: 定向井 | L23: 3 | M23: 4210 | N23: ='[1]05工序定额'!$E$9+'[1]05工序定额'!$E$5+'[1]05工序定额'!$E$13+'[1]05工序定额'!$E$14 -> 0 | O23: =M23*38*'[1]06米费定额 '!$E$31 -> 71738.09 | P23: =M23*'[1]07一般材料定额'!$F$31 -> 93512.109 | Q23: =M23*'[1]08能耗定额'!$G$31 -> 567802.7 | R23: =M23*'[1]09润滑油定额 '!$E$31*'[1]14钻机挂钩系数'!$E$7 -> 34654.488 | S23: =M23*'[1]10项修定额'!$E$31*'[1]14钻机挂钩系数'!$E$7 -> 16502.137 | T23: =M23*'[1]11生产水定额'!$E$31 -> 23301.793 | U23: =M23*'[1]12生活污水定额'!$E$31 -> 11001.425 | V23: ='[1]13土工膜定额'!$G$6 -> 12546 | Y23: 70520 | Z23: =N23+O23 -> 71738.09 | AA23: =P23+Q23+R23+S23 -> 712471.43 | AB23: =Z23+AA23 -> 784209.52 | AC23: =Z23+AD23+AA23 -> 831058.74 | AD23: =T23+U23+V23 -> 46849.218
B24: 7 | C24: 2025 | D24: 6月 | E24: 大港 | F24: 50537 | G24: ZJ50J | H24: 板61-36H | I24: 板桥 | J24: 开发井 | K24: 水平井 | L24: 2 | M24: 2850 | N24: ='[1]05工序定额'!$E$9+'[1]05工序定额'!$E$5+'[1]05工序定额'!$E$13+'[1]05工序定额'!$E$14 -> 0 | O24: =M24*38*'[1]06米费定额 '!$E$20 -> 37901.584 | P24: =M24*'[1]07一般材料定额'!$E$20 -> 43593.1 | Q24: =M24*'[1]08能耗定额'!$G$20 -> 232845 | R24: =M24*'[1]09润滑油定额 '!$E$20*'[1]14钻机挂钩系数'!$D$5 -> 8394.277 | S24: =M24*'[1]10项修定额'!$E$20*'[1]14钻机挂钩系数'!$E$5 -> 7846.7579 | T24: =M24*'[1]11生产水定额'!$E$20 -> 13115.051 | U24: =M24*'[1]12生活污水定额'!$E$20 -> 5812.4133 | V24: ='[1]13土工膜定额'!$G$5 -> 11500.5 | Y24: 50537 | Z24: =N24+O24 -> 37901.584 | AA24: =P24+Q24+R24+S24 -> 292679.13 | AB24: =Z24+AA24 -> 330580.72 | AC24: =Z24+AD24+AA24 -> 361008.68 | AD24: =T24+U24+V24 -> 30427.965
B25: 8 | C25: 2025 | D25: 7月 | E25: 大港 | F25: 50537 | G25: ZJ50J | H25: 板60-48H | I25: 板桥 | J25: 开发井 | K25: 水平井 | L25: 2 | M25: 2278 | N25: ='[1]05工序定额'!$E$5+'[1]05工序定额'!$E$8+'[1]05工序定额'!$E$13 -> #VALUE! | O25: =M25*38*'[1]06米费定额 '!$E$20 -> 30294.67 | P25: =M25*'[1]07一般材料定额'!$E$20 -> 34843.888 | Q25: =M25*'[1]08能耗定额'!$G$20 -> 186112.6 | R25: =M25*'[1]09润滑油定额 '!$E$20*'[1]14钻机挂钩系数'!$D$5 -> 6709.5309 | S25: =M25*'[1]10项修定额'!$E$20*'[1]14钻机挂钩系数'!$E$5 -> 6271.8998 | T25: =M25*'[1]11生产水定额'!$E$20 -> 10482.838 | U25: =M25*'[1]12生活污水定额'!$E$20 -> 4645.8517 | V25: ='[1]13土工膜定额'!$G$5 -> 11500.5 | Y25: 50537 | Z25: =N25+O25 -> #VALUE! | AA25: =P25+Q25+R25+S25 -> 233937.92 | AB25: =Z25+AA25 -> #VALUE! | AC25: =Z25+AD25+AA25 -> #VALUE! | AD25: =T25+U25+V25 -> 26629.189
B26: 9 | C26: 2025 | D26: 7月 | E26: 大港 | F26: 70520 | G26: ZJ70D | H26: 唐东9X9 | I26: 唐东 | J26: 评价井 | K26: 定向井 | L26: 3 | M26: 3945 | N26: ='[1]05工序定额'!$E$9+'[1]05工序定额'!$E$5+'[1]05工序定额'!$E$13+'[1]05工序定额'!$E$14 -> 0 | O26: =M26*38*'[1]06米费定额 '!$E$31 -> 67222.509 | P26: =M26*'[1]07一般材料定额'!$F$31 -> 87625.955 | Q26: =M26*'[1]08能耗定额'!$G$31 -> 532062.15 | R26: =M26*'[1]09润滑油定额 '!$E$31*'[1]14钻机挂钩系数'!$E$7 -> 32473.148 | S26: =M26*'[1]10项修定额'!$E$31*'[1]14钻机挂钩系数'!$E$7 -> 15463.404 | T26: =M26*'[1]11生产水定额'!$E$31 -> 21835.053 | U26: =M26*'[1]12生活污水定额'!$E$31 -> 10308.936 | V26: ='[1]13土工膜定额'!$G$6 -> 12546 | Y26: 70520 | Z26: =N26+O26 -> 67222.509 | AA26: =P26+Q26+R26+S26 -> 667624.66 | AB26: =Z26+AA26 -> 734847.17 | AC26: =Z26+AD26+AA26 -> 779537.16 | AD26: =T26+U26+V26 -> 44689.989
B27: 10 | C27: 2025 | D27: 10月 | E27: 大港 | F27: 70520 | G27: ZJ70D | H27: 唐东20X5 | I27: 唐东 | J27: 评价井 | K27: 定向井 | L27: 3 | M27: 5580 | N27: ='[1]05工序定额'!$E$9+'[1]05工序定额'!$E$5+'[1]05工序定额'!$E$13+'[1]05工序定额'!$E$14 -> 0 | O27: =M27*38*'[1]06米费定额 '!$E$31 -> 95082.789 | P27: =M27*'[1]07一般材料定额'!$F$31 -> 123942.42 | Q27: =M27*'[1]08能耗定额'!$G$31 -> 752574.6 | R27: =M27*'[1]09润滑油定额 '!$E$31*'[1]14钻机挂钩系数'!$E$7 -> 45931.601 | S27: =M27*'[1]10项修定额'!$E$31*'[1]14钻机挂钩系数'!$E$7 -> 21872.191 | T27: =M27*'[1]11生产水定额'!$E$31 -> 30884.562 | U27: =M27*'[1]12生活污水定额'!$E$31 -> 14581.461 | V27: ='[1]13土工膜定额'!$G$6 -> 12546 | Y27: 70520 | Z27: =N27+O27 -> 95082.789 | AA27: =P27+Q27+R27+S27 -> 944320.81 | AB27: =Z27+AA27 -> 1039403.6 | AC27: =Z27+AD27+AA27 -> 1097415.6 | AD27: =T27+U27+V27 -> 58012.022
AA28: =SUM(AA18:AA27) -> 4587777.9 | AD28: =SUM(AD18:AD27) -> 363515.02 | AH28: =(AD28+AA28-AA14)/AA14 -> 0.16019568
Y30: 与原政策对比
H31: 张海31-43 | Q31: =4318*'[1]08能耗定额'!$G$26 -> 625721.38 | Y31: 队号 | Z31: 周期兑现差额 | AA31: 材料考核项差额 | AB31: 总体考核差额
Y32: 70520 | Z32: =Z18-Z4 -> -40112.924 | AA32: =AA18+AD18-AA4 -> 56432.33 | AB32: =AC18-AB4 -> 16319.406
Y33: 70520 | Z33: =Z19-Z5 -> -41995.683 | AA33: =AA19+AD19-AA5 -> 10615.21 | AB33: =AC19-AB5 -> -31380.473
Y34: 50537 | Z34: =Z20-Z6 -> #VALUE! | AA34: =AA20+AD20-AA6 -> 75704.333 | AB34: =AC20-AB6 -> #VALUE!
Y35: 50537 | Z35: =Z21-Z7 -> #VALUE! | AA35: =AA21+AD21-AA7 -> 49281.127 | AB35: =AC21-AB7 -> #VALUE!
Y36: 50537 | Z36: =Z22-Z8 -> #VALUE! | AA36: =AA22+AD22-AA8 -> -357.10823 | AB36: =AC22-AB8 -> #VALUE!
Y37: 70520 | Z37: =Z23-Z9 -> -71021.91 | AA37: =AA23+AD23-AA9 -> -34500.722 | AB37: =AC23-AB9 -> -105522.63
Y38: 50537 | Z38: =Z24-Z10 -> -32618.416 | AA38: =AA24+AD24-AA10 -> 43834.06 | AB38: =AC24-AB10 -> 11215.645
Y39: 50537 | Z39: =Z25-Z11 -> #VALUE! | AA39: =AA25+AD25-AA11 -> 32101.235 | AB39: =AC25-AB11 -> #VALUE!
Y40: 70520 | Z40: =Z26-Z12 -> -41137.491 | AA40: =AA26+AD26-AA12 -> 192135.55 | AB40: =AC26-AB12 -> 150998.06
Y41: 70520 | Z41: =Z27-Z13 -> -49397.211 | AA41: =AA27+AD27-AA13 -> 258410.83 | AB41: =AC27-AB13 -> 209013.62
Y45: 全年差额
Y46: 70520 | Z46: =Z32+Z33+Z37+Z40+Z41 -> -243665.22 | AA46: =AA32+AA33+AA37+AA40+AA41 -> 483093.2 | AB46: =AB32+AB33+AB37+AB40+AB41 -> 239427.98
Y47: =Y34 -> 50537 | Z47: =Z34+Z35+Z36+Z38+Z39 -> #VALUE! | AA47: =AA34+AA35+AA36+AA38+AA39 -> 200563.65 | AB47: =AB34+AB35+AB36+AB38+AB39 -> #VALUE!

Sheet 目录
A1: 附件1
A3: 目录
A4: 序号 | B4: 名称
A5: 1 | B5: 奖金系数表
A6: 2 | B6: 人员定额
A7: 3 | B7: 机关部门、直属单位通用管理指标考核表
A8: 4 | B8: 机关部门、直属单位专业管理指标考核表
A9: 5 | B9: 大港油区工序定额
A10: 6 | B10: 大港油区米费定额
A11: 7 | B11: 大港油区一般材料定额
A12: 8 | B12: 大港油区能耗定额
A13: 9 | B13: 大港油区润滑油定额
A14: 10 | B14: 大港油区项修定额
A15: 11 | B15: 大港油区生产水定额
A16: 12 | B16: 大港油区生活污水定额
... A21: 17 | B21: 事故复杂率指标

Sheet 1奖金系数表
A1: 附件1-1
A3: 切块奖金系数表
A4: 部门或单位 | B4: 岗位名称 | C4: 系数
A5: 机关直属 | B5: 室内管理岗 | C5: 1.1
B6: 现场管理岗 | C6: 1.2
B7: 盯井工程师 | C7: 2 | D7: 凌云按盯井工程师系数2.0造
A8: 安全监督中心 | B8: 油区现场监督 | C8: 1.3
B9: 外部、外包现场监督 | C9: 1.5
A10: 生产保障中心 | B10: 档案管理 | C10: 1.1
B11: 班长、电工、司机、调度、安全员 | C11: 0.9
B12: 办事员、会务、打字员、食堂 | C12: 0.75
B13: 门岗 | C13: 0.65
B14: 清洁班、护厂、活动中心 | C14: 0.6
B15: 技术员、班长 | C15: 1
B16: 搬迁工、修理工、安全员 | C16: 0.9
B17: 办事员 | C17: 0.75
A18: 物资管理中心 | B18: 班长 | C18: 1
B19: 押运员、送料员、稽核员、安全员 | C19: 0.9
B20: 保管员 | C20: 0.8
A21: 外部项目部 | B21: 项目部管理人员 | C21: 1.6 | D21: 周雪峰、刘金文的系数1.4是否改，南部机构撤销
A22: 国际项目部/新项目管理部 | B22: 新项目部管理人员 | C22: 1.4 | D22: 2.13日修改为1.6系数
A23: 钻井队 | B23: 大港油区钻井队 | C23: 2.2
B24: 外部市场钻井队 | C24: 2.5
A25: 注：项目部驻公司机关办公人员奖金系数参照机关直属标准执行。
A27: 钻井队管理岗位奖金系数表
A28: 部门或单位 | B28: 岗位名称 | C28: 系数
A29: 钻井队 | B29: 队长（平台经理） | C29: 1.6
B30: 党支部书记、第一技术员 | C30: 1.4
B31: 副队长、第二技术员、司钻 | C31: 1.2
B32: 实习技术员 | C32: 0.9
A33: 注：该系数为指导性系数。司钻、实习技术员参照管理岗设置奖金系数。
A35: 钻井队操作岗位奖金系数表
A36: 部门或单位 | B36: 岗位名称 | C36: 系数
A37: 钻井队 | B37: 司钻 | C37: 1.5
B38: 机房大班、钻台大班、电气师、副司钻 | C38: 1.3
B39: 钻工、泥浆工、司机 | C39: 1.2
B40: 机工、发电工、炊事员、成本员、材料员、管理员 | C40: 1.1
A41: 注：该系数为指导性系数。

Sheet 2人员定额
A1: 附件1-2
A3: 人员定额
A4: 序号 | B4: 主体单位 | C4: 所属地区 | D4: 钻井队定员（人/队） | E4: 项目部定编（人）
A6: 1 | B6: 大港油区项目 | C6: 天津、河北等 | D6: 38 | E6: /
A7: 2 | B7: 西北项目 | C7: 南疆 | D7: 44 | E7: 88
C8: 北疆 | D8: 38
A9: 3 | B9: 长庆项目 | C9: 陕西、甘肃、内蒙等 | D9: 38 | E9: 73
A10: 注：动力外包、食堂外包队伍减少定员3人/队。

Sheet 3机关部门、直属单位通用管理指标考核表
A1: 附件1-3
A3: 机关部门、直属单位通用管理指标考核表
A4: 序号 | B4: 单位 | C4: 人数 | D4: 办公费（元/年） | E4: 车辆使用(台班/年) | F4: 备注
A5: 1 | B5: 办公室/党委办公室 | C5: 9 | D5: 3300 | E5: 31 | F5: 直属管理岗4人
A6: 2 | B6: 市场与生产协调部 | C6: 23 | D6: 7400 | E6: 911 | F6: 室内3人、室外8人
A7: 3 | B7: 工程技术部 | C7: 17 | D7: 5200 | E7: 444 | F7: 直属管理岗6人、EISC岗5人
A8: 4 | B8: 质量安全环保部 | C8: 21 | D8: 6190 | E8: 600 | F8: 室外5人、视频监控3人、门卫3人
A9: 5 | B9: 装备管理部 | C9: 9 | D9: 3300 | E9: 741 | F9: 室外3人
A10: 6 | B10: 人力资源部/党委组织部 | C10: 12 | D10: 6000 | E10: 107 | F10: 含人力资源共享中心6人
A11: 7 | B11: 企划财务部 | C11: 20 | D11: 10000 | E11: 82
A12: 8 | B12: 党群工作部/纪委办公室 | C12: 15 | D12: 6560 | E12: 134 | F12: 门卫2人
A13: 9 | B13: 物资管理中心 | C13: 26 | D13: 3820 | E13: 317 | F13: 管理岗9人、长期室内13人、押运4人
A14: 10 | B14: 安全监督中心 | C14: 22 | D14: 2570 | E14: 286 | F14: 管理岗4人、监督18人
A15: 11 | B15: 井控监督中心 | C15: 6 | D15: 1800 | E15: 0 | F15: 用车与工程技术科合并考核
A16: 12 | B16: 数智中心 | C16: 5 | D16: 2500 | E16: 20
A17: 13 | B17: 生产保障中心 | C17: 112 | D17: 75700 | E17: 335 | F17: 管理岗6人、室内6人，含公共实施消耗7万元
A18: 合 计 | C18: =SUM(C5:C17) -> 297 | D18: =SUM(D5:D17) -> 134340 | E18: =SUM(E5:E17) -> 4008
A19: 备注： 1．车辆使用每节余（超支）1台班奖励（扣减）科室80元；办公费按照节余（超支）额的50%进行奖励（扣减）。 2．机关部门使用车辆按台班签字；当日使用车辆8小时及以上，按1台班计算。多部门拼车出行，该车辆使用时间由用车部门分摊，计入考核指标。 3．办公费指标核定标准：机关部门人员核定标准为500元/人，长期室外工作人员100元/人；直属单位管理岗200元/人，办事员及长期室内工作人员100元/人，其他岗位人员按30元/人，安全监督65元/人。

Sheet 4机关部门、直属单位专业管理指标考核细则
A1: 附件1-4
A3: 机关部门、直属单位专业管理指标考核表
A4: 部门(单位) | B4: 承包管理指标项目名称 | C4: 计量单位 | D4: 承包管理指标 | E4: 考核方式 | F4: 考核办法
A6: 通用指标 | B6: 部门原因造成钻井队施工异常 | C6: 次 | D6: 0 | E6: 季度 | F6: 季度考核，每发生一次，核减责任部门10%月奖。
B7: 渤海钻探公司及相关处室下达的考核指标 | C7: 项 | D7: 0 | E7: 月度 | F7: 对公司相关职责承担部门（单位）进行考核，进度未完成核减业务牵头部门（单位）20%月奖、业务配合部门（单位）10%月奖；年度未完成考核指标累计核减业务牵头部门(单位）月度100%月奖、业务配合部门（单位）月度50%月奖。
B8: 生产经营过程管理考核 | E8: 月度 | F8: 在各级检查、审核中发现专业路管理问题或单位履职未尽责造成上级通报批评影响公司声誉的，每起核减责任单位10%月奖。
B9: 预提费用考核 | C9: % | E9: 月度 | F9: 考核变动成本月度预提费用准确性，考核结果与业务经办部门（含项目部)及机关归口部门负责人挂钩，费用偏差≤5%合格，5%＜费用偏差≤10%，沉没月奖10%；10%＜费用偏差≤15%，沉没月奖20%；费用偏差＞15%，沉没月奖30%。
B10: 荣誉奖励 | E10: 季度 | F10: 获得国家级、省部级集体荣誉，核增获奖集体人均绩效薪酬不超过1200元、800元，生产类核增加倍。上级有核增绩效薪酬的不重复。
A11: 市场与生产协调部 | B11: 大港油区搬安周期考核 | C11: % | E11: 季度 | F11: 按季度完成井进行考核，实际平均口井搬安天数同比去年缩短10%，核增绩效薪酬15000元；同比缩短15%，核增绩效薪酬20000元；超过去年平均口井搬安天数，核减10000元。
B12: 网电接入口井数和接入及时率 | C12: 次 | E12: 口井 | F12: 新搬迁井位的钻井队，在开钻前接入并使用网电的，口井核增绩效薪酬2000元。二开前完成核增绩效薪酬1000元。
B13: 公司进尺任务 | C13: 万米 | E13: 月度 | F13: 月度完成核增绩效薪酬5000元，未完成核减绩效薪酬2500元。
B14: 大港油区进尺任务 | C14: 万米 | E14: 月度 | F14: 月度完成核增绩效薪酬10000元，未完成核减绩效薪酬10000元。每增加（减少）1米，核增（核减）绩效薪酬1元。
B15: 公司创收任务 | C15: 亿元 | E15: 季度/年度 | F15: 季度完成核增绩效薪酬10000元，未完成核减绩效薪酬5000元；全年完成核增绩效薪酬20000元，未完成核减绩效薪酬10000元。
B16: 大港油区创收任务 | C16: 亿元 | E16: 季度/年度 | F16: 季度完成核增绩效薪酬20000元，未完成核减绩效薪酬20000元；年度完成核增绩效薪酬20000元，未完成核减绩效薪酬20000元。年度超额完成指标占比每1%核增绩效薪酬30000元。未达标准每1%核减绩效薪酬30000元。
A17: 工程技术部、井控监督中心 | B17: 公司整体提速（钻完井周期） | C17: % | E17: 半年/年度 | F17: 半年完成核增绩效薪酬20000元，未完成核减绩效薪酬10000元；全年完成核增绩效薪酬30000元；全年未完成核减绩效薪酬15000元。
B18: 大港油区五类井提速（钻井周期） | C18: % | E18: 季度/年度 | F18: 季度完成核增绩效薪酬20000元，未完成核减绩效薪酬10000元；年度完成核增绩效薪酬30000元，未完成核减绩效薪酬15000元。
B19: 大港油区提速工具考核 | C19: 天 | E19: 口井 | F19: 每口井考核提速工具提速目标，达到预期目标核增绩效薪酬3000元，未达到核减绩效薪酬1500元。
B20: 公司事故复杂考核 | C20: % | E20: 半年/年度 | F20: 半年完成核增绩效薪酬20000元，未完成核减绩效薪酬10000元；全年完成任务核增绩效薪酬40000元，未完成核减绩效薪酬20000元。
B21: 大港油区事故复杂考核 | C21: % | E21: 季度/年度 | F21: 季度完成核增绩效薪酬20000元，未完成核减绩效薪酬10000元；第四季度按年度考核，完成任务核增绩效薪酬40000元，未完成核减绩效薪酬20000元。
B22: 大港油区钻头米费考核 | C22: 元/米 | D22: 2025年平均值 | E22: 季度 | F22: 季度完成核增绩效薪酬10000元，未完成核减绩效薪酬5000元。钻头米费标准与平均井深同比例增减。
B23: 施工质量控制 | E23: 月度/年度 | F23: 发生井口未正常交井事件每起核减绩效薪酬3000元。年度固井质量优质率高于同市场水平核增绩效薪酬30000元。低于平均值核减绩效薪酬15000元。
A24: 质量安全环保部 | B24: 公司安全事故 | C24: 起 | D24: 0 | E24: 月度 | F24: 一般C级及以上安全事故，每发生1起核减10%绩效薪酬，部门负责人加倍。
B25: “四不两直”及体系审核 | E25: 季度 | F25: 在上级“四不两直”或体系审核中得到上级通报表扬的每次核增绩效薪酬20000元，发生严重违反上级禁令造成恶劣影响的，每次核减绩效薪酬10000元。
B26: 质量控制 | E26: 月度 | F26: 完成上级下达的质量工作目标。每发生一起质量事件核减绩效薪酬3000元。
B27: 年度HSE指标完成情况 | E27: 年度 | F27: 全年完成HSE指标，现场人员收入不低于市场、生产、装备现场管理人员平均收入水平。
A28: 装备管理部 | B28: 网电接入口井数和接入及时率 | C28: 次 | E28: 口井 | F28: 新搬迁井位的钻井队，在开钻前接入并使用网电的，口井核增绩效薪酬2000元。二开前完成核增绩效薪酬1000元。
B29: 机修率 | C29: % | D29: 0.8 | E29: 季度 | F29: 按当月施工井时效进行统计，机修率每低于考核指标0.1个点，核增绩效薪酬500元，每超出0.1点，核减绩效薪酬500元。考核结果与钻机利用率挂钩：钻机利用率≥80%，按全额考核兑现；当钻机利用率＜80%，按考核金额×（实际钻机利用率÷0.8)兑现。
B30: 大港油区设备保障 | C30: 次 | D30: 3 | E30: 季度 | F30: 生产过程中发生设备影响生产的情况每超出一起核减绩效薪酬1000元；在各类检查中发现设备不能正常运转而影响生产核减绩效薪酬2000元/起；发生因设备原因造成的事故复杂核减绩效薪酬10000元；季度未发生核增绩效薪酬10000元。
A31: 物资管理中心 | B31: 完成井一般材料消耗节余 | C31: % | D31: 1.5 | E31: 季度 | F31: 与单井一般材料定额相比，节余1.5%以上，按超额节余金额的2%核增绩效薪酬，节余不足部分按照2%核减绩效薪酬。
B32: 现场物资质量管控 | C32: 起 | D32: 0 | E32: 季度 | F32: 因物资质量问题影响生产，每发生1起核减绩效薪酬1000元。
B33: 物资运费 | C33: 车次/台月 | D33: 2 | E33: 季度 | F33: 每节约1车次核增绩效薪酬400元,增加1车次核减绩效薪酬200元。
A34: 生产保障中心 | B34: 单井电料消耗 | C34: 元 | D34: 4000 | E34: 季度 | F34: 按照季度完成井节超额10%核增（核减）绩效薪酬。
B35: 修理加工产值 | C35: 万元 | D35: 415 | E35: 季度 | F35: 按超（差）额5%核增（核减）绩效薪酬。设备修理、加工按市场价计算产值。
B36: 部门用车情况 | C36: 台班 | D36: 各部门 | E36: 年度 | F36: 根据各单位考核结果，完成考核指标核增绩效薪酬总额20%进行核增，未完成考核指标核减绩效薪酬总额20%进行核减。
B37: 增效工时考核 | C37: 天/人 | D37: 50 | E37: 季度 | F37: 鼓励搬迁队、水电队主动支援一线工作，按工时超（差）额进行核增（核减）绩效薪酬100元/天。

Sheet 5工序定额
A1: 附件1-5
A3: 大港油区工序定额
A4: 序号 | B4: 工序 | C4: 单位 | D4: 定额 | E4: 备注
A5: 1 | B5: 搬迁拆卸 | C5: 元/井次 | D5: 7245.3333
A6: 2 | B6: 平移拆卸 | C6: 元/井次 | D6: 1811.3333
A7: 3 | B7: 搬迁转场(腾井场） | C7: 元/井次 | D7: 3622.6667
A8: 4 | B8: 搬安（50型） | C8: 元/井次 | D8: 16302 | E8: 冬季上浮20%
A9: 5 | B9: 搬安（70型） | C9: 元/井次 | D9: 21736 | E9: 冬季上浮20%
A10: 6 | B10: 平移 | C10: 元/井次 | D10: 3622.6667
A11: 7 | B11: 砌方井 | C11: 元/井次 | D11: 1811.3333
A12: 8 | B12: 摆基础 | C12: 元/井次 | D12: 1811.3333
A13: 9 | B13: 配合安装泥浆不落地 | C13: 元/井次 | D13: 1811.3333
A14: 10 | B14: 顶驱拆装 | C14: 元/井次 | D14: 5434
A15: 11 | B15: 机械手拆装 | C15: 元/井次 | D15: 5434
A16: 12 | B16: 冬防保温（自保温） | C16: 元/井次 | D16: 3622.6667
A17: 13 | B17: 油基泥浆施工 | C17: 元/台月 | D17: 6000
A18: 14 | B18: 设备配套 | C18: 元/天·人 | D18: 104.86667

Sheet 大港油区定额统计
A1: 大港油区定额测算基础数据
A3: 序号 | B3: 井型 | C3: 区块 | D3: 开次 | E3: 累计进尺 | F3: 定员人数 | G3: 累计钻完井周期 | H3: 累计米费兑现 | I3: 一般材料累计 | J3: 能耗累计 | K3: 润滑油累计 | L3: 项修累计 | M3: 生产水累计 | N3: 生活污水累计 | O3: 累计贡献毛益额 | P3: 累计收入
A4: =ROW()-3 -> 1 | B4: 定向井 | C4: 板桥（＜2500米） | D4: 2 | E4: =SUMIFS(转置表!O:O,转置表!L:L,B4,转置表!J:J,C4,转置表!M:M,D4) -> 3957 | F4: 38 | G4: =SUMIFS(转置表!T:T,转置表!L:L,B4,转置表!J:J,C4,转置表!M:M,D4) -> 25 | H4: 54340 | I4: 56666.667 | J4: 323056.18 | K4: 17500 | L4: 8333.3333 | M4: 0 | N4: 8333.3333
A5: =ROW()-3 -> 2 | B5: 定向井 | C5: 板桥（＜3500米） | D5: 2 | E5: =SUMIFS(转置表!O:O,转置表!L:L,B5,转置表!J:J,C5,转置表!M:M,D5) -> 44234 | F5: 38 | G5: =SUMIFS(转置表!T:T,转置表!L:L,B5,转置表!J:J,C5,转置表!M:M,D5) -> 264.85417 | H5: 575687.02 | I5: 600336.11 | J5: 3279717.3 | K5: 185397.92 | L5: 88284.722 | M5: 155838.94 | N5: 88284.722 | O5: 3244615.8 | P5: 59347750
A6: =ROW()-3 -> 3 | B6: 定向井 | C6: 板桥（≥3500米） | D6: 2 | E6: =SUMIFS(转置表!O:O,转置表!L:L,B6,转置表!J:J,C6,转置表!M:M,D6) -> 21858 | F6: 38 | G6: =SUMIFS(转置表!T:T,转置表!L:L,B6,转置表!J:J,C6,转置表!M:M,D6) -> 182.66667 | H6: 397044.27 | I6: 414044.44 | J6: 2111417.2 | K6: 127866.67 | L6: 60888.889 | M6: 100586.49 | N6: 60888.889 | O6: 3090663.8 | P6: 37340293
A7: =ROW()-3 -> 4 | B7: 定向井 | C7: 港东 | D7: 2 | E7: =SUMIFS(转置表!O:O,转置表!L:L,B7,转置表!J:J,C7,转置表!M:M,D7) -> 3835 | F7: 38 | G7: =SUMIFS(转置表!T:T,转置表!L:L,B7,转置表!J:J,C7,转置表!M:M,D7) -> 20.104167 | H7: 43698.417 | I7: 45569.444 | J7: 177165.49 | K7: 14072.917 | L7: 6701.3889 | M7: 15207.5 | N7: 6701.3889
A8: =ROW()-3 -> 5 | B8: 定向井 | C8: 港西 | D8: 2 | E8: =SUMIFS(转置表!O:O,转置表!L:L,B8,转置表!J:J,C8,转置表!M:M,D8) -> 12133 | F8: 38 | G8: =SUMIFS(转置表!T:T,转置表!L:L,B8,转置表!J:J,C8,转置表!M:M,D8) -> 93 | H8: 202144.8 | I8: 210800 | J8: 788764.04 | K8: 65100 | L8: 31000 | M8: 53404 | N8: 31000 | O8: 2453789.6 | P8: 23277479
A9: =ROW()-3 -> 6 | B9: 定向井 | C9: 港中 | D9: 2 | E9: =SUMIFS(转置表!O:O,转置表!L:L,B9,转置表!J:J,C9,转置表!M:M,D9) -> 5497 | F9: 38 | G9: =SUMIFS(转置表!T:T,转置表!L:L,B9,转置表!J:J,C9,转置表!M:M,D9) -> 37 | H9: 80423.2 | I9: 83866.667 | J9: 350561.8 | K9: 25900 | L9: 12333.333 | M9: 19671 | N9: 12333.333
A10: =ROW()-3 -> 7 | B10: 定向井 | C10: 孔店 | D10: 2 | E10: =SUMIFS(转置表!O:O,转置表!L:L,B10,转置表!J:J,C10,转置表!M:M,D10) -> 3444 | F10: 38 | G10: =SUMIFS(转置表!T:T,转置表!L:L,B10,转置表!J:J,C10,转置表!M:M,D10) -> 30.8125 | H10: 66974.05 | I10: 69841.667 | J10: 118752.48 | K10: 21568.75 | L10: 10270.833 | M10: 0 | N10: 10270.833
A11: =ROW()-3 -> 8 | B11: 定向井 | C11: 扣村 | D11: 2 | E11: =SUMIFS(转置表!O:O,转置表!L:L,B11,转置表!J:J,C11,转置表!M:M,D11) -> 2492 | F11: 38 | G11: =SUMIFS(转置表!T:T,转置表!L:L,B11,转置表!J:J,C11,转置表!M:M,D11) -> 12 | H11: 26083.2 | I11: 27200 | J11: 125013.67 | K11: 8400 | L11: 4000 | M11: 0 | N11: 4000
A12: =ROW()-3 -> 9 | B12: 定向井 | C12: 唐家河 | D12: 2 | E12: =SUMIFS(转置表!O:O,转置表!L:L,B12,转置表!J:J,C12,转置表!M:M,D12) -> 3321 | F12: 38 | G12: =SUMIFS(转置表!T:T,转置表!L:L,B12,转置表!J:J,C12,转置表!M:M,D12) -> 20.416667 | H12: 44377.667 | I12: 46277.778 | J12: 178584.27 | K12: 14291.667 | L12: 6805.5556 | M12: 13390.5 | N12: 6805.5556
A13: =ROW()-3 -> 10 | B13: 定向井 | C13: 王官屯 | D13: 2 | E13: =SUMIFS(转置表!O:O,转置表!L:L,B13,转置表!J:J,C13,转置表!M:M,D13) -> 16455 | F13: 38 | G13: =SUMIFS(转置表!T:T,转置表!L:L,B13,转置表!J:J,C13,转置表!M:M,D13) -> 142.58333 | H13: 309919.13 | I13: 323188.89 | J13: 991491.19 | K13: 99808.333 | L13: 47527.778 | M13: 0 | N13: 47527.778 | O13: 4627576.6 | P13: 30068132
A14: =ROW()-3 -> 11 | B14: 定向井 | C14: 王徐庄 | D14: 2 | E14: =SUMIFS(转置表!O:O,转置表!L:L,B14,转置表!J:J,C14,转置表!M:M,D14) -> 2468 | F14: 38 | G14: =SUMIFS(转置表!T:T,转置表!L:L,B14,转置表!J:J,C14,转置表!M:M,D14) -> 16 | H14: 34777.6 | I14: 36266.667 | J14: 195776.57 | K14: 11200 | L14: 5333.3333 | M14: 0 | N14: 5333.3333
A15: =ROW()-3 -> 12 | B15: 定向井 | C15: 新华 | D15: 2 | E15: =SUMIFS(转置表!O:O,转置表!L:L,B15,转置表!J:J,C15,转置表!M:M,D15) -> 9956 | F15: 38 | G15: =SUMIFS(转置表!T:T,转置表!L:L,B15,转置表!J:J,C15,转置表!M:M,D15) -> 72.791667 | H15: 158219.97 | I15: 164994.44 | J15: 1080171.9 | K15: 50954.167 | L15: 24263.889 | M15: 0 | N15: 24263.889
A16: =ROW()-3 -> 13 | B16: 定向井 | C16: 羊二庄 | D16: 2 | E16: =SUMIFS(转置表!O:O,转置表!L:L,B16,转置表!J:J,C16,转置表!M:M,D16) -> 4402 | F16: 38 | G16: =SUMIFS(转置表!T:T,转置表!L:L,B16,转置表!J:J,C16,转置表!M:M,D16) -> 22 | H16: 47819.2 | I16: 49866.667 | J16: 219681.81 | K16: 15400 | L16: 7333.3333 | M16: 0 | N16: 7333.3333
A17: =ROW()-3 -> 14 | B17: 定向井 | C17: 羊三木 | D17: 2 | E17: =SUMIFS(转置表!O:O,转置表!L:L,B17,转置表!J:J,C17,转置表!M:M,D17) -> 2775 | F17: 38 | G17: =SUMIFS(转置表!T:T,转置表!L:L,B17,转置表!J:J,C17,转置表!M:M,D17) -> 21 | H17: 45645.6 | I17: 47600 | J17: 229345.42 | K17: 14700 | L17: 7000 | M17: 0 | N17: 7000
A18: =ROW()-3 -> 15 | B18: 定向井 | C18: 枣园 | D18: 2 | E18: =SUMIFS(转置表!O:O,转置表!L:L,B18,转置表!J:J,C18,转置表!M:M,D18) -> 10593 | F18: 38 | G18: =SUMIFS(转置表!T:T,转置表!L:L,B18,转置表!J:J,C18,转置表!M:M,D18) -> 71 | H18: 154325.6 | I18: 160933.33 | J18: 887015.45 | K18: 49700 | L18: 23666.667 | M18: 0 | N18: 23666.667 | O18: 1578394.2 | P18: 17030646
A19: =ROW()-3 -> 16 | B19: 水平井 | C19: 板桥 | D19: 2 | E19: =SUMIFS(转置表!O:O,转置表!L:L,B19,转置表!J:J,C19,转置表!M:M,D19) -> 19739 | F19: 38 | G19: =SUMIFS(转置表!T:T,转置表!L:L,B19,转置表!J:J,C19,转置表!M:M,D19) -> 123.8125 | H19: 269118.85 | I19: 280641.67 | J19: 1276260.2 | K19: 86668.75 | L19: 41270.833 | M19: 79872.964 | N19: 41270.833 | O19: 5696073 | P19: 34064343
A20: =ROW()-3 -> 17 | B20: 水平井 | C20: 埕海 | D20: 2 | E20: =SUMIFS(转置表!O:O,转置表!L:L,B20,转置表!J:J,C20,转置表!M:M,D20) -> 4804 | F20: 38 | G20: =SUMIFS(转置表!T:T,转置表!L:L,B20,转置表!J:J,C20,转置表!M:M,D20) -> 38.916667 | H20: 84589.267 | I20: 88211.111 | J20: 604309.57 | K20: 27241.667 | L20: 12972.222 | M20: 0 | N20: 12972.222
A21: =ROW()-3 -> 18 | B21: 水平井 | C21: 大港页岩油 | D21: 2 | E21: =SUMIFS(转置表!O:O,转置表!L:L,B21,转置表!J:J,C21,转置表!M:M,D21) -> 18574 | F21: 38 | G21: =SUMIFS(转置表!T:T,转置表!L:L,B21,转置表!J:J,C21,转置表!M:M,D21) -> 100.52431 | H21: 218499.63 | I21: 227855.09 | J21: 1862764.2 | K21: 70367.014 | L21: 33508.102 | M21: 0 | N21: 33508.102 | O21: -1830656.7 | P21: 29004677
A22: =ROW()-3 -> 19 | B22: 水平井 | C22: 枣园 | D22: 2 | E22: =SUMIFS(转置表!O:O,转置表!L:L,B22,转置表!J:J,C22,转置表!M:M,D22) -> 8000 | F22: 38 | G22: =SUMIFS(转置表!T:T,转置表!L:L,B22,转置表!J:J,C22,转置表!M:M,D22) -> 83.125 | H22: 180680.5 | I22: 188416.67 | J22: 705888 | K22: 58187.5 | L22: 27708.333 | M22: 0 | N22: 27708.333
A23: =ROW()-3 -> 20 | B23: 定向井 | C23: 板桥 | D23: 3 | E23: =SUMIFS(转置表!O:O,转置表!L:L,B23,转置表!J:J,C23,转置表!M:M,D23) -> 18653 | F23: 38 | G23: =SUMIFS(转置表!T:T,转置表!L:L,B23,转置表!J:J,C23,转置表!M:M,D23) -> 147 | H23: 319519.2 | I23: 313600 | J23: 1688506.9 | K23: 102900 | L23: 49000 | M23: 79632 | N23: 49000 | O23: 4595113.9 | P23: 45996967
A24: =ROW()-3 -> 21 | B24: 定向井 | C24: 埕海（＜4000米） | D24: 3 | E24: =SUMIFS(转置表!O:O,转置表!L:L,B24,转置表!J:J,C24,转置表!M:M,D24) -> 7594 | F24: 40 | G24: =SUMIFS(转置表!T:T,转置表!L:L,B24,转置表!J:J,C24,转置表!M:M,D24) -> 42.9375 | H24: 93328.95 | I24: 91600 | J24: 715973 | K24: 30056.25 | L24: 14312.5 | M24: 0 | N24: 14312.5 | O24: 6280277.6 | P24: 18857453
A25: =ROW()-3 -> 22 | B25: 定向井 | C25: 埕海（≥4000米） | D25: 3 | E25: =SUMIFS(转置表!O:O,转置表!L:L,B25,转置表!J:J,C25,转置表!M:M,D25) -> 23072 | F25: 40 | G25: =SUMIFS(转置表!T:T,转置表!L:L,B25,转置表!J:J,C25,转置表!M:M,D25) -> 153.79167 | H25: 334281.57 | I25: 328088.89 | J25: 2645276 | K25: 107654.17 | L25: 51263.889 | M25: 0 | N25: 51263.889 | O25: 34209204 | P25: 80955952
A26: =ROW()-3 -> 23 | B26: 定向井 | C26: 大港页岩油 | D26: 3 | E26: =SUMIFS(转置表!O:O,转置表!L:L,B26,转置表!J:J,C26,转置表!M:M,D26) -> 3732 | F26: 38 | G26: =SUMIFS(转置表!T:T,转置表!L:L,B26,转置表!J:J,C26,转置表!M:M,D26) -> 39 | H26: 84770.4 | I26: 83200 | J26: 544797.36 | K26: 27300 | L26: 13000 | M26: 0 | N26: 13000
A27: =ROW()-3 -> 24 | B27: 定向井 | C27: 港东 | D27: 3 | E27: =SUMIFS(转置表!O:O,转置表!L:L,B27,转置表!J:J,C27,转置表!M:M,D27) -> 8427 | F27: 38 | G27: =SUMIFS(转置表!T:T,转置表!L:L,B27,转置表!J:J,C27,转置表!M:M,D27) -> 113.08333 | H27: 245797.93 | I27: 241244.44 | J27: 367685.39 | K27: 79158.333 | L27: 37694.444 | M27: 0 | N27: 37694.444
A28: =ROW()-3 -> 25 | B28: 定向井 | C28: 歧口 | D28: 3 | E28: =SUMIFS(转置表!O:O,转置表!L:L,B28,转置表!J:J,C28,转置表!M:M,D28) -> 10314 | F28: 38 | G28: =SUMIFS(转置表!T:T,转置表!L:L,B28,转置表!J:J,C28,转置表!M:M,D28) -> 126 | H28: 273873.6 | I28: 268800 | J28: 1473891.2 | K28: 88200 | L28: 42000 | M28: 0 | N28: 42000
A29: =ROW()-3 -> 26 | B29: 定向井 | C29: 唐东（开发井） | D29: 3 | E29: =SUMIFS(转置表!O:O,转置表!L:L,B29,转置表!J:J,C29,转置表!M:M,D29) -> 30995 | F29: 38 | G29: =SUMIFS(转置表!T:T,转置表!L:L,B29,转置表!J:J,C29,转置表!M:M,D29) -> 201.08333 | H29: 437074.73 | I29: 428977.78 | J29: 3428013.7 | K29: 140758.33 | L29: 67027.778 | M29: 83800.52 | N29: 67027.778 | O29: 19052482 | P29: 82042278
A30: =ROW()-3 -> 27 | B30: 定向井 | C30: 唐东（探评井） | D30: 3 | E30: =SUMIFS(转置表!O:O,转置表!L:L,B30,转置表!J:J,C30,转置表!M:M,D30) -> 27892 | F30: 38 | G30: =SUMIFS(转置表!T:T,转置表!L:L,B30,转置表!J:J,C30,转置表!M:M,D30) -> 222.89583 | H30: 484486.38 | I30: 475511.11 | J30: 3804249.3 | K30: 156027.08 | L30: 74298.611 | M30: 100169.56 | N30: 74298.611 | O30: 5933178.9 | P30: 77953922
A31: =ROW()-3 -> 28 | B31: 定向井 | C31: 新华 | D31: 3 | E31: =SUMIFS(转置表!O:O,转置表!L:L,B31,转置表!J:J,C31,转置表!M:M,D31) -> 42074 | F31: 38 | G31: =SUMIFS(转置表!T:T,转置表!L:L,B31,转置表!J:J,C31,转置表!M:M,D31) -> 377.7325 | H31: 821039.36 | I31: 805829.33 | J31: 4782603.2 | K31: 264412.75 | L31: 125910.83 | M31: 0 | N31: 125910.83 | O31: 24342335 | P31: 1.5713417e+08
A32: =ROW()-3 -> 29 | B32: 水平井 | C32: 板桥 | D32: 3 | E32: =SUMIFS(转置表!O:O,转置表!L:L,B32,转置表!J:J,C32,转置表!M:M,D32) -> 0 | F32: 38 | G32: =SUMIFS(转置表!T:T,转置表!L:L,B32,转置表!J:J,C32,转置表!M:M,D32) -> 0 | H32: #DIV/0! | I32: #DIV/0! | J32: 185393.26 | K32: #DIV/0! | L32: #DIV/0! | M32: 10169.057 | N32: #DIV/0!
A33: =ROW()-3 -> 30 | B33: 水平井 | C33: 埕海 | D33: 3 | E33: =SUMIFS(转置表!O:O,转置表!L:L,B33,转置表!J:J,C33,转置表!M:M,D33) -> 8218 | F33: 38 | G33: =SUMIFS(转置表!T:T,转置表!L:L,B33,转置表!J:J,C33,转置表!M:M,D33) -> 62 | H33: 134763.2 | I33: 132266.67 | J33: 1033766.9 | K33: 43400 | L33: 20666.667 | M33: 0 | N33: 20666.667
A34: =ROW()-3 -> 31 | B34: 水平井 | C34: 大港页岩油 | D34: 3 | E34: =SUMIFS(转置表!O:O,转置表!L:L,B34,转置表!J:J,C34,转置表!M:M,D34) -> 43535 | F34: 38 | G34: =SUMIFS(转置表!T:T,转置表!L:L,B34,转置表!J:J,C34,转置表!M:M,D34) -> 389 | H34: 845530.4 | I34: 829866.67 | J34: 7231651.1 | K34: 272300 | L34: 129666.67 | M34: 0 | N34: 129666.67 | O34: 1368516.9 | P34: 182709100
A35: =ROW()-3 -> 32 | B35: 水平井 | C35: 唐东 | D35: 3 | E35: =SUMIFS(转置表!O:O,转置表!L:L,B35,转置表!J:J,C35,转置表!M:M,D35) -> 5842 | F35: 38 | G35: =SUMIFS(转置表!T:T,转置表!L:L,B35,转置表!J:J,C35,转置表!M:M,D35) -> 46.71 | H35: 101528.86 | I35: 99648 | J35: 888900.3 | K35: 32697 | L35: 15570 | M35: 36624.232 | N35: 15570
A36: =ROW()-3 -> 33 | B36: 定向井 | C36: 板桥 | D36: 4 | E36: =SUMIFS(转置表!O:O,转置表!L:L,B36,转置表!J:J,C36,转置表!M:M,D36) -> 14474 | F36: 38 | G36: =SUMIFS(转置表!T:T,转置表!L:L,B36,转置表!J:J,C36,转置表!M:M,D36) -> 152.77083 | H36: 332062.68 | I36: 325911.11 | J36: 1983628.5 | K36: 106939.58 | L36: 50923.611 | M36: 84135 | N36: 50923.611 | O36: 17977484 | P36: 59828852

Sheet 6米费定额 
A1: 附件1-6
A3: 大港油区米费定额
H4: 单位：元/米•人
A5: 序号 | B5: 井型 | C5: 区块 | D5: 开次 | E5: 累计井深 | F5: 累计钻完井周期 | G5: 累计费用 | H5: 米费定额 | I5: 备注
A6: =ROW()-5 -> 1 | B6: 定向井 | C6: 板桥（＜2500米） | D6: 2 | E6: =SUMIFS(转置表!O:O,转置表!L:L,B6,转置表!J:J,C6,转置表!M:M,D6) -> 3957 | F6: =SUMIFS(转置表!T:T,转置表!L:L,B6,转置表!J:J,C6,转置表!M:M,D6) -> 25 | G6: =E6*H6*38 -> 54340 | H6: =(1300*2.2/30)*F6/E6*0.6 -> 0.36138489 | K6: =COUNTIFS(转置表!L:L,B6,转置表!J:J,C6,转置表!M:M,D6) -> 2
A7: =ROW()-5 -> 2 | B7: 定向井 | C7: 板桥（＜3500米） | D7: 2 | E7: =SUMIFS(转置表!O:O,转置表!L:L,B7,转置表!J:J,C7,转置表!M:M,D7) -> 44234 | F7: =SUMIFS(转置表!T:T,转置表!L:L,B7,转置表!J:J,C7,转置表!M:M,D7) -> 264.85417 | G7: =E7*H7*38 -> 575687.02 | H7: =(1300*2.2/30)*F7/E7*0.6 -> 0.342489 | K7: =COUNTIFS(转置表!L:L,B7,转置表!J:J,C7,转置表!M:M,D7) -> 14
A8: =ROW()-5 -> 3 | B8: 定向井 | C8: 板桥（≥3500米） | D8: 2 | E8: =SUMIFS(转置表!O:O,转置表!L:L,B8,转置表!J:J,C8,转置表!M:M,D8) -> 21858 | F8: =SUMIFS(转置表!T:T,转置表!L:L,B8,转置表!J:J,C8,转置表!M:M,D8) -> 182.66667 | G8: =E8*H8*38 -> 397044.27 | H8: =(1300*2.2/30)*F8/E8*0.6 -> 0.47801873 | K8: =COUNTIFS(转置表!L:L,B8,转置表!J:J,C8,转置表!M:M,D8) -> 6
A9: =ROW()-5 -> 4 | B9: 定向井 | C9: 港东 | D9: 2 | E9: =SUMIFS(转置表!O:O,转置表!L:L,B9,转置表!J:J,C9,转置表!M:M,D9) -> 3835 | F9: =SUMIFS(转置表!T:T,转置表!L:L,B9,转置表!J:J,C9,转置表!M:M,D9) -> 20.104167 | G9: =E9*H9*38 -> 43698.417 | H9: =(1300*2.2/30)*F9/E9*0.6 -> 0.29985876 | K9: =COUNTIFS(转置表!L:L,B9,转置表!J:J,C9,转置表!M:M,D9) -> 2
A10: =ROW()-5 -> 5 | B10: 定向井 | C10: 港西 | D10: 2 | E10: =SUMIFS(转置表!O:O,转置表!L:L,B10,转置表!J:J,C10,转置表!M:M,D10) -> 12133 | F10: =SUMIFS(转置表!T:T,转置表!L:L,B10,转置表!J:J,C10,转置表!M:M,D10) -> 93 | G10: =E10*H10*38 -> 202144.8 | H10: =(1300*2.2/30)*F10/E10*0.6 -> 0.43844062 | K10: =COUNTIFS(转置表!L:L,B10,转置表!J:J,C10,转置表!M:M,D10) -> 8
A11: =ROW()-5 -> 6 | B11: 定向井 | C11: 港中 | D11: 2 | E11: =SUMIFS(转置表!O:O,转置表!L:L,B11,转置表!J:J,C11,转置表!M:M,D11) -> 5497 | F11: =SUMIFS(转置表!T:T,转置表!L:L,B11,转置表!J:J,C11,转置表!M:M,D11) -> 37 | G11: =E11*H11*38 -> 80423.2 | H11: =(1300*2.2/30)*F11/E11*0.6 -> 0.38501001 | K11: =COUNTIFS(转置表!L:L,B11,转置表!J:J,C11,转置表!M:M,D11) -> 2
A12: =ROW()-5 -> 7 | B12: 定向井 | C12: 孔店 | D12: 2 | E12: =SUMIFS(转置表!O:O,转置表!L:L,B12,转置表!J:J,C12,转置表!M:M,D12) -> 3444 | F12: =SUMIFS(转置表!T:T,转置表!L:L,B12,转置表!J:J,C12,转置表!M:M,D12) -> 30.8125 | G12: =E12*H12*38 -> 66974.05 | H12: =(1300*2.2/30)*F12/E12*0.6 -> 0.51175232 | K12: =COUNTIFS(转置表!L:L,B12,转置表!J:J,C12,转置表!M:M,D12) -> 2
A13: =ROW()-5 -> 8 | B13: 定向井 | C13: 扣村 | D13: 2 | E13: =SUMIFS(转置表!O:O,转置表!L:L,B13,转置表!J:J,C13,转置表!M:M,D13) -> 2492 | F13: =SUMIFS(转置表!T:T,转置表!L:L,B13,转置表!J:J,C13,转置表!M:M,D13) -> 12 | G13: =E13*H13*38 -> 26083.2 | H13: =(1300*2.2/30)*F13/E13*0.6 -> 0.27544141 | I13: 扣301 | K13: =COUNTIFS(转置表!L:L,B13,转置表!J:J,C13,转置表!M:M,D13) -> 1
A14: =ROW()-5 -> 9 | B14: 定向井 | C14: 唐家河 | D14: 2 | E14: =SUMIFS(转置表!O:O,转置表!L:L,B14,转置表!J:J,C14,转置表!M:M,D14) -> 3321 | F14: =SUMIFS(转置表!T:T,转置表!L:L,B14,转置表!J:J,C14,转置表!M:M,D14) -> 20.416667 | G14: =E14*H14*38 -> 44377.667 | H14: =(1300*2.2/30)*F14/E14*0.6 -> 0.35165111 | K14: =COUNTIFS(转置表!L:L,B14,转置表!J:J,C14,转置表!M:M,D14) -> 1
A15: =ROW()-5 -> 10 | B15: 定向井 | C15: 王官屯 | D15: 2 | E15: =SUMIFS(转置表!O:O,转置表!L:L,B15,转置表!J:J,C15,转置表!M:M,D15) -> 16455 | F15: =SUMIFS(转置表!T:T,转置表!L:L,B15,转置表!J:J,C15,转置表!M:M,D15) -> 142.58333 | G15: =E15*H15*38 -> 309919.13 | H15: =(1300*2.2/30)*F15/E15*0.6 -> 0.49564064 | K15: =COUNTIFS(转置表!L:L,B15,转置表!J:J,C15,转置表!M:M,D15) -> 5
A16: =ROW()-5 -> 11 | B16: 定向井 | C16: 王徐庄 | D16: 2 | E16: =SUMIFS(转置表!O:O,转置表!L:L,B16,转置表!J:J,C16,转置表!M:M,D16) -> 2468 | F16: =SUMIFS(转置表!T:T,转置表!L:L,B16,转置表!J:J,C16,转置表!M:M,D16) -> 16 | G16: =E16*H16*38 -> 34777.6 | H16: =(1300*2.2/30)*F16/E16*0.6 -> 0.37082658 | K16: =COUNTIFS(转置表!L:L,B16,转置表!J:J,C16,转置表!M:M,D16) -> 1
A17: =ROW()-5 -> 12 | B17: 定向井 | C17: 新华 | D17: 2 | E17: =SUMIFS(转置表!O:O,转置表!L:L,B17,转置表!J:J,C17,转置表!M:M,D17) -> 9956 | F17: =SUMIFS(转置表!T:T,转置表!L:L,B17,转置表!J:J,C17,转置表!M:M,D17) -> 72.791667 | G17: =E17*H17*38 -> 158219.97 | H17: =(1300*2.2/30)*F17/E17*0.6 -> 0.41820845 | K17: =COUNTIFS(转置表!L:L,B17,转置表!J:J,C17,转置表!M:M,D17) -> 2
A18: =ROW()-5 -> 13 | B18: 定向井 | C18: 羊二庄 | D18: 2 | E18: =SUMIFS(转置表!O:O,转置表!L:L,B18,转置表!J:J,C18,转置表!M:M,D18) -> 4402 | F18: =SUMIFS(转置表!T:T,转置表!L:L,B18,转置表!J:J,C18,转置表!M:M,D18) -> 22 | G18: =E18*H18*38 -> 47819.2 | H18: =(1300*2.2/30)*F18/E18*0.6 -> 0.28587006 | K18: =COUNTIFS(转置表!L:L,B18,转置表!J:J,C18,转置表!M:M,D18) -> 2
A19: =ROW()-5 -> 14 | B19: 定向井 | C19: 羊三木 | D19: 2 | E19: =SUMIFS(转置表!O:O,转置表!L:L,B19,转置表!J:J,C19,转置表!M:M,D19) -> 2775 | F19: =SUMIFS(转置表!T:T,转置表!L:L,B19,转置表!J:J,C19,转置表!M:M,D19) -> 21 | G19: =E19*H19*38 -> 45645.6 | H19: =(1300*2.2/30)*F19/E19*0.6 -> 0.43286486 | K19: =COUNTIFS(转置表!L:L,B19,转置表!J:J,C19,转置表!M:M,D19) -> 1
A20: =ROW()-5 -> 15 | B20: 定向井 | C20: 枣园 | D20: 2 | E20: =SUMIFS(转置表!O:O,转置表!L:L,B20,转置表!J:J,C20,转置表!M:M,D20) -> 10593 | F20: =SUMIFS(转置表!T:T,转置表!L:L,B20,转置表!J:J,C20,转置表!M:M,D20) -> 71 | G20: =E20*H20*38 -> 154325.6 | H20: =(1300*2.2/30)*F20/E20*0.6 -> 0.38338525 | K20: =COUNTIFS(转置表!L:L,B20,转置表!J:J,C20,转置表!M:M,D20) -> 4
A21: =ROW()-5 -> 16 | B21: 水平井 | C21: 板桥 | D21: 2 | E21: =SUMIFS(转置表!O:O,转置表!L:L,B21,转置表!J:J,C21,转置表!M:M,D21) -> 19739 | F21: =SUMIFS(转置表!T:T,转置表!L:L,B21,转置表!J:J,C21,转置表!M:M,D21) -> 123.8125 | G21: =E21*H21*38 -> 269118.85 | H21: =(1300*2.2/30)*F21/E21*0.6 -> 0.35878591 | K21: =COUNTIFS(转置表!L:L,B21,转置表!J:J,C21,转置表!M:M,D21) -> 8
A22: =ROW()-5 -> 17 | B22: 水平井 | C22: 埕海 | D22: 2 | E22: =SUMIFS(转置表!O:O,转置表!L:L,B22,转置表!J:J,C22,转置表!M:M,D22) -> 4804 | F22: =SUMIFS(转置表!T:T,转置表!L:L,B22,转置表!J:J,C22,转置表!M:M,D22) -> 38.916667 | G22: =E22*H22*38 -> 84589.267 | H22: =(1300*2.2/30)*F22/E22*0.6 -> 0.4633708 | K22: =COUNTIFS(转置表!L:L,B22,转置表!J:J,C22,转置表!M:M,D22) -> 1
A23: =ROW()-5 -> 18 | B23: 水平井 | C23: 大港页岩油 | D23: 2 | E23: =SUMIFS(转置表!O:O,转置表!L:L,B23,转置表!J:J,C23,转置表!M:M,D23) -> 18574 | F23: =SUMIFS(转置表!T:T,转置表!L:L,B23,转置表!J:J,C23,转置表!M:M,D23) -> 100.52431 | G23: =E23*H23*38 -> 218499.63 | H23: =(1300*2.2/30)*F23/E23*0.6 -> 0.309572 | K23: =COUNTIFS(转置表!L:L,B23,转置表!J:J,C23,转置表!M:M,D23) -> 3
A24: =ROW()-5 -> 19 | B24: 水平井 | C24: 枣园 | D24: 2 | E24: =SUMIFS(转置表!O:O,转置表!L:L,B24,转置表!J:J,C24,转置表!M:M,D24) -> 8000 | F24: =SUMIFS(转置表!T:T,转置表!L:L,B24,转置表!J:J,C24,转置表!M:M,D24) -> 83.125 | G24: =E24*H24*38 -> 180680.5 | H24: =(1300*2.2/30)*F24/E24*0.6 -> 0.59434375 | K24: =COUNTIFS(转置表!L:L,B24,转置表!J:J,C24,转置表!M:M,D24) -> 2
A25: =ROW()-5 -> 20 | B25: 定向井 | C25: 板桥 | D25: 3 | E25: =SUMIFS(转置表!O:O,转置表!L:L,B25,转置表!J:J,C25,转置表!M:M,D25) -> 18653 | F25: =SUMIFS(转置表!T:T,转置表!L:L,B25,转置表!J:J,C25,转置表!M:M,D25) -> 147 | G25: =E25*H25*38 -> 319519.2 | H25: =(1300*2.2/30)*F25/E25*0.6 -> 0.45078004 | K25: =COUNTIFS(转置表!L:L,B25,转置表!J:J,C25,转置表!M:M,D25) -> 5
... A35: =ROW()-5 -> 30 | B35: 水平井 | C35: 埕海 | D35: 3 | E35: =SUMIFS(转置表!O:O,转置表!L:L,B35,转置表!J:J,C35,转置表!M:M,D35) -> 8218 | F35: =SUMIFS(转置表!T:T,转置表!L:L,B35,转置表!J:J,C35,转置表!M:M,D35) -> 62 | G35: =E35*H35*38 -> 134763.2 | H35: =(1300*2.2/30)*F35/E35*0.6 -> 0.43154052 | K35: =COUNTIFS(转置表!L:L,B35,转置表!J:J,C35,转置表!M:M,D35) -> 2
A36: =ROW()-5 -> 31 | B36: 水平井 | C36: 大港页岩油 | D36: 3 | E36: =SUMIFS(转置表!O:O,转置表!L:L,B36,转置表!J:J,C36,转置表!M:M,D36) -> 43535 | F36: =SUMIFS(转置表!T:T,转置表!L:L,B36,转置表!J:J,C36,转置表!M:M,D36) -> 389 | G36: =E36*H36*38 -> 845530.4 | H36: =(1300*2.2/30)*F36/E36*0.6 -> 0.51110141 | I36: 华页1、官页5-5-1 | K36: =COUNTIFS(转置表!L:L,B36,转置表!J:J,C36,转置表!M:M,D36) -> 7
A37: =ROW()-5 -> 32 | B37: 水平井 | C37: 唐东 | D37: 3 | E37: =SUMIFS(转置表!O:O,转置表!L:L,B37,转置表!J:J,C37,转置表!M:M,D37) -> 5842 | F37: =SUMIFS(转置表!T:T,转置表!L:L,B37,转置表!J:J,C37,转置表!M:M,D37) -> 46.71 | G37: =E37*H37*38 -> 101528.86 | H37: =(1300*2.2/30)*F37/E37*0.6 -> 0.45734543 | K37: =COUNTIFS(转置表!L:L,B37,转置表!J:J,C37,转置表!M:M,D37) -> 1
A38: =ROW()-5 -> 33 | B38: 定向井 | C38: 板桥 | D38: 4 | E38: =SUMIFS(转置表!O:O,转置表!L:L,B38,转置表!J:J,C38,转置表!M:M,D38) -> 14474 | F38: =SUMIFS(转置表!T:T,转置表!L:L,B38,转置表!J:J,C38,转置表!M:M,D38) -> 152.77083 | G38: =E38*H38*38 -> 332062.68 | H38: =(1300*2.2/30)*F38/E38*0.6 -> 0.60373716 | K38: =COUNTIFS(转置表!L:L,B38,转置表!J:J,C38,转置表!M:M,D38) -> 3
B39: 定向井 | C39: 常探1 | D39: 3 | E39: 6082 | F39: 52.75 | G39: =E39*H39*38 -> 114657.4 | H39: =(1300*2.2/30)*F39/E39*0.6 -> 0.49610326
B40: 定向井 | C40: 滨188X1 | D40: 3 | E40: 5220 | F40: 53.5 | G40: =E40*H40*38 -> 116287.6 | H40: =(1300*2.2/30)*F40/E40*0.6 -> 0.58624521
B41: 定向井 | C41: 孔101-9 | D41: 2 | E41: 1761 | F41: 10 | G41: =E41*H41*38 -> 21736 | H41: =(1300*2.2/30)*F41/E41*0.6 -> 0.32481545
B42: 定向井 | C42: 家29-30 | D42: 2 | E42: 2327 | F42: 14 | G42: =E42*H42*38 -> 30430.4 | H42: =(1300*2.2/30)*F42/E42*0.6 -> 0.34413408
B43: 定向井 | C43: 官40-67 | D43: 2 | E43: 3092 | F43: 17 | G43: =E43*H43*38 -> 36951.2 | H43: =(1300*2.2/30)*F43/E43*0.6 -> 0.314489
B44: 水平井 | C44: 板70-20H | D44: 3 | E44: 2695 | F44: 25.5 | G44: =E44*H44*38 -> 55426.8 | H44: =(1300*2.2/30)*F44/E44*0.6 -> 0.54122449
B45: 水平井 | C45: 板69-22H | D45: 3 | E45: 2720 | F45: 23.1 | G45: =E45*H45*38 -> 50210.16 | H45: =(1300*2.2/30)*F45/E45*0.6 -> 0.48577941
B46: 定向井 | C46: 灯探1 | D46: 3 | E46: 3632 | F46: 27 | G46: =E46*H46*38 -> 58687.2 | H46: =(1300*2.2/30)*F46/E46*0.6 -> 0.42522026
B47: 定向井 | C47: 官40-61 | D47: 2 | E47: 3092 | F47: 18.5 | G47: =E47*H47*38 -> 40211.6 | H47: =(1300*2.2/30)*F47/E47*0.6 -> 0.34223803
B48: 定向井 | C48: 塘39-6 | D48: 3 | E48: 4540 | F48: 27.5 | G48: =E48*H48*38 -> 59774 | H48: =(1300*2.2/30)*F48/E48*0.6 -> 0.34647577

Sheet 7一般材料定额
A1: 附件1-7
A2: 大港油区区块一般材料定额
I3: 单位：元/米
A4: 序号 | B4: 井型 | C4: 区块 | D4: 开次 | E4: 累计井深 | F4: 累计钻完井周期 | G4: 50型累计费用 | H4: 70型累计费用 | I4: 50型定额 | J4: 70型定额 | K4: 备注 | Q4: 修订说明：
A5: =ROW()-4 -> 1 | B5: 定向井 | C5: 板桥（＜2500米） | D5: 2 | E5: =SUMIFS(转置表!O:O,转置表!L:L,B5,转置表!J:J,C5,转置表!M:M,D5) -> 3957 | F5: =SUMIFS(转置表!T:T,转置表!L:L,B5,转置表!J:J,C5,转置表!M:M,D5) -> 25 | G5: =E5*I5 -> 53125 | H5: =E5*J5 -> 60208.333 | I5: =(75000/30)*F5/E5*0.85 -> 13.425575 | J5: =(85000/30)*F5/E5*0.85 -> 15.215652 | Q5: 2.10修订：考虑完井因素，一般材料二开井下浮15%，三开井下浮20% | T5: 13.425575 | U5: =ROUND(T5,2) -> 13.43 | V5: 15.215652 | W5: =ROUND(V5,2) -> 15.22
A6: =ROW()-4 -> 2 | B6: 定向井 | C6: 板桥（＜3500米） | D6: 2 | E6: =SUMIFS(转置表!O:O,转置表!L:L,B6,转置表!J:J,C6,转置表!M:M,D6) -> 44234 | F6: =SUMIFS(转置表!T:T,转置表!L:L,B6,转置表!J:J,C6,转置表!M:M,D6) -> 264.85417 | G6: =E6*I6 -> 562815.1 | H6: =E6*J6 -> 637857.12 | I6: =(75000/30)*F6/E6*0.85 -> 12.723586 | J6: =(85000/30)*F6/E6*0.85 -> 14.420064 | Q6: 2.13日修订：取心定额按60%核算 | T6: 13.055197 | U6: =ROUND(T6,2) -> 13.06 | V6: 14.79589 | W6: =ROUND(V6,2) -> 14.8
A7: =ROW()-4 -> 3 | B7: 定向井 | C7: 板桥（≥3500米） | D7: 2 | E7: =SUMIFS(转置表!O:O,转置表!L:L,B7,转置表!J:J,C7,转置表!M:M,D7) -> 21858 | F7: =SUMIFS(转置表!T:T,转置表!L:L,B7,转置表!J:J,C7,转置表!M:M,D7) -> 182.66667 | G7: =E7*I7 -> 388166.67 | H7: =E7*J7 -> 439922.22 | I7: =(75000/30)*F7/E7*0.85 -> 17.758563 | J7: =(85000/30)*F7/E7*0.85 -> 20.126371 | M7: 定向井 | N7: 板桥 | O7: =N7=C7 -> FALSE | T7: 17.758563 | U7: =ROUND(T7,2) -> 17.76 | V7: 20.126371 | W7: =ROUND(V7,2) -> 20.13
A8: =ROW()-4 -> 4 | B8: 定向井 | C8: 港东 | D8: 2 | E8: =SUMIFS(转置表!O:O,转置表!L:L,B8,转置表!J:J,C8,转置表!M:M,D8) -> 3835 | F8: =SUMIFS(转置表!T:T,转置表!L:L,B8,转置表!J:J,C8,转置表!M:M,D8) -> 20.104167 | G8: =E8*I8 -> 42721.354 | H8: =E8*J8 -> 48417.535 | I8: =(75000/30)*F8/E8*0.85 -> 11.139858 | J8: =(85000/30)*F8/E8*0.85 -> 12.625172 | M8: 定向井 | N8: 港东 | O8: =N8=C8 -> TRUE | T8: 11.139858 | U8: =ROUND(T8,2) -> 11.14 | V8: 12.625172 | W8: =ROUND(V8,2) -> 12.63
A9: =ROW()-4 -> 5 | B9: 定向井 | C9: 港西 | D9: 2 | E9: =SUMIFS(转置表!O:O,转置表!L:L,B9,转置表!J:J,C9,转置表!M:M,D9) -> 12133 | F9: =SUMIFS(转置表!T:T,转置表!L:L,B9,转置表!J:J,C9,转置表!M:M,D9) -> 93 | G9: =E9*I9 -> 197625 | H9: =E9*J9 -> 223975 | I9: =(75000/30)*F9/E9*0.85 -> 16.288222 | J9: =(85000/30)*F9/E9*0.85 -> 18.459985 | M9: 定向井 | N9: 港西 | O9: =N9=C9 -> TRUE | T9: 16.288222 | U9: =ROUND(T9,2) -> 16.29 | V9: 18.459985 | W9: =ROUND(V9,2) -> 18.46
A10: =ROW()-4 -> 6 | B10: 定向井 | C10: 港中 | D10: 2 | E10: =SUMIFS(转置表!O:O,转置表!L:L,B10,转置表!J:J,C10,转置表!M:M,D10) -> 5497 | F10: =SUMIFS(转置表!T:T,转置表!L:L,B10,转置表!J:J,C10,转置表!M:M,D10) -> 37 | G10: =E10*I10 -> 78625 | H10: =E10*J10 -> 89108.333 | I10: =(75000/30)*F10/E10*0.85 -> 14.303256 | J10: =(85000/30)*F10/E10*0.85 -> 16.210357 | M10: 定向井 | N10: 港中 | O10: =N10=C10 -> TRUE | T10: 14.303256 | U10: =ROUND(T10,2) -> 14.3 | V10: 16.210357 | W10: =ROUND(V10,2) -> 16.21
A11: =ROW()-4 -> 7 | B11: 定向井 | C11: 孔店 | D11: 2 | E11: =SUMIFS(转置表!O:O,转置表!L:L,B11,转置表!J:J,C11,转置表!M:M,D11) -> 3444 | F11: =SUMIFS(转置表!T:T,转置表!L:L,B11,转置表!J:J,C11,转置表!M:M,D11) -> 30.8125 | G11: =E11*I11 -> 65476.562 | H11: =E11*J11 -> 74206.771 | I11: =(75000/30)*F11/E11*0.85 -> 19.011778 | J11: =(85000/30)*F11/E11*0.85 -> 21.546681 | M11: 定向井 | N11: 孔店 | O11: =N11=C11 -> TRUE | T11: 19.011778 | U11: =ROUND(T11,2) -> 19.01 | V11: 21.546681 | W11: =ROUND(V11,2) -> 21.55
A12: =ROW()-4 -> 8 | B12: 定向井 | C12: 扣村 | D12: 2 | E12: =SUMIFS(转置表!O:O,转置表!L:L,B12,转置表!J:J,C12,转置表!M:M,D12) -> 2492 | F12: =SUMIFS(转置表!T:T,转置表!L:L,B12,转置表!J:J,C12,转置表!M:M,D12) -> 12 | G12: =E12*I12 -> 25500 | H12: =E12*J12 -> 28900 | I12: =(75000/30)*F12/E12*0.85 -> 10.232745 | J12: =(85000/30)*F12/E12*0.85 -> 11.597111 | K12: 扣301 | M12: 定向井 | N12: 扣村 | O12: =N12=C12 -> TRUE | T12: 10.232745 | U12: =ROUND(T12,2) -> 10.23 | V12: 11.597111 | W12: =ROUND(V12,2) -> 11.6
A13: =ROW()-4 -> 9 | B13: 定向井 | C13: 唐家河 | D13: 2 | E13: =SUMIFS(转置表!O:O,转置表!L:L,B13,转置表!J:J,C13,转置表!M:M,D13) -> 3321 | F13: =SUMIFS(转置表!T:T,转置表!L:L,B13,转置表!J:J,C13,转置表!M:M,D13) -> 20.416667 | G13: =E13*I13 -> 43385.417 | H13: =E13*J13 -> 49170.139 | I13: =(75000/30)*F13/E13*0.85 -> 13.063962 | J13: =(85000/30)*F13/E13*0.85 -> 14.805823 | M13: 定向井 | N13: 唐家河 | O13: =N13=C13 -> TRUE | T13: 13.063962 | U13: =ROUND(T13,2) -> 13.06 | V13: 14.805823 | W13: =ROUND(V13,2) -> 14.81
A14: =ROW()-4 -> 10 | B14: 定向井 | C14: 王官屯 | D14: 2 | E14: =SUMIFS(转置表!O:O,转置表!L:L,B14,转置表!J:J,C14,转置表!M:M,D14) -> 16455 | F14: =SUMIFS(转置表!T:T,转置表!L:L,B14,转置表!J:J,C14,转置表!M:M,D14) -> 142.58333 | G14: =E14*I14 -> 302989.58 | H14: =E14*J14 -> 343388.19 | I14: =(75000/30)*F14/E14*0.85 -> 18.413223 | J14: =(85000/30)*F14/E14*0.85 -> 20.868319 | M14: 定向井 | N14: 王官屯 | O14: =N14=C14 -> TRUE | T14: 18.916442 | U14: =ROUND(T14,2) -> 18.92 | V14: 21.438635 | W14: =ROUND(V14,2) -> 21.44
A15: =ROW()-4 -> 11 | B15: 定向井 | C15: 王徐庄 | D15: 2 | E15: =SUMIFS(转置表!O:O,转置表!L:L,B15,转置表!J:J,C15,转置表!M:M,D15) -> 2468 | F15: =SUMIFS(转置表!T:T,转置表!L:L,B15,转置表!J:J,C15,转置表!M:M,D15) -> 16 | G15: =E15*I15 -> 34000 | H15: =E15*J15 -> 38533.333 | I15: =(75000/30)*F15/E15*0.85 -> 13.776337 | J15: =(85000/30)*F15/E15*0.85 -> 15.613182 | M15: 定向井 | N15: 王徐庄 | O15: =N15=C15 -> TRUE | T15: 13.776337 | U15: =ROUND(T15,2) -> 13.78 | V15: 15.613182 | W15: =ROUND(V15,2) -> 15.61
A16: =ROW()-4 -> 12 | B16: 定向井 | C16: 新华 | D16: 2 | E16: =SUMIFS(转置表!O:O,转置表!L:L,B16,转置表!J:J,C16,转置表!M:M,D16) -> 9956 | F16: =SUMIFS(转置表!T:T,转置表!L:L,B16,转置表!J:J,C16,转置表!M:M,D16) -> 72.791667 | G16: =E16*I16 -> 154682.29 | H16: =E16*J16 -> 175306.6 | I16: =(75000/30)*F16/E16*0.85 -> 15.53659 | J16: =(85000/30)*F16/E16*0.85 -> 17.608136 | M16: 定向井 | N16: 新华 | O16: =N16=C16 -> TRUE | T16: 15.53659 | U16: =ROUND(T16,2) -> 15.54 | V16: 17.608136 | W16: =ROUND(V16,2) -> 17.61
A17: =ROW()-4 -> 13 | B17: 定向井 | C17: 羊二庄 | D17: 2 | E17: =SUMIFS(转置表!O:O,转置表!L:L,B17,转置表!J:J,C17,转置表!M:M,D17) -> 4402 | F17: =SUMIFS(转置表!T:T,转置表!L:L,B17,转置表!J:J,C17,转置表!M:M,D17) -> 22 | G17: =E17*I17 -> 46750 | H17: =E17*J17 -> 52983.333 | I17: =(75000/30)*F17/E17*0.85 -> 10.620173 | J17: =(85000/30)*F17/E17*0.85 -> 12.036196 | M17: 定向井 | N17: 羊二庄 | O17: =N17=C17 -> TRUE | T17: 10.620173 | U17: =ROUND(T17,2) -> 10.62 | V17: 12.036196 | W17: =ROUND(V17,2) -> 12.04
A18: =ROW()-4 -> 14 | B18: 定向井 | C18: 羊三木 | D18: 2 | E18: =SUMIFS(转置表!O:O,转置表!L:L,B18,转置表!J:J,C18,转置表!M:M,D18) -> 2775 | F18: =SUMIFS(转置表!T:T,转置表!L:L,B18,转置表!J:J,C18,转置表!M:M,D18) -> 21 | G18: =E18*I18 -> 44625 | H18: =E18*J18 -> 50575 | I18: =(75000/30)*F18/E18*0.85 -> 16.081081 | J18: =(85000/30)*F18/E18*0.85 -> 18.225225 | M18: 定向井 | N18: 羊三木 | O18: =N18=C18 -> TRUE | T18: 16.081081 | U18: =ROUND(T18,2) -> 16.08 | V18: 18.225225 | W18: =ROUND(V18,2) -> 18.23
A19: =ROW()-4 -> 15 | B19: 定向井 | C19: 枣园 | D19: 2 | E19: =SUMIFS(转置表!O:O,转置表!L:L,B19,转置表!J:J,C19,转置表!M:M,D19) -> 10593 | F19: =SUMIFS(转置表!T:T,转置表!L:L,B19,转置表!J:J,C19,转置表!M:M,D19) -> 71 | G19: =E19*I19 -> 150875 | H19: =E19*J19 -> 170991.67 | I19: =(75000/30)*F19/E19*0.85 -> 14.242896 | J19: =(85000/30)*F19/E19*0.85 -> 16.141949 | M19: 定向井 | N19: 枣园 | O19: =N19=C19 -> TRUE | T19: 14.242896 | U19: =ROUND(T19,2) -> 14.24 | V19: 16.141949 | W19: =ROUND(V19,2) -> 16.14
A20: =ROW()-4 -> 16 | B20: 水平井 | C20: 板桥 | D20: 2 | E20: =SUMIFS(转置表!O:O,转置表!L:L,B20,转置表!J:J,C20,转置表!M:M,D20) -> 19739 | F20: =SUMIFS(转置表!T:T,转置表!L:L,B20,转置表!J:J,C20,转置表!M:M,D20) -> 123.8125 | G20: =E20*I20 -> 263101.56 | H20: =E20*J20 -> 298181.77 | I20: =(75000/30)*F20/E20*0.85 -> 13.329022 | J20: =(85000/30)*F20/E20*0.85 -> 15.106225 | M20: 水平井 | N20: 板桥 | O20: =N20=C20 -> TRUE | T20: 13.329022 | U20: =ROUND(T20,2) -> 13.33 | V20: 15.106225 | W20: =ROUND(V20,2) -> 15.11
A21: =ROW()-4 -> 17 | B21: 水平井 | C21: 埕海 | D21: 2 | E21: =SUMIFS(转置表!O:O,转置表!L:L,B21,转置表!J:J,C21,转置表!M:M,D21) -> 4804 | F21: =SUMIFS(转置表!T:T,转置表!L:L,B21,转置表!J:J,C21,转置表!M:M,D21) -> 38.916667 | G21: =E21*I21 -> 82697.917 | H21: =E21*J21 -> 93724.306 | I21: =(75000/30)*F21/E21*0.85 -> 17.214387 | J21: =(85000/30)*F21/E21*0.85 -> 19.509639 | M21: 水平井 | N21: 埕海 | O21: =N21=C21 -> TRUE | T21: 17.214387 | U21: =ROUND(T21,2) -> 17.21 | V21: 19.509639 | W21: =ROUND(V21,2) -> 19.51
A22: =ROW()-4 -> 18 | B22: 水平井 | C22: 大港页岩油 | D22: 2 | E22: =SUMIFS(转置表!O:O,转置表!L:L,B22,转置表!J:J,C22,转置表!M:M,D22) -> 18574 | F22: =SUMIFS(转置表!T:T,转置表!L:L,B22,转置表!J:J,C22,转置表!M:M,D22) -> 100.52431 | G22: =E22*I22 -> 213614.15 | H22: =E22*J22 -> 242096.04 | I22: =(75000/30)*F22/E22*0.85 -> 11.500708 | J22: =(85000/30)*F22/E22*0.85 -> 13.034136 | M22: 水平井 | N22: 大港页岩油 | O22: =N22=C22 -> TRUE | T22: 11.500708 | U22: =ROUND(T22,2) -> 11.5 | V22: 13.034136 | W22: =ROUND(V22,2) -> 13.03
A23: =ROW()-4 -> 19 | B23: 水平井 | C23: 枣园 | D23: 2 | E23: =SUMIFS(转置表!O:O,转置表!L:L,B23,转置表!J:J,C23,转置表!M:M,D23) -> 8000 | F23: =SUMIFS(转置表!T:T,转置表!L:L,B23,转置表!J:J,C23,转置表!M:M,D23) -> 83.125 | G23: =E23*I23 -> 176640.62 | H23: =E23*J23 -> 200192.71 | I23: =(75000/30)*F23/E23*0.85 -> 22.080078 | J23: =(85000/30)*F23/E23*0.85 -> 25.024089 | M23: 水平井 | N23: 枣园 | O23: =N23=C23 -> TRUE | T23: 22.080078 | U23: =ROUND(T23,2) -> 22.08 | V23: 25.024089 | W23: =ROUND(V23,2) -> 25.02
A24: =ROW()-4 -> 20 | B24: 定向井 | C24: 板桥 | D24: 3 | E24: =SUMIFS(转置表!O:O,转置表!L:L,B24,转置表!J:J,C24,转置表!M:M,D24) -> 18653 | F24: =SUMIFS(转置表!T:T,转置表!L:L,B24,转置表!J:J,C24,转置表!M:M,D24) -> 147 | G24: =E24*I24 -> 294000 | H24: =E24*J24 -> 333200 | I24: =(75000/30)*F24/E24*0.8 -> 15.76154 | J24: =(85000/30)*F24/E24*0.8 -> 17.863078 | M24: 定向井 | N24: 板桥 | O24: =N24=C24 -> TRUE | T24: 15.76154 | U24: =ROUND(T24,2) -> 15.76 | V24: 17.863078 | W24: =ROUND(V24,2) -> 17.86
A25: =ROW()-4 -> 21 | B25: 定向井 | C25: 埕海（＜4000米） | D25: 3 | E25: =SUMIFS(转置表!O:O,转置表!L:L,B25,转置表!J:J,C25,转置表!M:M,D25) -> 7594 | F25: =SUMIFS(转置表!T:T,转置表!L:L,B25,转置表!J:J,C25,转置表!M:M,D25) -> 42.9375 | G25: =E25*I25 -> 85875 | H25: =E25*J25 -> 97325 | I25: =(75000/30)*F25/E25*0.8 -> 11.30827 | J25: =(85000/30)*F25/E25*0.8 -> 12.816039 | M25: 定向井 | N25: 埕海 | O25: =N25=C25 -> FALSE | T25: 11.30827 | U25: =ROUND(T25,2) -> 11.31 | V25: 12.816039 | W25: =ROUND(V25,2) -> 12.82
A26: =ROW()-4 -> 22 | B26: 定向井 | C26: 埕海（≥4000米） | D26: 3 | E26: =SUMIFS(转置表!O:O,转置表!L:L,B26,转置表!J:J,C26,转置表!M:M,D26) -> 23072 | F26: =SUMIFS(转置表!T:T,转置表!L:L,B26,转置表!J:J,C26,转置表!M:M,D26) -> 153.79167 | G26: =E26*I26 -> 307583.33 | H26: =E26*J26 -> 348594.44 | I26: =(75000/30)*F26/E26*0.8 -> 13.331455 | J26: =(85000/30)*F26/E26*0.8 -> 15.108983 | M26: 定向井 | N26: 埕海 | O26: =N26=C26 -> FALSE | T26: 13.331455 | U26: =ROUND(T26,2) -> 13.33 | V26: 15.108983 | W26: =ROUND(V26,2) -> 15.11
A27: =ROW()-4 -> 23 | B27: 定向井 | C27: 大港页岩油 | D27: 3 | E27: =SUMIFS(转置表!O:O,转置表!L:L,B27,转置表!J:J,C27,转置表!M:M,D27) -> 3732 | F27: =SUMIFS(转置表!T:T,转置表!L:L,B27,转置表!J:J,C27,转置表!M:M,D27) -> 39 | G27: =E27*I27 -> 78000 | H27: =E27*J27 -> 88400 | I27: =(75000/30)*F27/E27*0.8 -> 20.900322 | J27: =(85000/30)*F27/E27*0.8 -> 23.687031 | M27: 定向井 | N27: 大港页岩油 | O27: =N27=C27 -> TRUE | T27: 20.900322 | U27: =ROUND(T27,2) -> 20.9 | V27: 23.687031 | W27: =ROUND(V27,2) -> 23.69
A28: =ROW()-4 -> 24 | B28: 定向井 | C28: 港东 | D28: 3 | E28: =SUMIFS(转置表!O:O,转置表!L:L,B28,转置表!J:J,C28,转置表!M:M,D28) -> 8427 | F28: =SUMIFS(转置表!T:T,转置表!L:L,B28,转置表!J:J,C28,转置表!M:M,D28) -> 113.08333 | G28: =E28*I28 -> 226166.67 | H28: =E28*J28 -> 256322.22 | I28: =(75000/30)*F28/E28*0.8 -> 26.838337 | J28: =(85000/30)*F28/E28*0.8 -> 30.416782 | M28: 定向井 | N28: 港东 | O28: =N28=C28 -> TRUE | T28: 26.838337 | U28: =ROUND(T28,2) -> 26.84 | V28: 30.416782 | W28: =ROUND(V28,2) -> 30.42
A29: =ROW()-4 -> 25 | B29: 定向井 | C29: 歧口 | D29: 3 | E29: =SUMIFS(转置表!O:O,转置表!L:L,B29,转置表!J:J,C29,转置表!M:M,D29) -> 10314 | F29: =SUMIFS(转置表!T:T,转置表!L:L,B29,转置表!J:J,C29,转置表!M:M,D29) -> 126 | G29: =E29*I29 -> 252000 | H29: =E29*J29 -> 285600 | I29: =(75000/30)*F29/E29*0.8 -> 24.43281 | J29: =(85000/30)*F29/E29*0.8 -> 27.690518 | M29: 定向井 | N29: 歧口 | O29: =N29=C29 -> TRUE | T29: 24.43281 | U29: =ROUND(T29,2) -> 24.43 | V29: 27.690518 | W29: =ROUND(V29,2) -> 27.69
A30: =ROW()-4 -> 26 | B30: 定向井 | C30: 唐东（开发井） | D30: 3 | E30: =SUMIFS(转置表!O:O,转置表!L:L,B30,转置表!J:J,C30,转置表!M:M,D30) -> 30995 | F30: =SUMIFS(转置表!T:T,转置表!L:L,B30,转置表!J:J,C30,转置表!M:M,D30) -> 201.08333 | G30: =E30*I30 -> 402166.67 | H30: =E30*J30 -> 455788.89 | I30: =(75000/30)*F30/E30*0.8 -> 12.975211 | J30: =(85000/30)*F30/E30*0.8 -> 14.705239 | T30: 12.513276 | U30: =ROUND(T30,2) -> 12.51 | V30: 14.181713 | W30: =ROUND(V30,2) -> 14.18
A31: =ROW()-4 -> 27 | B31: 定向井 | C31: 唐东（探评井） | D31: 3 | E31: =SUMIFS(转置表!O:O,转置表!L:L,B31,转置表!J:J,C31,转置表!M:M,D31) -> 27892 | F31: =SUMIFS(转置表!T:T,转置表!L:L,B31,转置表!J:J,C31,转置表!M:M,D31) -> 222.89583 | G31: =E31*I31 -> 445791.67 | H31: =E31*J31 -> 505230.56 | I31: =(75000/30)*F31/E31*0.8 -> 15.982779 | J31: =(85000/30)*F31/E31*0.8 -> 18.113816 | M31: 定向井 | N31: 唐东 | O31: =N31=C31 -> FALSE | T31: 15.187169 | U31: =ROUND(T31,2) -> 15.19 | V31: 17.212125 | W31: =ROUND(V31,2) -> 17.21
A32: =ROW()-4 -> 28 | B32: 定向井 | C32: 新华 | D32: 3 | E32: =SUMIFS(转置表!O:O,转置表!L:L,B32,转置表!J:J,C32,转置表!M:M,D32) -> 42074 | F32: =SUMIFS(转置表!T:T,转置表!L:L,B32,转置表!J:J,C32,转置表!M:M,D32) -> 377.7325 | G32: =E32*I32 -> 755465 | H32: =E32*J32 -> 856193.67 | I32: =(75000/30)*F32/E32*0.8 -> 17.955626 | J32: =(85000/30)*F32/E32*0.8 -> 20.349709 | M32: 定向井 | N32: 新华 | O32: =N32=C32 -> TRUE | T32: 16.489474 | U32: =ROUND(T32,2) -> 16.49 | V32: 18.68807 | W32: =ROUND(V32,2) -> 18.69
A33: =ROW()-4 -> 29 | B33: 水平井 | C33: 板桥 | D33: 3 | E33: =SUMIFS(转置表!O:O,转置表!L:L,B33,转置表!J:J,C33,转置表!M:M,D33) -> 0 | F33: =SUMIFS(转置表!T:T,转置表!L:L,B33,转置表!J:J,C33,转置表!M:M,D33) -> 0 | G33: =E33*I33 -> #DIV/0! | H33: =E33*J33 -> #DIV/0! | I33: =(75000/30)*F33/E33*0.8 -> #DIV/0! | J33: =(85000/30)*F33/E33*0.8 -> #DIV/0! | M33: 水平井 | N33: 板桥 | O33: =N33=C33 -> TRUE | T33: #DIV/0! | U33: =ROUND(T33,2) -> #DIV/0! | V33: #DIV/0! | W33: =ROUND(V33,2) -> #DIV/0!
A34: =ROW()-4 -> 30 | B34: 水平井 | C34: 埕海 | D34: 3 | E34: =SUMIFS(转置表!O:O,转置表!L:L,B34,转置表!J:J,C34,转置表!M:M,D34) -> 8218 | F34: =SUMIFS(转置表!T:T,转置表!L:L,B34,转置表!J:J,C34,转置表!M:M,D34) -> 62 | G34: =E34*I34 -> 124000 | H34: =E34*J34 -> 140533.33 | I34: =(75000/30)*F34/E34*0.8 -> 15.088829 | J34: =(85000/30)*F34/E34*0.8 -> 17.100673 | M34: 水平井 | N34: 埕海 | O34: =N34=C34 -> TRUE | T34: 15.088829 | U34: =ROUND(T34,2) -> 15.09 | V34: 17.100673 | W34: =ROUND(V34,2) -> 17.1
A35: =ROW()-4 -> 31 | B35: 水平井 | C35: 大港页岩油 | D35: 3 | E35: =SUMIFS(转置表!O:O,转置表!L:L,B35,转置表!J:J,C35,转置表!M:M,D35) -> 43535 | F35: =SUMIFS(转置表!T:T,转置表!L:L,B35,转置表!J:J,C35,转置表!M:M,D35) -> 389 | G35: =E35*I35 -> 778000 | H35: =E35*J35 -> 881733.33 | I35: =(75000/30)*F35/E35*0.8 -> 17.870679 | J35: =(85000/30)*F35/E35*0.8 -> 20.253436 | K35: 华页1、官页5-5-1 | M35: 水平井 | N35: 大港页岩油 | O35: =N35=C35 -> TRUE | T35: 17.870679 | U35: =ROUND(T35,2) -> 17.87 | V35: 20.253436 | W35: =ROUND(V35,2) -> 20.25
A36: =ROW()-4 -> 32 | B36: 水平井 | C36: 唐东 | D36: 3 | E36: =SUMIFS(转置表!O:O,转置表!L:L,B36,转置表!J:J,C36,转置表!M:M,D36) -> 5842 | F36: =SUMIFS(转置表!T:T,转置表!L:L,B36,转置表!J:J,C36,转置表!M:M,D36) -> 46.71 | G36: =E36*I36 -> 93420 | H36: =E36*J36 -> 105876 | I36: =(75000/30)*F36/E36*0.8 -> 15.991099 | J36: =(85000/30)*F36/E36*0.8 -> 18.123245 | M36: 水平井 | N36: 唐东 | O36: =N36=C36 -> TRUE | T36: 15.991099 | U36: =ROUND(T36,2) -> 15.99 | V36: 18.123245 | W36: =ROUND(V36,2) -> 18.12
A37: =ROW()-4 -> 33 | B37: 定向井 | C37: 板桥 | D37: 4 | E37: =SUMIFS(转置表!O:O,转置表!L:L,B37,转置表!J:J,C37,转置表!M:M,D37) -> 14474 | F37: =SUMIFS(转置表!T:T,转置表!L:L,B37,转置表!J:J,C37,转置表!M:M,D37) -> 152.77083 | G37: =E37*I37 -> 305541.67 | H37: =E37*J37 -> 346280.56 | I37: =(75000/30)*F37/E37*0.8 -> 21.109691 | J37: =(85000/30)*F37/E37*0.8 -> 23.924316 | M37: 定向井 | N37: 板桥 | O37: =N37=C37 -> TRUE | T37: 21.109691 | U37: =ROUND(T37,2) -> 21.11 | V37: 23.924316 | W37: =ROUND(V37,2) -> 23.92
B38: 定向井 | C38: 常探1 | D38: 3 | E38: 6082 | F38: 52.75 | I38: =(75000/30)*F38/E38*0.8 -> 17.346268 | J38: =(85000/30)*F38/E38*0.8 -> 19.659103
B39: 定向井 | C39: 滨188X1 | D39: 3 | E39: 5220 | F39: 53.5 | I39: =(75000/30)*F39/E39*0.8 -> 20.498084 | J39: =(85000/30)*F39/E39*0.8 -> 23.231162
B40: 定向井 | C40: 孔101-9 | D40: 2 | E40: 1761 | F40: 10 | I40: =(75000/30)*F40/E40*0.8 -> 11.357183 | J40: =(85000/30)*F40/E40*0.8 -> 12.871475
B41: 定向井 | C41: 家29-30 | D41: 2 | E41: 2327 | F41: 14 | I41: =(75000/30)*F41/E41*0.8 -> 12.03266 | J41: =(85000/30)*F41/E41*0.8 -> 13.637015
B42: 定向井 | C42: 官40-67 | D42: 2 | E42: 3092 | F42: 17 | I42: =(75000/30)*F42/E42*0.8 -> 10.996119 | J42: =(85000/30)*F42/E42*0.8 -> 12.462268
B43: 水平井 | C43: 板70-20H | D43: 3 | E43: 2695 | F43: 25.5 | I43: =(75000/30)*F43/E43*0.8 -> 18.923933 | J43: =(85000/30)*F43/E43*0.8 -> 21.447124
B44: 水平井 | C44: 板69-22H | D44: 3 | E44: 2720 | F44: 23.1 | I44: =(75000/30)*F44/E44*0.8 -> 16.985294 | J44: =(85000/30)*F44/E44*0.8 -> 19.25
B45: 定向井 | C45: 官40-61 | D45: 2 | E45: 3092 | F45: 18.5 | I45: =(75000/30)*F45/E45*0.8 -> 11.966365 | J45: =(85000/30)*F45/E45*0.8 -> 13.56188
B46: 定向井 | C46: 塘39-6 | D46: 3 | E46: 4540 | F46: 27.5 | I46: =(75000/30)*F46/E46*0.8 -> 12.114537 | J46: =(85000/30)*F46/E46*0.8 -> 13.729809

Sheet 纯柴油+转化柴油定额 (2)
A1: 附件1-8
A2: 大港油区柴油定额 | M2: 实际 | O2: 预算
G3: 单位：元/米 | M3: 50J | N3: 70D | O3: 50J | P3: 70D
A4: 序号 | B4: 井型 | C4: 区块 | D4: 开次 | E4: 平均井深 | F4: 平均柴油费用 | G4: 米进尺费用 | H4: 备注 | J4: 井型 | K4: 区块 | L4: 开次 | M4: 米进尺费用 | N4: 米进尺费用 | O4: 米进尺费用 | P4: 米进尺费用
A5: 1 | B5: 定向井 | C5: 板桥 | D5: 2 | E5: 3238.6875 | F5: 811397.07 | G5: =F5/E5 -> 250.53268 | J5: 定向井 | K5: 板桥 | L5: 2 | M5: =VLOOKUP(C$5:C$17,#REF!,5,FALSE) -> #REF! | N5: 177.97633 | O5: 209.79978 | P5: 174.7544
A6: 2 | B6: 定向井 | C6: 港东 | D6: 2 | E6: 1917.5 | F6: 251792.16 | G6: =F6/E6 -> 131.31273 | J6: 定向井 | K6: 港东 | L6: 2 | M6: =VLOOKUP(C$5:C$17,#REF!,5,FALSE) -> #REF! | N6: 78.841785 | O6: 119.63445 | P6: 112.38847
A7: 3 | B7: 定向井 | C7: 港西 | D7: 2 | E7: 1516.625 | F7: 268978.12 | G7: =F7/E7 -> 177.35309 | J7: 定向井 | K7: 港西 | L7: 2 | M7: =VLOOKUP(C$5:C$17,#REF!,5,FALSE) -> #REF! | O7: 161.68713
A8: 4 | B8: 定向井 | C8: 港中 | D8: 2 | E8: 2748.5 | F8: 433459 | G8: =F8/E8 -> 157.70748 | J8: 定向井 | K8: 港中 | L8: 2 | M8: =VLOOKUP(C$5:C$17,#REF!,5,FALSE) -> #REF! | O8: 125.71221
A9: 5 | B9: 定向井 | C9: 孔店 | D9: 2 | E9: 1785 | F9: 312767 | G9: =F9/E9 -> 175.21961 | J9: 定向井 | K9: 孔店 | L9: 2 | M9: =VLOOKUP(C$5:C$17,#REF!,5,FALSE) -> #REF! | O9: 152.94118
A10: 6 | B10: 定向井 | C10: 扣村 | D10: 2 | E10: 3026 | F10: 999531 | G10: =F10/E10 -> 330.31428 | J10: 定向井 | K10: 扣村 | L10: 2 | M10: =VLOOKUP(C$5:C$17,#REF!,5,FALSE) -> #REF! | O10: 290.54858
A11: 7 | B11: 定向井 | C11: 泰安 | D11: 2 | E11: 1346 | F11: 312602.51 | G11: =F11/E11 -> 232.24555 | J11: 定向井 | K11: 泰安 | L11: 2 | M11: =VLOOKUP(C$5:C$17,#REF!,5,FALSE) -> #REF! | O11: 284.57652
A12: 8 | B12: 定向井 | C12: 唐家河 | D12: 2 | E12: 3321 | F12: 358453.09 | G12: =F12/E12 -> 107.93529 | J12: 定向井 | K12: 唐家河 | L12: 2 | N12: 111.66366 | P12: 117.93135
A13: 9 | B13: 定向井 | C13: 王官屯 | D13: 2 | E13: 2859 | F13: 559907.9 | G13: =F13/E13 -> 195.84047 | J13: 定向井 | K13: 王官屯 | L13: 2 | M13: =VLOOKUP(C$5:C$17,#REF!,5,FALSE) -> #REF! | O13: 118.60091
A14: 10 | B14: 定向井 | C14: 王徐庄 | D14: 2 | E14: 2468 | F14: 411422.21 | G14: =F14/E14 -> 166.70268 | J14: 定向井 | K14: 王徐庄 | L14: 2 | M14: =VLOOKUP(C$5:C$17,#REF!,5,FALSE) -> #REF! | O14: 110.87115
A15: 11 | B15: 定向井 | C15: 羊二庄 | D15: 2 | E15: 2201 | F15: 311229.61 | G15: =F15/E15 -> 141.40373 | J15: 定向井 | K15: 羊二庄 | L15: 2 | M15: =VLOOKUP(C$5:C$17,#REF!,5,FALSE) -> #REF! | O15: 125.08405
A16: 12 | B16: 定向井 | C16: 羊三木 | D16: 2 | E16: 2775 | F16: 514657 | G16: =F16/E16 -> 185.46198 | J16: 定向井 | K16: 羊三木 | L16: 2 | M16: =VLOOKUP(C$5:C$17,#REF!,5,FALSE) -> #REF! | O16: 119.13874
A17: 13 | B17: 定向井 | C17: 枣园 | D17: 2 | E17: 2658.8 | F17: 765488.1 | G17: =F17/E17 -> 287.90736 | J17: 定向井 | K17: 枣园 | L17: 2 | M17: =VLOOKUP(C$5:C$17,#REF!,5,FALSE) -> #REF! | O17: 198.21047
A18: 14 | B18: 水平井 | C18: 板桥 | D18: 2 | E18: 2642.3333 | F18: 429491.83 | G18: =F18/E18 -> 162.54264 | J18: 水平井 | K18: 板桥 | L18: 2 | M18: =VLOOKUP(C$18:C$19,#REF!,5,FALSE) -> #REF! | N18: 184.2613 | O18: 154.29193 | P18: 185.13188
A19: 15 | B19: 水平井 | C19: 枣园 | D19: 2 | E19: 3896 | F19: 2108266.5 | G19: =F19/E19 -> 541.13615 | J19: 水平井 | K19: 枣园 | L19: 2 | M19: =VLOOKUP(C$18:C$19,#REF!,5,FALSE) -> #REF! | O19: 476.50667
A20: 16 | B20: 直井 | C20: 泰安 | D20: 2 | E20: 1008.5 | F20: 1045813.6 | G20: =F20/E20 -> 1036.9991 | J20: 直井 | K20: 泰安 | L20: 2 | M20: 874.1328 | N20: 1165.1975 | O20: 898.48596 | P20: 930.69473
A21: 17 | B21: 定向井 | C21: 板桥 | D21: 3 | E21: 3779.5 | F21: 998593.55 | G21: =F21/E21 -> 264.21314 | J21: 定向井 | K21: 板桥 | L21: 3 | M21: 245.58341 | N21: 252.38829 | O21: 263.25985 | P21: 239.10375
A22: 18 | B22: 定向井 | C22: 泰安 | D22: 3 | E22: 1107 | F22: 267997.21 | G22: =F22/E22 -> 242.09324 | J22: 定向井 | K22: 泰安 | L22: 3 | M22: 354.11021 | O22: 313.38753
A23: 19 | B23: 定向井 | C23: 唐东 | D23: 3 | E23: 4210 | F23: 1110104.6 | G23: =F23/E23 -> 263.68279 | J23: 定向井 | K23: 唐东 | L23: 3 | N23: 298.27412 | P23: 236.53682
A24: 20 | B24: 定向井 | C24: 新华 | D24: 3 | E24: 5245 | F24: 1200328.6 | G24: =F24/E24 -> 228.85197 | J24: 定向井 | K24: 新华 | L24: 3
A25: 21 | B25: 水平井 | C25: 板桥 | D25: 3 | E25: 2382 | F25: 401511.66 | G25: =F25/E25 -> 168.56073 | J25: 水平井 | K25: 板桥 | L25: 3 | M25: 161.45256 | O25: 130.86062
A26: 22 | B26: 水平井 | C26: 大港页岩油 | D26: 3 | E26: 6182 | F26: 2698592 | G26: =F26/E26 -> 436.52411 | J26: 水平井 | K26: 大港页岩油 | L26: 3
A27: 23 | B27: 直井 | C27: 泰安 | D27: 3 | E27: 1033 | F27: 1168872.8 | G27: =F27/E27 -> 1131.5322 | J27: 直井 | K27: 泰安 | L27: 3 | M27: 1097.7735 | O27: 1079.7483
A28: 24 | B28: 定向井 | C28: 板桥 | D28: 4 | E28: 4942 | F28: 1663166.2 | G28: =F28/E28 -> 336.53708 | J28: 定向井 | K28: 板桥 | L28: 4 | N28: 314.90152 | P28: 297.0689
A29: 25
A30: 26
A31: 27
A32: 28
A33: 29
A34: 30
A35: 31
A36: 32
A37: 33
A38: 34
A39: 35
A40: 36
A41: 37

Sheet 能耗定额（郭）
A1: 附件1-8
A2: 大港油区能耗定额 | N2: 实际 | S2: 预算
A3: 单位：元/米
A4: 序号 | B4: 井型 | C4: 区块 | D4: 开次 | E4: 柴油 | G4: 网电 | I4: 备注 | N4: 50J | O4: 70D | S4: 50J | T4: 70D
E5: 50型 | F5: 70型 | G5: 50型 | H5: 70型 | K5: 井型 | L5: 区块 | M5: 开次 | N5: 米进尺费用 | O5: 米进尺费用 | P5: 井型 | Q5: 区块 | R5: 开次 | S5: 网电定额（度/米） | T5: 网电定额（度/米）
A6: =ROW()-5 -> 1 | B6: 定向井 | C6: 板桥 | D6: 2 | E6: 220.97191 | F6: 177.97633 | H6: 81.547915 | K6: 定向井 | L6: 板桥 | M6: 2 | N6: 220.97191 | O6: 177.97633 | P6: 定向井 | Q6: 扣村 | R6: 2 | S6: 68.759356
A7: =ROW()-5 -> 2 | B7: 定向井 | C7: 港东 | D7: 2 | E7: 104.36664 | F7: 78.841785 | K7: 定向井 | L7: 港东 | M7: 2 | N7: 104.36664 | O7: 78.841785 | P7: 定向井 | Q7: 沈家铺 | R7: 2 | S7: 96.995684
A8: =ROW()-5 -> 3 | B8: 定向井 | C8: 港西 | D8: 2 | E8: 157.50433 | K8: 定向井 | L8: 港西 | M8: 2 | N8: 157.50433 | P8: 定向井 | Q8: 王官屯 | R8: 2 | S8: 109.02016
A9: =ROW()-5 -> 4 | B9: 定向井 | C9: 港中 | D9: 2 | E9: 132.43587 | K9: 定向井 | L9: 港中 | M9: 2 | N9: 132.43587 | P9: 定向井 | Q9: 板桥 | R9: 2 | T9: 81.547915
A10: =ROW()-5 -> 5 | B10: 定向井 | C10: 孔店 | D10: 2 | E10: 152.94118 | K10: 定向井 | L10: 孔店 | M10: 2 | N10: 152.94118 | P10: 定向井 | Q10: 新华 | R10: 2 | T10: 120.54947
A11: =ROW()-5 -> 6 | B11: 定向井 | C11: 扣村 | D11: 2 | G11: 68.759356 | I11: 扣301 | K11: 定向井 | L11: 扣村 | M11: 2 | N11: 290.54858 | P11: 水平井 | Q11: 埕海 | R11: 2 | T11: 127.46669
A12: =ROW()-5 -> 7 | B12: 定向井 | C12: 沈家铺 | D12: 2 | G12: 96.995684 | K12: 定向井 | L12: 泰安 | M12: 2 | N12: 178.38039 | P12: 水平井 | Q12: 大港页岩油 | R12: 2 | T12: 141.06771
A13: =ROW()-5 -> 8 | B13: 定向井 | C13: 泰安 | D13: 2 | E13: 178.38039 | K13: 定向井 | L13: 唐家河 | M13: 2 | O13: 111.66366 | P13: 水平井 | Q13: 枣园 | R13: 2 | T13: 117.03704
A14: =ROW()-5 -> 9 | B14: 定向井 | C14: 唐家河 | D14: 2 | F14: 111.66366 | K14: 定向井 | L14: 王官屯 | M14: 2 | N14: 179.46835 | P14: 定向井 | Q14: 板桥 | R14: 3 | S14: 85.194073 | T14: 106.45691
A15: =ROW()-5 -> 10 | B15: 定向井 | C15: 王官屯 | D15: 2 | E15: 179.46835 | G15: 109.02016 | K15: 定向井 | L15: 王徐庄 | M15: 2 | N15: 195.37388 | P15: 定向井 | Q15: 埕海 | R15: 3 | T15: 173.95264
A16: =ROW()-5 -> 11 | B16: 定向井 | C16: 王徐庄 | D16: 2 | E16: 195.37388 | K16: 定向井 | L16: 羊二庄 | M16: 2 | N16: 136.54487 | P16: 定向井 | Q16: 大港页岩油 | R16: 3 | S16: 118.43114
A17: =ROW()-5 -> 12 | B17: 定向井 | C17: 新华 | D17: 2 | H17: 120.54947 | K17: 定向井 | L17: 羊三木 | M17: 2 | N17: 165.6036 | P17: 定向井 | Q17: 港东 | R17: 3 | S17: 109.82909
A18: =ROW()-5 -> 13 | B18: 定向井 | C18: 羊二庄 | D18: 2 | E18: 136.54487 | K18: 定向井 | L18: 枣园 | M18: 2 | N18: 254.38087 | P18: 定向井 | Q18: 歧口 | R18: 3 | T18: 201.5006
A19: =ROW()-5 -> 14 | B19: 定向井 | C19: 羊三木 | D19: 2 | E19: 165.6036 | K19: 水平井 | L19: 板桥 | M19: 2 | N19: 146.37921 | O19: 184.2613 | P19: 定向井 | Q19: 泰安 | R19: 3 | S19: 350.47731
A20: =ROW()-5 -> 15 | B20: 定向井 | C20: 枣园 | D20: 2 | E20: 254.38087 | K20: 水平井 | L20: 枣园 | M20: 2 | N20: 505.29274 | P20: 定向井 | Q20: 唐东 | R20: 3 | T20: 119.7604
A21: =ROW()-5 -> 16 | B21: 水平井 | C21: 板桥 | D21: 2 | F21: 184.2613 | K21: 直井 | L21: 泰安 | M21: 2 | N21: 874.1328 | O21: 1165.1975 | P21: 定向井 | Q21: 新华 | R21: 3 | S21: 127.31151 | T21: 153.22287
A22: =ROW()-5 -> 17 | B22: 水平井 | C22: 埕海 | D22: 2 | H22: 127.46669 | K22: 定向井 | L22: 板桥 | M22: 3 | N22: 245.58341 | O22: 252.38829 | P22: 水平井 | Q22: 埕海 | R22: 3 | T22: 133.19187
A23: =ROW()-5 -> 18 | B23: 水平井 | C23: 大港页岩油 | D23: 2 | H23: 141.06771 | K23: 定向井 | L23: 泰安 | M23: 3 | N23: 354.11021 | P23: 水平井 | Q23: 大港页岩油 | R23: 3 | T23: 215.84391
A24: =ROW()-5 -> 19 | B24: 水平井 | C24: 枣园 | D24: 2 | H24: 117.03704 | K24: 定向井 | L24: 唐东 | M24: 3 | O24: 298.27412 | P24: 水平井 | Q24: 港东 | R24: 3 | T24: 208.91335
A25: =ROW()-5 -> 20 | B25: 直井 | C25: 泰安 | D25: 2 | E25: 874.1328 | K25: 定向井 | L25: 新华 | M25: 3 | P25: 水平井 | Q25: 唐东 | R25: 3 | T25: 169.06319
A26: =ROW()-5 -> 21 | B26: 定向井 | C26: 板桥 | D26: 3 | E26: 245.58341 | F26: 252.38829 | G26: 85.194073 | H26: 106.45691 | K26: 水平井 | L26: 板桥 | M26: 3 | N26: 161.45256 | P26: 水平井 | Q26: 王官屯 | R26: 3 | T26: 461.76197
A27: =ROW()-5 -> 22 | B27: 定向井 | C27: 埕海 | D27: 3 | H27: 173.95264 | K27: 水平井 | L27: 大港页岩油 | M27: 3 | P27: 水平井 | Q27: 乌马营 | R27: 3 | T27: 158.20908
A28: =ROW()-5 -> 23 | B28: 定向井 | C28: 大港页岩油 | D28: 3 | G28: 118.43114 | K28: 直井 | L28: 泰安 | M28: 3 | N28: 1097.7735 | P28: 水平井 | Q28: 新华 | R28: 3 | T28: 234.32951
A29: =ROW()-5 -> 24 | B29: 定向井 | C29: 港东 | D29: 3 | G29: 109.82909 | K29: 定向井 | L29: 板桥 | M29: 4 | O29: 314.90152 | P29: 直井 | Q29: 泰安 | R29: 3 | S29: 330.23014 | T29: 350.92199
A30: =ROW()-5 -> 25 | B30: 定向井 | C30: 歧口 | D30: 3 | H30: 201.5006 | P30: 定向井 | Q30: 板桥 | R30: 4 | T30: 214.90735
A31: =ROW()-5 -> 26 | B31: 定向井 | C31: 泰安 | D31: 3 | P31: 定向井 | Q31: 青县 | R31: 4 | S31: 191.49786
A32: =ROW()-5 -> 27 | B32: 定向井 | C32: 唐东 | D32: 3 | F32: 298.27412 | H32: 119.7604
A33: =ROW()-5 -> 28 | B33: 定向井 | C33: 新华 | D33: 3 | G33: 127.31151 | H33: 153.22287
A34: =ROW()-5 -> 29 | B34: 水平井 | C34: 板桥 | D34: 3 | E34: 161.45256
A35: =ROW()-5 -> 30 | B35: 水平井 | C35: 埕海 | D35: 3 | H35: 133.19187
A36: =ROW()-5 -> 31 | B36: 水平井 | C36: 大港页岩油 | D36: 3 | H36: 215.84391 | I36: 华页1、官页5-5-1
A37: =ROW()-5 -> 32 | B37: 水平井 | C37: 港东 | D37: 3 | I37: 滨186X1
A38: =ROW()-5 -> 33 | B38: 水平井 | C38: 唐东 | D38: 3 | H38: 169.06319
A39: =ROW()-5 -> 34 | B39: 水平井 | C39: 王官屯 | D39: 3 | I39: 官探1H
A40: =ROW()-5 -> 35 | B40: 水平井 | C40: 乌马营 | D40: 3 | I40: 营105-1-18事故侧钻
A41: =ROW()-5 -> 36 | B41: 水平井 | C41: 新华 | D41: 3 | H41: 234.32951
A42: =ROW()-5 -> 37 | B42: 直井 | C42: 泰安 | D42: 3 | E42: 1097.7735 | G42: 330.23014 | H42: 350.92199
A43: =ROW()-5 -> 38 | B43: 定向井 | C43: 板桥 | D43: 4 | F43: 314.90152 | H43: 214.90735
A44: =ROW()-5 -> 39 | B44: 定向井 | C44: 青县 | D44: 4 | I44: 青热1青热2
A45: 注：冬季施工，能耗定额上浮20%。

Sheet 纯网电+转化网电定额 (4)
A1: 附件1-8
A2: 大港油区网电定额 | N2: 实际 | U2: 预算
G3: 单位：元/米 | L3: 50J | N3: 50J | Q3: 70 | S3: 70D | U3: 50J | V3: 70D
A4: 序号 | B4: 井型 | C4: 区块 | D4: 开次 | E4: 平均井深 | F4: 平均网电费用 | G4: 米进尺费用 | H4: 备注 | J4: 区块 | K4: 求和项:实际井深（米） | L4: 求和项:网电 | M4: 计数项:井号 | N4: 网电定额（度/米） | O4: 区块 | P4: 求和项:实际井深（米） | Q4: 求和项:网电 | R4: 计数项:井号 | S4: 网电定额（度/米） | U4: 网电定额（度/米） | V4: 网电定额（度/米）
A5: 1 | B5: 定向井 | C5: 扣村 | D5: 2 | E5: 2492 | F5: 84202.19 | G5: =F5/E5 -> 33.789001 | H5: 不含架线费 | J5: 扣村 | K5: 2492 | L5: 121011.24 | M5: 1 | N5: 48.559886 | U5: 68.759356
A6: 2 | B6: 定向井 | C6: 沈家铺 | D6: 2 | E6: 3113 | F6: 249235.35 | G6: =F6/E6 -> 80.062753 | J6: 沈家铺 | K6: 3113 | L6: 237827.72 | M6: 1 | N6: 76.398238 | U6: 96.995684
A7: 3 | B7: 定向井 | C7: 王官屯 | D7: 2 | E7: 3503 | F7: 308800.78 | G7: =F7/E7 -> 88.153236 | J7: 王官屯 | K7: 10509 | L7: 1333442.3 | M7: 3 | N7: 126.88575 | U7: 109.02016
B8: 定向井 | C8: 板桥 | D8: 2 | O8: 板桥 | P8: 3603 | Q8: 293817.14 | R8: 1 | S8: 81.547915 | V8: 82.515507
A9: 4 | B9: 定向井 | C9: 新华 | D9: 2 | E9: 4978 | F9: 491041.35 | G9: =F9/E9 -> 98.642297 | O9: 新华 | P9: 9956 | Q9: 1200190.5 | R9: 2 | S9: 120.54947 | V9: 104.80384
A10: 5 | B10: 水平井 | C10: 埕海 | D10: 2 | E10: 4804 | F10: 612350 | G10: =F10/E10 -> 127.46669 | O10: 埕海 | P10: 4804 | Q10: 612350 | R10: 1 | S10: 127.46669 | V10: 86.5102
A11: 6 | B11: 水平井 | C11: 大港页岩油 | D11: 2 | E11: 6191.3333 | F11: 815089.15 | G11: =F11/E11 -> 131.65002 | O11: 大港页岩油 | P11: 18574 | Q11: 2620191.6 | R11: 3 | S11: 141.06771 | V11: 116.0258
A12: 7 | B12: 水平井 | C12: 枣园 | D12: 2 | E12: 4104 | F12: 326617.6 | G12: =F12/E12 -> 79.585185 | O12: 枣园 | P12: 4104 | Q12: 480320 | R12: 1 | S12: 117.03704 | V12: 125.75655
A13: 8 | B13: 定向井 | C13: 板桥 | D13: 3 | E13: 3535 | F13: 208862.62 | G13: =F13/E13 -> 59.084192 | J13: 板桥 | K13: 3535 | L13: 240524.34 | M13: 1 | N13: 68.040833 | O13: 板桥 | P13: 3785 | Q13: 402939.42 | R13: 1 | S13: 106.45691 | U13: 85.194073 | V13: 95.765366 | X13: =U13/V13 -> 0.88961257
A14: 9 | B14: 定向井 | C14: 埕海 | D14: 3 | E14: 5061.5 | F14: 670961.35 | G14: =F14/E14 -> 132.56176 | O14: 埕海 | P14: 10123 | Q14: 1760922.5 | R14: 2 | S14: 173.95264 | V14: 165.49442
A15: 10 | B15: 定向井 | C15: 大港页岩油 | D15: 3 | E15: 3732 | F15: 314369.59 | G15: =F15/E15 -> 84.236225 | J15: 大港页岩油 | K15: 3732 | L15: 643970.04 | M15: 1 | N15: 172.5536 | U15: 118.43114
A16: 11 | B16: 定向井 | C16: 港东 | D16: 3 | E16: 3197 | F16: 348002.09 | G16: =F16/E16 -> 108.8527 | J16: 港东 | K16: 3197 | L16: 408539.33 | M16: 1 | N16: 127.78834 | U16: 109.82909
A17: 12 | B17: 定向井 | C17: 歧口 | D17: 3 | E17: 5157 | F17: 507939.91 | G17: =F17/E17 -> 98.495231 | O17: 歧口 | P17: 10314 | Q17: 2078277.2 | R17: 2 | S17: 201.5006 | V17: 157.33315
A18: 13 | B18: 定向井 | C18: 泰安 | D18: 3 | E18: 1036 | F18: 332087.1 | G18: =F18/E18 -> 320.5474 | J18: 泰安 | K18: 1036 | L18: 380038.95 | M18: 1 | N18: 366.83296 | U18: 350.47731
A19: 14 | B19: 定向井 | C19: 唐东 | D19: 3 | E19: 4792.5 | F19: 662071.99 | G19: =F19/E19 -> 138.14752 | O19: 唐东 | P19: 9585 | Q19: 1147903.4 | R19: 2 | S19: 119.7604 | V19: 114.71367
A20: 15 | B20: 定向井 | C20: 新华 | D20: 3 | E20: 5159 | F20: 544013.82 | G20: =F20/E20 -> 105.44947 | J20: 新华 | K20: 4088 | L20: 488277.15 | M20: 1 | N20: 119.44157 | O20: 新华 | P20: 37356 | Q20: 5723793.4 | R20: 7 | S20: 153.22287 | U20: 127.31151 | V20: 142.75385 | X20: =U20/V20 -> 0.89182536
A21: 16 | B21: 水平井 | C21: 埕海 | D21: 3 | E21: 4109 | F21: 494931 | G21: =F21/E21 -> 120.45047 | O21: 埕海 | P21: 8218 | Q21: 1094570.8 | R21: 2 | S21: 133.19187 | V21: 131.55556
A22: 17 | B22: 水平井 | C22: 大港页岩油 | D22: 3 | E22: 6464 | F22: 1028598.7 | G22: =F22/E22 -> 159.12727 | O22: 大港页岩油 | P22: 57894 | Q22: 12496067 | R22: 9 | S22: 215.84391 | V22: 194.72565
A23: 18 | B23: 水平井 | C23: 港东 | D23: 3 | E23: 5860 | F23: 1109298.9 | G23: =F23/E23 -> 189.30015 | O23: 港东 | P23: 5860 | Q23: 1224232.2 | R23: 1 | S23: 208.91335 | V23: 173.53734
A24: 19 | B24: 水平井 | C24: 唐东 | D24: 3 | E24: 5842 | F24: 984981.64 | G24: =F24/E24 -> 168.6035 | O24: 唐东 | P24: 5842 | Q24: 987667.14 | R24: 1 | S24: 169.06319 | V24: 153.61041
A25: 20 | B25: 水平井 | C25: 王官屯 | D25: 3 | E25: 4741 | F25: 1540824.9 | G25: =F25/E25 -> 324.99998 | O25: 王官屯 | P25: 4741 | Q25: 2189213.5 | R25: 1 | S25: 461.76197 | V25: 461.76197
A26: 21 | B26: 水平井 | C26: 乌马营 | D26: 3 | E26: 4668 | F26: 903409.36 | G26: =F26/E26 -> 193.53242 | O26: 乌马营 | P26: 4668 | Q26: 738520 | R26: 1 | S26: 158.20908 | V26: 135.45889
A27: 22 | B27: 水平井 | C27: 新华 | D27: 3 | E27: 5873 | F27: 839494.2 | G27: =F27/E27 -> 142.94129 | O27: 新华 | P27: 5873 | Q27: 1376217.2 | R27: 1 | S27: 234.32951 | V27: 234.32951
A28: 23 | B28: 直井 | C28: 泰安 | D28: 3 | E28: 1008.33 | F28: 289916 | G28: =F28/E28 -> 287.52095 | J28: 泰安 | K28: 1029.66 | L28: 457400 | M28: 1 | N28: 444.22431 | O28: 泰安 | P28: 987 | Q28: 346360 | R28: 1 | S28: 350.92199 | U28: 330.23014 | V28: 344.50331 | X28: =U28/V28 -> 0.95856885
A29: 24 | B29: 定向井 | C29: 板桥 | D29: 4 | E29: 5345 | F29: 692902.1 | G29: =F29/E29 -> 129.63557 | O29: 板桥 | P29: 15378 | Q29: 3304845.2 | R29: 3 | S29: 214.90735 | V29: 203.52322
A30: 25 | B30: 定向井 | C30: 青县 | D30: 4 | E30: 3774 | F30: 713537.66 | G30: =F30/E30 -> 189.06668 | J30: 青县 | K30: 7548 | L30: 1861950.6 | M30: 2 | N30: 246.68131 | U30: 191.49786
A31: 26
A32: 27
A33: 28
A34: 29
A35: 30
A36: 31
A37: 32
A38: 33
A39: 34
A40: 35
A41: 36
A42: 37
S43: =SUM(S5:S42) -> 3489.7044 | V43: =SUM(V5:V42) -> 3224.6782
U44: =(S43-V43)/V43 -> 0.082186876

Sheet 柴油定额
A1: 附件1-9
A2: 大港油区柴油定额
A3: 序号 | B3: 区块 | C3: 井眼尺寸 （mm） | D3: 平均段长 （m） | E3: 钻机类型（单位：元/米）
E4: 50型机械 | F4: 50型电动 | G4: 70型机械 | H4: 70型电动
A5: =ROW()-4 -> 1 | B5: 板桥 | C5: 660 | D5: 362.9
C6: 444 | D6: 548.61
C7: 311 | D7: 1080.21
C8: 216 | D8: 2148.88
A9: 2 | B9: 港东 | C9: 444 | D9: 651.04
C10: 311 | D10: 1399.99
C11: 216 | D11: 1727.32
A12: 3 | B12: 港西 | C12: 311 | D12: 508.73
C13: 216 | D13: 989.05
A14: 4 | B14: 港中 | C14: 311 | D14: 650.43
C15: 216 | D15: 2056.28
A16: 5 | B16: 孔店 | C16: 311 | D16: 599.95
C17: 216 | D17: 1180.23
A18: 6 | B18: 扣村 | C18: 311 | D18: 592.25
A19: 7 | B19: 沈家铺 | C19: 311 | D19: 808.47
C20: 216 | D20: 2300.6
A21: 8 | B21: 泰安 | C21: 762 | D21: 215.8
C22: 572 | D22: 702
C23: 406 | D23: 61.24
C24: 375 | D24: 91
C25: 241 | D25: 1009
C26: 152 | D26: 347.23
A27: 9 | B27: 唐家河 | C27: 311 | D27: 802.74
C28: 216 | D28: 2515.94
A29: 10 | B29: 王官屯 | C29: 444 | D29: 808.89
C30: 311 | D30: 1058.96
C31: 216 | D31: 2398.03
A32: 11 | B32: 王徐庄 | C32: 311 | D32: 505.65
C33: 216 | D33: 1956.07
A34: 12 | B34: 新华 | C34: 444 | D34: 429.28
C35: 311 | D35: 1970.18
C36: 216 | D36: 3012.844
A37: 13 | B37: 羊二庄 | C37: 444 | D37: 607.93
C38: 216 | D38: 2487.7
A39: 14 | B39: 羊三木 | C39: 311 | D39: 801.36
C40: 216 | D40: 574.92
A41: 15 | B41: 枣园 | C41: 311 | D41: 754.2
C42: 216 | D42: 2285.58
A43: 16 | B43: 埕海 | C43: 444 | D43: 513.63
C44: 311 | D44: 2514.53
C45: 216 | D45: 2604.35
A46: 17 | B46: 大港页岩油 | C46: 444 | D46: 605.46
C47: 311 | D47: 2318.19
C48: 216 | D48: 2891.02
A49: 18 | B49: 歧口 | C49: 444 | D49: 655.79
C50: 311 | D50: 2893.13
C51: 216 | D51: 1580.1
A52: 19 | B52: 唐东 | C52: 444 | D52: 565.3
C53: 311 | D53: 2658.72
C54: 216 | D54: 2347.01
A55: 20 | B55: 乌马营 | C55: 444 | D55: 502
C56: 311 | D56: 1802
C57: 216 | D57: 2329.36
A58: 21 | B58: 青县 | C58: 444 | D58: 662.7
C59: 311 | D59: 1087.8
C60: 216 | D60: 1457.75
C61: 152 | D61: 495

Sheet 8能耗定额
A1: 附件1-8
A2: 大港油区能耗定额（网电） | N2: 2026年完成井
A3: 单位：元/米
A4: 序号 | B4: 井型 | C4: 区块 | D4: 开次 | E4: 累计进尺 | F4: 累计电量 | G4: 米定额 | L4: 井数 | N4: 井号 | O4: 井型 | P4: 区块 | Q4: 开次 | R4: 电量
A5: =ROW()-4 -> 1 | B5: 定向井 | C5: 板桥（＜2500米） | D5: 2 | E5: =SUMIFS(转置表!O:O,转置表!L:L,B5,转置表!J:J,C5,转置表!M:M,D5) -> 3957 | F5: 323056.18 | G5: =F5/E5*0.9 -> 73.477524 | I5: =E5*G5 -> 290750.56 | J5: =K5*E5 -> 261675.51 | K5: =G5*0.9 -> 66.129771 | L5: =COUNTIFS(转置表!L:L,B5,转置表!J:J,C5,转置表!M:M,D5) -> 2 | N5: =转置表!I99 -> 板12-18 | O5: =转置表!L99 -> 定向井 | P5: =转置表!J99 -> 板桥（＜3500米） | Q5: =转置表!M99 -> 2 | R5: 已核完
A6: =ROW()-4 -> 2 | B6: 定向井 | C6: 板桥（＜3500米） | D6: 2 | E6: =SUMIFS(转置表!O:O,转置表!L:L,B6,转置表!J:J,C6,转置表!M:M,D6) -> 44234 | F6: =2239047.30640449+R13+R17+R18+R25+R26 -> 3279717.3 | G6: =F6/E6*0.9 -> 66.730243 | J6: =K6*E6 -> 2656571 | K6: =G6*0.9 -> 60.057219 | L6: =COUNTIFS(转置表!L:L,B6,转置表!J:J,C6,转置表!M:M,D6) -> 14 | N6: =转置表!I100 -> 板14-18 | O6: =转置表!L100 -> 定向井 | P6: =转置表!J100 -> 板桥（＜3500米） | Q6: =转置表!M100 -> 2 | R6: 已核完
A7: =ROW()-4 -> 3 | B7: 定向井 | C7: 板桥（≥3500米） | D7: 2 | E7: =SUMIFS(转置表!O:O,转置表!L:L,B7,转置表!J:J,C7,转置表!M:M,D7) -> 21858 | F7: 2111417.2 | G7: =F7/E7*0.9 -> 86.9373 | J7: =K7*E7 -> 1710248 | K7: =G7*0.9 -> 78.24357 | L7: =COUNTIFS(转置表!L:L,B7,转置表!J:J,C7,转置表!M:M,D7) -> 6 | N7: =转置表!I101 -> 张海31-43 | O7: =转置表!L101 -> 定向井 | P7: =转置表!J101 -> 埕海（≥4000米） | Q7: =转置表!M101 -> 3 | R7: 已核完
A8: =ROW()-4 -> 4 | B8: 定向井 | C8: 港东 | D8: 2 | E8: =SUMIFS(转置表!O:O,转置表!L:L,B8,转置表!J:J,C8,转置表!M:M,D8) -> 3835 | F8: 177165.49 | G8: =F8/E8 -> 46.197 | J8: =K8*E8 -> 159448.95 | K8: =G8*0.9 -> 41.5773 | L8: =COUNTIFS(转置表!L:L,B8,转置表!J:J,C8,转置表!M:M,D8) -> 2 | N8: =转置表!I102 -> 南港13-6 | O8: =转置表!L102 -> 定向井 | P8: =转置表!J102 -> 唐东（开发井） | Q8: =转置表!M102 -> 3 | R8: 已核完
A9: =ROW()-4 -> 5 | B9: 定向井 | C9: 港西 | D9: 2 | E9: =SUMIFS(转置表!O:O,转置表!L:L,B9,转置表!J:J,C9,转置表!M:M,D9) -> 12133 | F9: 788764.04 | G9: =F9/E9 -> 65.009812 | J9: =K9*E9 -> 709887.64 | K9: =G9*0.9 -> 58.50883 | L9: =COUNTIFS(转置表!L:L,B9,转置表!J:J,C9,转置表!M:M,D9) -> 8 | N9: =转置表!I103 -> 南港20-10 | O9: =转置表!L103 -> 定向井 | P9: =转置表!J103 -> 唐东（开发井） | Q9: =转置表!M103 -> 3 | R9: 已核完
A10: =ROW()-4 -> 6 | B10: 定向井 | C10: 港中 | D10: 2 | E10: =SUMIFS(转置表!O:O,转置表!L:L,B10,转置表!J:J,C10,转置表!M:M,D10) -> 5497 | F10: 350561.8 | G10: =F10/E10 -> 63.773294 | J10: =K10*E10 -> 315505.62 | K10: =G10*0.9 -> 57.395965 | L10: =COUNTIFS(转置表!L:L,B10,转置表!J:J,C10,转置表!M:M,D10) -> 2 | N10: =转置表!I104 -> 南港20-6 | O10: =转置表!L104 -> 定向井 | P10: =转置表!J104 -> 唐东（开发井） | Q10: =转置表!M104 -> 3 | R10: 已核完
A11: =ROW()-4 -> 7 | B11: 定向井 | C11: 孔店 | D11: 2 | E11: =SUMIFS(转置表!O:O,转置表!L:L,B11,转置表!J:J,C11,转置表!M:M,D11) -> 3444 | F11: 118752.48 | G11: =F11/E11 -> 34.480976 | J11: =K11*E11 -> 106877.23 | K11: =G11*0.9 -> 31.032878 | L11: =COUNTIFS(转置表!L:L,B11,转置表!J:J,C11,转置表!M:M,D11) -> 2 | N11: =转置表!I105 -> 新华105H | O11: =转置表!L105 -> 水平井 | P11: =转置表!J105 -> 新华 | Q11: =转置表!M105 -> 3 | R11: 1470829.7
A12: =ROW()-4 -> 8 | B12: 定向井 | C12: 扣村 | D12: 2 | E12: =SUMIFS(转置表!O:O,转置表!L:L,B12,转置表!J:J,C12,转置表!M:M,D12) -> 2492 | F12: 125013.67 | G12: =F12/E12 -> 50.166 | J12: =K12*E12 -> 112512.3 | K12: =G12*0.9 -> 45.1494 | L12: =COUNTIFS(转置表!L:L,B12,转置表!J:J,C12,转置表!M:M,D12) -> 1 | N12: =转置表!I106 -> 唐东20X6 | O12: =转置表!L106 -> 定向井 | P12: =转置表!J106 -> 唐东（探评井） | Q12: =转置表!M106 -> 3 | R12: 已核完
A13: =ROW()-4 -> 9 | B13: 定向井 | C13: 唐家河 | D13: 2 | E13: =SUMIFS(转置表!O:O,转置表!L:L,B13,转置表!J:J,C13,转置表!M:M,D13) -> 3321 | F13: 178584.27 | G13: =F13/E13 -> 53.774246 | J13: =K13*E13 -> 160725.84 | K13: =G13*0.9 -> 48.396821 | L13: =COUNTIFS(转置表!L:L,B13,转置表!J:J,C13,转置表!M:M,D13) -> 1 | N13: 板14-16 | O13: 定向井 | P13: =转置表!J107 -> 板桥（＜3500米） | Q13: =转置表!M107 -> 2 | R13: 207405 | S13: 已核完
A14: =ROW()-4 -> 10 | B14: 定向井 | C14: 王官屯 | D14: 2 | E14: =SUMIFS(转置表!O:O,转置表!L:L,B14,转置表!J:J,C14,转置表!M:M,D14) -> 16455 | F14: 991491.19 | G14: =F14/E14 -> 60.254706 | J14: =K14*E14 -> 892342.07 | K14: =G14*0.9 -> 54.229236 | L14: =COUNTIFS(转置表!L:L,B14,转置表!J:J,C14,转置表!M:M,D14) -> 5 | N14: 张海32-38 | O14: 定向井 | P14: 埕海（＜4000米） | Q14: 3 | R14: 278080 | S14: 已核完
A15: =ROW()-4 -> 11 | B15: 定向井 | C15: 王徐庄 | D15: 2 | E15: =SUMIFS(转置表!O:O,转置表!L:L,B15,转置表!J:J,C15,转置表!M:M,D15) -> 2468 | F15: 195776.57 | G15: =F15/E15 -> 79.326 | J15: =K15*E15 -> 176198.91 | K15: =G15*0.9 -> 71.3934 | L15: =COUNTIFS(转置表!L:L,B15,转置表!J:J,C15,转置表!M:M,D15) -> 1 | N15: 南港13-8 | O15: 定向井 | P15: 唐东（开发井） | Q15: 3 | R15: 756437 | S15: 已核完
A16: =ROW()-4 -> 12 | B16: 定向井 | C16: 新华 | D16: 2 | E16: =SUMIFS(转置表!O:O,转置表!L:L,B16,转置表!J:J,C16,转置表!M:M,D16) -> 9956 | F16: 1080171.9 | G16: =F16/E16 -> 108.49457 | J16: =K16*E16 -> 972154.71 | K16: =G16*0.9 -> 97.645109 | L16: =COUNTIFS(转置表!L:L,B16,转置表!J:J,C16,转置表!M:M,D16) -> 2 | N16: 庄海8Nm-L9KH | O16: 水平井 | P16: 埕海 | R16: 1535967.6 | S16: 开窗侧钻 | T16: 开窗侧钻
A17: =ROW()-4 -> 13 | B17: 定向井 | C17: 羊二庄 | D17: 2 | E17: =SUMIFS(转置表!O:O,转置表!L:L,B17,转置表!J:J,C17,转置表!M:M,D17) -> 4402 | F17: 219681.81 | G17: =F17/E17 -> 49.905 | J17: =K17*E17 -> 197713.63 | K17: =G17*0.9 -> 44.9145 | L17: =COUNTIFS(转置表!L:L,B17,转置表!J:J,C17,转置表!M:M,D17) -> 2 | N17: 板14-15 | O17: 定向井 | P17: 板桥（＜3500米） | Q17: 2 | R17: 259771 | S17: 已核完
A18: =ROW()-4 -> 14 | B18: 定向井 | C18: 羊三木 | D18: 2 | E18: =SUMIFS(转置表!O:O,转置表!L:L,B18,转置表!J:J,C18,转置表!M:M,D18) -> 2775 | F18: 229345.42 | G18: =F18/E18 -> 82.647 | J18: =K18*E18 -> 206410.88 | K18: =G18*0.9 -> 74.3823 | L18: =COUNTIFS(转置表!L:L,B18,转置表!J:J,C18,转置表!M:M,D18) -> 1 | N18: 板879-22 | O18: 定向井 | P18: 板桥（＜3500米） | Q18: 2 | R18: 285904
A19: =ROW()-4 -> 15 | B19: 定向井 | C19: 枣园 | D19: 2 | E19: =SUMIFS(转置表!O:O,转置表!L:L,B19,转置表!J:J,C19,转置表!M:M,D19) -> 10593 | F19: 887015.45 | G19: =F19/E19 -> 83.736 | J19: =K19*E19 -> 798313.9 | K19: =G19*0.9 -> 75.3624 | L19: =COUNTIFS(转置表!L:L,B19,转置表!J:J,C19,转置表!M:M,D19) -> 4 | N19: 滨188X1 | O19: 定向井 | P19: 港东 | Q19: 3 | R19: 1410133.2 | S19: 事故 | T19: 事故
A20: =ROW()-4 -> 16 | B20: 水平井 | C20: 板桥 | D20: 2 | E20: =SUMIFS(转置表!O:O,转置表!L:L,B20,转置表!J:J,C20,转置表!M:M,D20) -> 19739 | F20: 1276260.2 | G20: =F20/E20 -> 64.656781 | J20: =K20*E20 -> 1148634.2 | K20: =G20*0.9 -> 58.191103 | L20: =COUNTIFS(转置表!L:L,B20,转置表!J:J,C20,转置表!M:M,D20) -> 8 | N20: 滨海33 | O20: 定向井 | P20: 唐东（探评井） | Q20: 3 | R20: =1792994+20*10000/2.67 -> 1867900.4
A21: =ROW()-4 -> 17 | B21: 水平井 | C21: 埕海 | D21: 2 | E21: =SUMIFS(转置表!O:O,转置表!L:L,B21,转置表!J:J,C21,转置表!M:M,D21) -> 4804 | F21: 604309.57 | G21: =F21/E21 -> 125.793 | J21: =K21*E21 -> 543878.61 | K21: =G21*0.9 -> 113.2137 | L21: =COUNTIFS(转置表!L:L,B21,转置表!J:J,C21,转置表!M:M,D21) -> 1 | N21: 常探1 | O21: 定向井 | P21: 沧东 | Q21: 3 | R21: 1074544 | S21: 已核完
A22: =ROW()-4 -> 18 | B22: 水平井 | C22: 大港页岩油 | D22: 2 | E22: =SUMIFS(转置表!O:O,转置表!L:L,B22,转置表!J:J,C22,转置表!M:M,D22) -> 18574 | F22: 1862764.2 | G22: =F22/E22 -> 100.2888 | J22: =K22*E22 -> 1676487.8 | K22: =G22*0.9 -> 90.25992 | L22: =COUNTIFS(转置表!L:L,B22,转置表!J:J,C22,转置表!M:M,D22) -> 3 | N22: 埕107X5 | O22: 定向井 | P22: 埕海（≥4000米） | Q22: 3 | R22: 458502
A23: =ROW()-4 -> 19 | B23: 水平井 | C23: 枣园 | D23: 2 | E23: =SUMIFS(转置表!O:O,转置表!L:L,B23,转置表!J:J,C23,转置表!M:M,D23) -> 8000 | F23: 705888 | G23: =F23/E23 -> 88.236 | J23: =K23*E23 -> 635299.2 | K23: =G23*0.9 -> 79.4124 | L23: =COUNTIFS(转置表!L:L,B23,转置表!J:J,C23,转置表!M:M,D23) -> 2 | N23: 孔101-9 | O23: 定向井 | P23: 孔店 | Q23: 2 | R23: 207888 | S23: 已核完
A24: =ROW()-4 -> 20 | B24: 定向井 | C24: 板桥 | D24: 3 | E24: =SUMIFS(转置表!O:O,转置表!L:L,B24,转置表!J:J,C24,转置表!M:M,D24) -> 18653 | F24: 1688506.9 | G24: =F24/E24 -> 90.522 | J24: =K24*E24 -> 1519656.2 | K24: =G24*0.9 -> 81.4698 | L24: =COUNTIFS(转置表!L:L,B24,转置表!J:J,C24,转置表!M:M,D24) -> 5 | N24: 张海32-39 | O24: 定向井 | P24: 埕海（＜4000米） | Q24: 3 | R24: 313200
A25: =ROW()-4 -> 21 | B25: 定向井 | C25: 埕海（＜4000米） | D25: 3 | E25: =SUMIFS(转置表!O:O,转置表!L:L,B25,转置表!J:J,C25,转置表!M:M,D25) -> 7594 | F25: =(230005+R14+R23) -> 715973 | G25: =F25/E25*1.1 -> 103.70955 | J25: =K25*E25 -> 708813.27 | K25: =G25*0.9 -> 93.338592 | L25: =COUNTIFS(转置表!L:L,B25,转置表!J:J,C25,转置表!M:M,D25) -> 2 | N25: 板深1601-11 | O25: 定向井 | P25: 板桥（＜3500米） | Q25: 2 | R25: 117834 | S25: 已核完
A26: =ROW()-4 -> 22 | B26: 定向井 | C26: 埕海（≥4000米） | D26: 3 | E26: =SUMIFS(转置表!O:O,转置表!L:L,B26,转置表!J:J,C26,转置表!M:M,D26) -> 23072 | F26: =2186773.9776+R22 -> 2645276 | G26: =F26/E26 -> 114.65309 | J26: =K26*E26 -> 2380748.4 | K26: =G26*0.9 -> 103.18778 | L26: =COUNTIFS(转置表!L:L,B26,转置表!J:J,C26,转置表!M:M,D26) -> 5 | N26: 板深1601-9 | O26: 定向井 | P26: 板桥（＜3500米） | Q26: 2 | R26: 169756 | S26: 已核完
A27: =ROW()-4 -> 23 | B27: 定向井 | C27: 大港页岩油 | D27: 3 | E27: =SUMIFS(转置表!O:O,转置表!L:L,B27,转置表!J:J,C27,转置表!M:M,D27) -> 3732 | F27: 544797.36 | G27: =F27/E27 -> 145.98 | J27: =K27*E27 -> 490317.62 | K27: =G27*0.9 -> 131.382 | L27: =COUNTIFS(转置表!L:L,B27,转置表!J:J,C27,转置表!M:M,D27) -> 1 | N27: 家29-30 | O27: 定向井 | P27: 沈家铺 | Q27: 2 | R27: 100600 | S27: 侧钻
A28: =ROW()-4 -> 24 | B28: 定向井 | C28: 港东 | D28: 3 | E28: =SUMIFS(转置表!O:O,转置表!L:L,B28,转置表!J:J,C28,转置表!M:M,D28) -> 8427 | F28: 367685.39 | G28: =F28/E28 -> 43.631825 | J28: =K28*E28 -> 330916.85 | K28: =G28*0.9 -> 39.268643 | L28: =COUNTIFS(转置表!L:L,B28,转置表!J:J,C28,转置表!M:M,D28) -> 2 | N28: 唐东20X7 | O28: 定向井 | P28: 唐东（探评井） | Q28: 3 | R28: 776554 | S28: 已核完
A29: =ROW()-4 -> 25 | B29: 定向井 | C29: 歧口 | D29: 3 | E29: =SUMIFS(转置表!O:O,转置表!L:L,B29,转置表!J:J,C29,转置表!M:M,D29) -> 10314 | F29: 1473891.2 | G29: =F29/E29 -> 142.902 | J29: =K29*E29 -> 1326502.1 | K29: =G29*0.9 -> 128.6118 | L29: =COUNTIFS(转置表!L:L,B29,转置表!J:J,C29,转置表!M:M,D29) -> 2 | N29: 官40-67 | O29: 定向井 | P29: 王官屯 | Q29: 2 | R29: 254379
A30: =ROW()-4 -> 26 | B30: 定向井 | C30: 唐东（开发井） | D30: 3 | E30: =SUMIFS(转置表!O:O,转置表!L:L,B30,转置表!J:J,C30,转置表!M:M,D30) -> 30995 | F30: =1696475.7+R15+R30+R34 -> 3428013.7 | G30: =F30/E30 -> 110.59893 | J30: =K30*E30 -> 3085212.3 | K30: =G30*0.9 -> 99.539033 | L30: =COUNTIFS(转置表!L:L,B30,转置表!J:J,C30,转置表!M:M,D30) -> 7 | N30: 南港20-9 | O30: 定向井 | P30: 唐东（开发井） | Q30: 3 | R30: 626030 | S30: 已核完
A31: =ROW()-4 -> 27 | B31: 定向井 | C31: 唐东（探评井） | D31: 3 | E31: =SUMIFS(转置表!O:O,转置表!L:L,B31,转置表!J:J,C31,转置表!M:M,D31) -> 27892 | F31: =2340148.28426967+R28+R31 -> 3804249.3 | G31: =F31/E31 -> 136.39213 | J31: =K31*E31 -> 3423824.4 | K31: =G31*0.9 -> 122.75292 | L31: =COUNTIFS(转置表!L:L,B31,转置表!J:J,C31,转置表!M:M,D31) -> 5 | N31: 唐东65X1 | O31: 定向井 | P31: 唐东（探评井） | Q31: 3 | R31: 687547 | S31: 已核完
A32: =ROW()-4 -> 28 | B32: 定向井 | C32: 新华 | D32: 3 | E32: =SUMIFS(转置表!O:O,转置表!L:L,B32,转置表!J:J,C32,转置表!M:M,D32) -> 42074 | F32: 4782603.2 | G32: =F32/E32 -> 113.67123 | J32: =K32*E32 -> 4304342.9 | K32: =G32*0.9 -> 102.3041 | L32: =COUNTIFS(转置表!L:L,B32,转置表!J:J,C32,转置表!M:M,D32) -> 8 | N32: 新华6 | O32: 定向井 | P32: 新华 | Q32: 3 | R32: =1234495+239234 -> 1473729 | S32: 阶段停钻，钻井取心
A33: =ROW()-4 -> 29 | B33: 水平井 | C33: 板桥 | D33: 3 | E33: =SUMIFS(转置表!O:O,转置表!L:L,B33,转置表!J:J,C33,转置表!M:M,D33) -> 0 | F33: 185393.26 | G33: =F33/E33 -> #DIV/0! | J33: =K33*E33 -> #DIV/0! | K33: =G33*0.9 -> #DIV/0! | L33: =COUNTIFS(转置表!L:L,B33,转置表!J:J,C33,转置表!M:M,D33) -> 0 | N33: 张海39-8 | O33: 定向井 | P33: 埕海（≥4000米）侧钻 | Q33: 3 | R33: 621360 | S33: 侧钻
A34: =ROW()-4 -> 30 | B34: 水平井 | C34: 埕海 | D34: 3 | E34: =SUMIFS(转置表!O:O,转置表!L:L,B34,转置表!J:J,C34,转置表!M:M,D34) -> 8218 | F34: 1033766.9 | G34: =F34/E34 -> 125.793 | J34: =K34*E34 -> 930390.19 | K34: =G34*0.9 -> 113.2137 | L34: =COUNTIFS(转置表!L:L,B34,转置表!J:J,C34,转置表!M:M,D34) -> 2 | N34: 南港20-4 | O34: 定向井 | P34: 唐东（开发井） | Q34: 3 | R34: 349071 | S34: 已核完
A35: =ROW()-4 -> 31 | B35: 水平井 | C35: 大港页岩油 | D35: 3 | E35: =SUMIFS(转置表!O:O,转置表!L:L,B35,转置表!J:J,C35,转置表!M:M,D35) -> 43535 | F35: 7231651.1 | G35: =F35/E35 -> 166.1112 | J35: =K35*E35 -> 6508486 | K35: =G35*0.9 -> 149.50008 | L35: =COUNTIFS(转置表!L:L,B35,转置表!J:J,C35,转置表!M:M,D35) -> 7
A36: =ROW()-4 -> 32 | B36: 水平井 | C36: 唐东 | D36: 3 | E36: =SUMIFS(转置表!O:O,转置表!L:L,B36,转置表!J:J,C36,转置表!M:M,D36) -> 5842 | F36: 888900.3 | G36: =F36/E36 -> 152.15685 | J36: =K36*E36 -> 800010.27 | K36: =G36*0.9 -> 136.94116 | L36: =COUNTIFS(转置表!L:L,B36,转置表!J:J,C36,转置表!M:M,D36) -> 1
A37: =ROW()-4 -> 33 | B37: 定向井 | C37: 板桥 | D37: 4 | E37: =SUMIFS(转置表!O:O,转置表!L:L,B37,转置表!J:J,C37,转置表!M:M,D37) -> 14474 | F37: 1983628.5 | G37: =F37/E37 -> 137.0477 | J37: =K37*E37 -> 1785265.6 | K37: =G37*0.9 -> 123.34293 | L37: =COUNTIFS(转置表!L:L,B37,转置表!J:J,C37,转置表!M:M,D37) -> 3
B38: 定向井 | C38: 常探1 | D38: 3 | E38: 6082 | F38: 802335.71 | G38: =F38/E38 -> 131.91972
B39: 定向井 | C39: 滨188X1 | D39: 3 | E39: 5220 | F39: 813573.6 | G39: =F39/E39 -> 155.85701
B40: 定向井 | C40: 孔101-9 | D40: 2 | E40: 1761 | F40: 92215 | G40: =F40/E40 -> 52.365133
B41: 定向井 | C41: 家29-30 | D41: 2 | E41: 2327 | F41: 139322 | G41: =F41/E41 -> 59.871938
B42: 定向井 | C42: 官40-67 | D42: 2 | E42: 3092 | F42: 166995 | G42: =F42/E42 -> 54.008732
B43: 水平井 | C43: 板70-20H | D43: 3 | E43: 2695 | F43: 343374.5 | G43: =F43/E43 -> 127.41169
B44: 水平井 | C44: 板69-22H | D44: 3 | E44: 2720 | F44: 259635.1 | G44: =F44/E44 -> 95.454081
B45: 定向井 | C45: 官40-61 | D45: 2 | E45: 3092 | F45: 184917.75 | G45: =F45/E45 -> 59.805223
B46: 定向井 | C46: 塘39-6 | D46: 3 | E46: 4540 | F46: 343750 | G46: =F46/E46 -> 75.715859
B48: 2.10日修订：能耗下浮10%
B49: 2.13日修订：取心定额按60%核算
B50: 3.12日修订：增加埕海（＜4000米），实际耗电量上浮10%
B51: 6.10日修订：板桥区块能耗下浮10%

Sheet 08能耗定额（2）
A1: 附件1-8
A2: 大港油区能耗定额
A3: 单位：元/米
A4: 区块 | B4: 50型 | E4: 50型电动 | H4: 70型机械 | K4: 70型
B5: 444.5 | C5: 311.1 | D5: 215.9 | E5: 444.5 | F5: 311.1 | G5: 215.9 | H5: 444.5 | I5: 311.1 | J5: 215.9 | K5: 444.5 | L5: 311.1 | M5: 215.9 | P5: 1 | Q5: 定向井 | R5: 板桥
A6: 板桥 | B6: 38.07 | C6: 49.6 | D6: 65.29 | E6: / | F6: / | G6: / | H6: 36.11 | I6: 42.04 | J6: 43.52 | K6: 57.86 | L6: 48.79 | M6: 61.14 | P6: 2 | Q6: 定向井 | R6: 港东 | T6: =1/10000*2.67*7000 -> 1.869
A7: 孔店 | B7: / | C7: / | D7: / | E7: / | F7: / | G7: / | H7: / | I7: / | J7: / | K7: / | L7: 48.24 | M7: 37.87 | P7: 3 | Q7: 定向井 | R7: 港西
A8: 扣村 | B8: / | C8: 43.9 | D8: 64.27 | E8: / | F8: / | G8: / | H8: / | I8: / | J8: / | K8: / | L8: 52.22 | M8: 53.95 | P8: 4 | Q8: 定向井 | R8: 港中
A9: 羊二庄 | B9: 41.53 | C9: 37.43 | D9: 57.54 | E9: / | F9: / | G9: / | H9: / | I9: / | J9: / | K9: / | L9: / | M9: / | P9: 5 | Q9: 定向井 | R9: 孔店
A10: 枣园 | B10: / | C10: 40.88 | D10: 69.27 | E10: / | F10: / | G10: / | H10: / | I10: / | J10: / | K10: / | L10: 62.63 | M10: 116.9 | P10: 6 | Q10: 定向井 | R10: 扣村
A11: 埕海 | B11: / | C11: / | D11: / | E11: / | F11: / | G11: / | H11: / | I11: / | J11: / | K11: 26.24 | L11: 71.48 | P11: 7 | Q11: 定向井 | R11: 沈家铺
A12: 枣园/风化店 | C12: 47.05 | D12: 68.67 | E12: / | F12: / | G12: / | H12: / | I12: / | J12: / | L12: 62.63 | M12: 116.9 | P12: 8 | Q12: 定向井 | R12: 泰安
A13: 歧口 | B13: / | C13: 26.06 | D13: 63.87 | E13: / | F13: / | G13: / | H13: / | I13: / | J13: / | K13: / | L13: / | M13: / | P13: 9 | Q13: 定向井 | R13: 唐家河
A14: 泰安 | B14: / | C14: / | D14: / | E14: / | F14: / | G14: / | H14: / | I14: / | J14: / | K14: 115（762井眼） | L14: 318（571井眼） | M14: / | P14: 10 | Q14: 定向井 | R14: 王官屯
A15: 王官屯 | B15: / | C15: 43.35 | D15: 53.31 | E15: / | F15: / | G15: / | H15: / | I15: 26 | J15: 48.72 | K15: / | L15: 26 | M15: 48.72 | P15: 11 | Q15: 定向井 | R15: 王徐庄
A16: 乌马营 | B16: / | C16: / | D16: / | E16: / | F16: / | G16: / | H16: 46.1 | I16: 39.64 | J16: 143.32 | K16: 46.1 | L16: 39.64 | M16: 143.32 | P16: 12 | Q16: 定向井 | R16: 新华
A17: 青县 | B17: 55.91 | C17: 141.26 | D17: 133.7 | E17: / | F17: / | G17: / | H17: / | I17: / | J17: / | K17: / | L17: / | M17: / | P17: 13 | Q17: 定向井 | R17: 羊二庄
A18: 华页/新华 | B18: / | C18: / | D18: / | E18: / | F18: / | G18: / | H18: / | I18: / | J18: / | K18: 34.33 | L18: 61.4 | M18: 125.32 | P18: 14 | Q18: 定向井 | R18: 羊三木
A19: 唐东/南港 | B19: / | C19: / | D19: / | E19: / | F19: / | G19: / | H19: 41.5 | I19: 63.1 | J19: 200.45 | K19: 41.5 | L19: 63.1 | M19: 200.45 | P19: 15 | Q19: 定向井 | R19: 枣园
A20: 张海 | B20: / | C20: / | D20: / | E20: / | F20: / | G20: / | H20: / | I20: / | J20: / | K20: 53.6 | L20: 81 | M20: 80.91 | P20: 16 | Q20: 水平井 | R20: 板桥
A21: 官页 | B21: / | C21: / | D21: / | E21: / | F21: / | G21: / | H21: / | I21: / | J21: / | K21: 51.44 | L21: 114.9 | M21: 183.43 | P21: 17 | Q21: 水平井 | R21: 埕海
A22: 注：柴油定额与网电定额转换系数为1.869。 | P22: 18 | Q22: 水平井 | R22: 大港页岩油
P23: 19 | Q23: 水平井 | R23: 枣园
P24: 20 | Q24: 直井 | R24: 泰安
P25: 21 | Q25: 定向井 | R25: 板桥
P26: 22 | Q26: 定向井 | R26: 埕海
P27: 23 | Q27: 定向井 | R27: 大港页岩油
P28: 24 | Q28: 定向井 | R28: 港东
P29: 25 | Q29: 定向井 | R29: 歧口
P30: 26 | Q30: 定向井 | R30: 泰安
P31: 27 | Q31: 定向井 | R31: 唐东
P32: 28 | Q32: 定向井 | R32: 新华
P33: 29 | Q33: 水平井 | R33: 板桥
P34: 30 | Q34: 水平井 | R34: 埕海
... P43: 39 | Q43: 定向井 | R43: 青县

Sheet 9润滑油定额 
A1: 附件1-9
A2: 大港油区润滑油定额
H3: 单位：元/米
A4: 序号 | B4: 井型 | C4: 区块 | D4: 开次 | E4: 累计井深 | F4: 累计钻完井周期 | G4: 累计费用 | H4: 米定额 | I4: 备注
A5: =ROW()-4 -> 1 | B5: 定向井 | C5: 板桥（＜2500米） | D5: 2 | E5: =SUMIFS(转置表!O:O,转置表!L:L,B5,转置表!J:J,C5,转置表!M:M,D5) -> 3957 | F5: =SUMIFS(转置表!T:T,转置表!L:L,B5,转置表!J:J,C5,转置表!M:M,D5) -> 25 | G5: =E5*H5 -> 17500 | H5: =(1.05*20000)/30*F5/E5 -> 4.4225423 | J5: 电代油*0.3 | K5: =COUNTIFS(转置表!L:L,B5,转置表!J:J,C5,转置表!M:M,D5) -> 2
A6: =ROW()-4 -> 2 | B6: 定向井 | C6: 板桥（＜3500米） | D6: 2 | E6: =SUMIFS(转置表!O:O,转置表!L:L,B6,转置表!J:J,C6,转置表!M:M,D6) -> 44234 | F6: =SUMIFS(转置表!T:T,转置表!L:L,B6,转置表!J:J,C6,转置表!M:M,D6) -> 264.85417 | G6: =E6*H6 -> 185397.92 | H6: =(1.05*20000)/30*F6/E6 -> 4.1912989
A7: =ROW()-4 -> 3 | B7: 定向井 | C7: 板桥（≥3500米） | D7: 2 | E7: =SUMIFS(转置表!O:O,转置表!L:L,B7,转置表!J:J,C7,转置表!M:M,D7) -> 21858 | F7: =SUMIFS(转置表!T:T,转置表!L:L,B7,转置表!J:J,C7,转置表!M:M,D7) -> 182.66667 | G7: =E7*H7 -> 127866.67 | H7: =(1.05*20000)/30*F7/E7 -> 5.8498795
A8: =ROW()-4 -> 4 | B8: 定向井 | C8: 港东 | D8: 2 | E8: =SUMIFS(转置表!O:O,转置表!L:L,B8,转置表!J:J,C8,转置表!M:M,D8) -> 3835 | F8: =SUMIFS(转置表!T:T,转置表!L:L,B8,转置表!J:J,C8,转置表!M:M,D8) -> 20.104167 | G8: =E8*H8 -> 14072.917 | H8: =(1.05*20000)/30*F8/E8 -> 3.6696002
A9: =ROW()-4 -> 5 | B9: 定向井 | C9: 港西 | D9: 2 | E9: =SUMIFS(转置表!O:O,转置表!L:L,B9,转置表!J:J,C9,转置表!M:M,D9) -> 12133 | F9: =SUMIFS(转置表!T:T,转置表!L:L,B9,转置表!J:J,C9,转置表!M:M,D9) -> 93 | G9: =E9*H9 -> 65100 | H9: =(1.05*20000)/30*F9/E9 -> 5.365532
A10: =ROW()-4 -> 6 | B10: 定向井 | C10: 港中 | D10: 2 | E10: =SUMIFS(转置表!O:O,转置表!L:L,B10,转置表!J:J,C10,转置表!M:M,D10) -> 5497 | F10: =SUMIFS(转置表!T:T,转置表!L:L,B10,转置表!J:J,C10,转置表!M:M,D10) -> 37 | G10: =E10*H10 -> 25900 | H10: =(1.05*20000)/30*F10/E10 -> 4.7116609
A11: =ROW()-4 -> 7 | B11: 定向井 | C11: 孔店 | D11: 2 | E11: =SUMIFS(转置表!O:O,转置表!L:L,B11,转置表!J:J,C11,转置表!M:M,D11) -> 3444 | F11: =SUMIFS(转置表!T:T,转置表!L:L,B11,转置表!J:J,C11,转置表!M:M,D11) -> 30.8125 | G11: =E11*H11 -> 21568.75 | H11: =(1.05*20000)/30*F11/E11 -> 6.2627033
A12: =ROW()-4 -> 8 | B12: 定向井 | C12: 扣村 | D12: 2 | E12: =SUMIFS(转置表!O:O,转置表!L:L,B12,转置表!J:J,C12,转置表!M:M,D12) -> 2492 | F12: =SUMIFS(转置表!T:T,转置表!L:L,B12,转置表!J:J,C12,转置表!M:M,D12) -> 12 | G12: =E12*H12 -> 8400 | H12: =(1.05*20000)/30*F12/E12 -> 3.3707865 | I12: 扣301
A13: =ROW()-4 -> 9 | B13: 定向井 | C13: 唐家河 | D13: 2 | E13: =SUMIFS(转置表!O:O,转置表!L:L,B13,转置表!J:J,C13,转置表!M:M,D13) -> 3321 | F13: =SUMIFS(转置表!T:T,转置表!L:L,B13,转置表!J:J,C13,转置表!M:M,D13) -> 20.416667 | G13: =E13*H13 -> 14291.667 | H13: =(1.05*20000)/30*F13/E13 -> 4.3034227
A14: =ROW()-4 -> 10 | B14: 定向井 | C14: 王官屯 | D14: 2 | E14: =SUMIFS(转置表!O:O,转置表!L:L,B14,转置表!J:J,C14,转置表!M:M,D14) -> 16455 | F14: =SUMIFS(转置表!T:T,转置表!L:L,B14,转置表!J:J,C14,转置表!M:M,D14) -> 142.58333 | G14: =E14*H14 -> 99808.333 | H14: =(1.05*20000)/30*F14/E14 -> 6.0655323
A15: =ROW()-4 -> 11 | B15: 定向井 | C15: 王徐庄 | D15: 2 | E15: =SUMIFS(转置表!O:O,转置表!L:L,B15,转置表!J:J,C15,转置表!M:M,D15) -> 2468 | F15: =SUMIFS(转置表!T:T,转置表!L:L,B15,转置表!J:J,C15,转置表!M:M,D15) -> 16 | G15: =E15*H15 -> 11200 | H15: =(1.05*20000)/30*F15/E15 -> 4.5380875
A16: =ROW()-4 -> 12 | B16: 定向井 | C16: 新华 | D16: 2 | E16: =SUMIFS(转置表!O:O,转置表!L:L,B16,转置表!J:J,C16,转置表!M:M,D16) -> 9956 | F16: =SUMIFS(转置表!T:T,转置表!L:L,B16,转置表!J:J,C16,转置表!M:M,D16) -> 72.791667 | G16: =E16*H16 -> 50954.167 | H16: =(1.05*20000)/30*F16/E16 -> 5.1179356
A17: =ROW()-4 -> 13 | B17: 定向井 | C17: 羊二庄 | D17: 2 | E17: =SUMIFS(转置表!O:O,转置表!L:L,B17,转置表!J:J,C17,转置表!M:M,D17) -> 4402 | F17: =SUMIFS(转置表!T:T,转置表!L:L,B17,转置表!J:J,C17,转置表!M:M,D17) -> 22 | G17: =E17*H17 -> 15400 | H17: =(1.05*20000)/30*F17/E17 -> 3.4984098
A18: =ROW()-4 -> 14 | B18: 定向井 | C18: 羊三木 | D18: 2 | E18: =SUMIFS(转置表!O:O,转置表!L:L,B18,转置表!J:J,C18,转置表!M:M,D18) -> 2775 | F18: =SUMIFS(转置表!T:T,转置表!L:L,B18,转置表!J:J,C18,转置表!M:M,D18) -> 21 | G18: =E18*H18 -> 14700 | H18: =(1.05*20000)/30*F18/E18 -> 5.2972973
A19: =ROW()-4 -> 15 | B19: 定向井 | C19: 枣园 | D19: 2 | E19: =SUMIFS(转置表!O:O,转置表!L:L,B19,转置表!J:J,C19,转置表!M:M,D19) -> 10593 | F19: =SUMIFS(转置表!T:T,转置表!L:L,B19,转置表!J:J,C19,转置表!M:M,D19) -> 71 | G19: =E19*H19 -> 49700 | H19: =(1.05*20000)/30*F19/E19 -> 4.6917776
A20: =ROW()-4 -> 16 | B20: 水平井 | C20: 板桥 | D20: 2 | E20: =SUMIFS(转置表!O:O,转置表!L:L,B20,转置表!J:J,C20,转置表!M:M,D20) -> 19739 | F20: =SUMIFS(转置表!T:T,转置表!L:L,B20,转置表!J:J,C20,转置表!M:M,D20) -> 123.8125 | G20: =E20*H20 -> 86668.75 | H20: =(1.05*20000)/30*F20/E20 -> 4.3907366
A21: =ROW()-4 -> 17 | B21: 水平井 | C21: 埕海 | D21: 2 | E21: =SUMIFS(转置表!O:O,转置表!L:L,B21,转置表!J:J,C21,转置表!M:M,D21) -> 4804 | F21: =SUMIFS(转置表!T:T,转置表!L:L,B21,转置表!J:J,C21,转置表!M:M,D21) -> 38.916667 | G21: =E21*H21 -> 27241.667 | H21: =(1.05*20000)/30*F21/E21 -> 5.6706217
A22: =ROW()-4 -> 18 | B22: 水平井 | C22: 大港页岩油 | D22: 2 | E22: =SUMIFS(转置表!O:O,转置表!L:L,B22,转置表!J:J,C22,转置表!M:M,D22) -> 18574 | F22: =SUMIFS(转置表!T:T,转置表!L:L,B22,转置表!J:J,C22,转置表!M:M,D22) -> 100.52431 | G22: =E22*H22 -> 70367.014 | H22: =(1.05*20000)/30*F22/E22 -> 3.7884685
A23: =ROW()-4 -> 19 | B23: 水平井 | C23: 枣园 | D23: 2 | E23: =SUMIFS(转置表!O:O,转置表!L:L,B23,转置表!J:J,C23,转置表!M:M,D23) -> 8000 | F23: =SUMIFS(转置表!T:T,转置表!L:L,B23,转置表!J:J,C23,转置表!M:M,D23) -> 83.125 | G23: =E23*H23 -> 58187.5 | H23: =(1.05*20000)/30*F23/E23 -> 7.2734375
A24: =ROW()-4 -> 20 | B24: 定向井 | C24: 板桥 | D24: 3 | E24: =SUMIFS(转置表!O:O,转置表!L:L,B24,转置表!J:J,C24,转置表!M:M,D24) -> 18653 | F24: =SUMIFS(转置表!T:T,转置表!L:L,B24,转置表!J:J,C24,转置表!M:M,D24) -> 147 | G24: =E24*H24 -> 102900 | H24: =(1.05*20000)/30*F24/E24 -> 5.5165389
... A34: =ROW()-4 -> 30 | B34: 水平井 | C34: 埕海 | D34: 3 | E34: =SUMIFS(转置表!O:O,转置表!L:L,B34,转置表!J:J,C34,转置表!M:M,D34) -> 8218 | F34: =SUMIFS(转置表!T:T,转置表!L:L,B34,转置表!J:J,C34,转置表!M:M,D34) -> 62 | G34: =E34*H34 -> 43400 | H34: =(1.05*20000)/30*F34/E34 -> 5.2810903
A35: =ROW()-4 -> 31 | B35: 水平井 | C35: 大港页岩油 | D35: 3 | E35: =SUMIFS(转置表!O:O,转置表!L:L,B35,转置表!J:J,C35,转置表!M:M,D35) -> 43535 | F35: =SUMIFS(转置表!T:T,转置表!L:L,B35,转置表!J:J,C35,转置表!M:M,D35) -> 389 | G35: =E35*H35 -> 272300 | H35: =(1.05*20000)/30*F35/E35 -> 6.2547376 | I35: 华页1、官页5-5-1
A36: =ROW()-4 -> 32 | B36: 水平井 | C36: 唐东 | D36: 3 | E36: =SUMIFS(转置表!O:O,转置表!L:L,B36,转置表!J:J,C36,转置表!M:M,D36) -> 5842 | F36: =SUMIFS(转置表!T:T,转置表!L:L,B36,转置表!J:J,C36,转置表!M:M,D36) -> 46.71 | G36: =E36*H36 -> 32697 | H36: =(1.05*20000)/30*F36/E36 -> 5.5968846
A37: =ROW()-4 -> 33 | B37: 定向井 | C37: 板桥 | D37: 4 | E37: =SUMIFS(转置表!O:O,转置表!L:L,B37,转置表!J:J,C37,转置表!M:M,D37) -> 14474 | F37: =SUMIFS(转置表!T:T,转置表!L:L,B37,转置表!J:J,C37,转置表!M:M,D37) -> 152.77083 | G37: =E37*H37 -> 106939.58 | H37: =(1.05*20000)/30*F37/E37 -> 7.3883918
A38: 注：润滑油定额与机型系数挂钩；实施电代油井机油按原定额的30%核算。
B39: 定向井 | C39: 常探1 | D39: 3 | E39: 6082 | F39: 52.75 | H39: =(1.05*20000)/30*F39/E39 -> 6.0711937
B40: 定向井 | C40: 滨188X1 | D40: 3 | E40: 5220 | F40: 53.5 | H40: =(1.05*20000)/30*F40/E40 -> 7.1743295
B41: 定向井 | C41: 孔101-9 | D41: 2 | E41: 1761 | F41: 10 | H41: =(1.05*20000)/30*F41/E41 -> 3.9750142
B42: 定向井 | C42: 家29-30 | D42: 2 | E42: 2327 | F42: 14 | H42: =(1.05*20000)/30*F42/E42 -> 4.211431
B43: 定向井 | C43: 官40-67 | D43: 2 | E43: 3092 | F43: 17 | H43: =(1.05*20000)/30*F43/E43 -> 3.8486417
B44: 水平井 | C44: 板70-20H | D44: 3 | E44: 2695 | F44: 25.5 | H44: =(1.05*20000)/30*F44/E44 -> 6.6233766
B45: 水平井 | C45: 板69-22H | D45: 3 | E45: 2720 | F45: 23.1 | H45: =(1.05*20000)/30*F45/E45 -> 5.9448529
B46: 定向井 | C46: 官40-61 | D46: 2 | E46: 3092 | F46: 18.5 | H46: =(1.05*20000)/30*F46/E46 -> 4.1882277
B47: 定向井 | C47: 塘39-6 | D47: 3 | E47: 4540 | F47: 27.5 | H47: =(1.05*20000)/30*F47/E47 -> 4.2400881
A51: 2.13日修订：取心定额按60%核算

Sheet 10项修定额
A1: 附件1-10
A2: 大港油区项修定额
H3: 单位：元/米
A4: 序号 | B4: 井型 | C4: 区块 | D4: 开次 | E4: 累计井深 | F4: 累计钻完井周期 | G4: 累计费用 | H4: 米定额 | I4: 备注
A5: =ROW()-4 -> 1 | B5: 定向井 | C5: 板桥（＜2500米） | D5: 2 | E5: =SUMIFS(转置表!O:O,转置表!L:L,B5,转置表!J:J,C5,转置表!M:M,D5) -> 3957 | F5: =SUMIFS(转置表!T:T,转置表!L:L,B5,转置表!J:J,C5,转置表!M:M,D5) -> 25 | G5: =E5*H5 -> 8333.3333 | H5: =10000/30*F5/E5 -> 2.1059725
A6: =ROW()-4 -> 2 | B6: 定向井 | C6: 板桥（＜3500米） | D6: 2 | E6: =SUMIFS(转置表!O:O,转置表!L:L,B6,转置表!J:J,C6,转置表!M:M,D6) -> 44234 | F6: =SUMIFS(转置表!T:T,转置表!L:L,B6,转置表!J:J,C6,转置表!M:M,D6) -> 264.85417 | G6: =E6*H6 -> 88284.722 | H6: =10000/30*F6/E6 -> 1.9958566
A7: =ROW()-4 -> 3 | B7: 定向井 | C7: 板桥（≥3500米） | D7: 2 | E7: =SUMIFS(转置表!O:O,转置表!L:L,B7,转置表!J:J,C7,转置表!M:M,D7) -> 21858 | F7: =SUMIFS(转置表!T:T,转置表!L:L,B7,转置表!J:J,C7,转置表!M:M,D7) -> 182.66667 | G7: =E7*H7 -> 60888.889 | H7: =10000/30*F7/E7 -> 2.7856569
A8: =ROW()-4 -> 4 | B8: 定向井 | C8: 港东 | D8: 2 | E8: =SUMIFS(转置表!O:O,转置表!L:L,B8,转置表!J:J,C8,转置表!M:M,D8) -> 3835 | F8: =SUMIFS(转置表!T:T,转置表!L:L,B8,转置表!J:J,C8,转置表!M:M,D8) -> 20.104167 | G8: =E8*H8 -> 6701.3889 | H8: =10000/30*F8/E8 -> 1.7474287
A9: =ROW()-4 -> 5 | B9: 定向井 | C9: 港西 | D9: 2 | E9: =SUMIFS(转置表!O:O,转置表!L:L,B9,转置表!J:J,C9,转置表!M:M,D9) -> 12133 | F9: =SUMIFS(转置表!T:T,转置表!L:L,B9,转置表!J:J,C9,转置表!M:M,D9) -> 93 | G9: =E9*H9 -> 31000 | H9: =10000/30*F9/E9 -> 2.5550152
A10: =ROW()-4 -> 6 | B10: 定向井 | C10: 港中 | D10: 2 | E10: =SUMIFS(转置表!O:O,转置表!L:L,B10,转置表!J:J,C10,转置表!M:M,D10) -> 5497 | F10: =SUMIFS(转置表!T:T,转置表!L:L,B10,转置表!J:J,C10,转置表!M:M,D10) -> 37 | G10: =E10*H10 -> 12333.333 | H10: =10000/30*F10/E10 -> 2.2436481
A11: =ROW()-4 -> 7 | B11: 定向井 | C11: 孔店 | D11: 2 | E11: =SUMIFS(转置表!O:O,转置表!L:L,B11,转置表!J:J,C11,转置表!M:M,D11) -> 3444 | F11: =SUMIFS(转置表!T:T,转置表!L:L,B11,转置表!J:J,C11,转置表!M:M,D11) -> 30.8125 | G11: =E11*H11 -> 10270.833 | H11: =10000/30*F11/E11 -> 2.9822396
A12: =ROW()-4 -> 8 | B12: 定向井 | C12: 扣村 | D12: 2 | E12: =SUMIFS(转置表!O:O,转置表!L:L,B12,转置表!J:J,C12,转置表!M:M,D12) -> 2492 | F12: =SUMIFS(转置表!T:T,转置表!L:L,B12,转置表!J:J,C12,转置表!M:M,D12) -> 12 | G12: =E12*H12 -> 4000 | H12: =10000/30*F12/E12 -> 1.6051364 | I12: 扣301
A13: =ROW()-4 -> 9 | B13: 定向井 | C13: 唐家河 | D13: 2 | E13: =SUMIFS(转置表!O:O,转置表!L:L,B13,转置表!J:J,C13,转置表!M:M,D13) -> 3321 | F13: =SUMIFS(转置表!T:T,转置表!L:L,B13,转置表!J:J,C13,转置表!M:M,D13) -> 20.416667 | G13: =E13*H13 -> 6805.5556 | H13: =10000/30*F13/E13 -> 2.0492489
A14: =ROW()-4 -> 10 | B14: 定向井 | C14: 王官屯 | D14: 2 | E14: =SUMIFS(转置表!O:O,转置表!L:L,B14,转置表!J:J,C14,转置表!M:M,D14) -> 16455 | F14: =SUMIFS(转置表!T:T,转置表!L:L,B14,转置表!J:J,C14,转置表!M:M,D14) -> 142.58333 | G14: =E14*H14 -> 47527.778 | H14: =10000/30*F14/E14 -> 2.8883487
A15: =ROW()-4 -> 11 | B15: 定向井 | C15: 王徐庄 | D15: 2 | E15: =SUMIFS(转置表!O:O,转置表!L:L,B15,转置表!J:J,C15,转置表!M:M,D15) -> 2468 | F15: =SUMIFS(转置表!T:T,转置表!L:L,B15,转置表!J:J,C15,转置表!M:M,D15) -> 16 | G15: =E15*H15 -> 5333.3333 | H15: =10000/30*F15/E15 -> 2.1609941
A16: =ROW()-4 -> 12 | B16: 定向井 | C16: 新华 | D16: 2 | E16: =SUMIFS(转置表!O:O,转置表!L:L,B16,转置表!J:J,C16,转置表!M:M,D16) -> 9956 | F16: =SUMIFS(转置表!T:T,转置表!L:L,B16,转置表!J:J,C16,转置表!M:M,D16) -> 72.791667 | G16: =E16*H16 -> 24263.889 | H16: =10000/30*F16/E16 -> 2.4371122
A17: =ROW()-4 -> 13 | B17: 定向井 | C17: 羊二庄 | D17: 2 | E17: =SUMIFS(转置表!O:O,转置表!L:L,B17,转置表!J:J,C17,转置表!M:M,D17) -> 4402 | F17: =SUMIFS(转置表!T:T,转置表!L:L,B17,转置表!J:J,C17,转置表!M:M,D17) -> 22 | G17: =E17*H17 -> 7333.3333 | H17: =10000/30*F17/E17 -> 1.6659094
A18: =ROW()-4 -> 14 | B18: 定向井 | C18: 羊三木 | D18: 2 | E18: =SUMIFS(转置表!O:O,转置表!L:L,B18,转置表!J:J,C18,转置表!M:M,D18) -> 2775 | F18: =SUMIFS(转置表!T:T,转置表!L:L,B18,转置表!J:J,C18,转置表!M:M,D18) -> 21 | G18: =E18*H18 -> 7000 | H18: =10000/30*F18/E18 -> 2.5225225
A19: =ROW()-4 -> 15 | B19: 定向井 | C19: 枣园 | D19: 2 | E19: =SUMIFS(转置表!O:O,转置表!L:L,B19,转置表!J:J,C19,转置表!M:M,D19) -> 10593 | F19: =SUMIFS(转置表!T:T,转置表!L:L,B19,转置表!J:J,C19,转置表!M:M,D19) -> 71 | G19: =E19*H19 -> 23666.667 | H19: =10000/30*F19/E19 -> 2.2341798
A20: =ROW()-4 -> 16 | B20: 水平井 | C20: 板桥 | D20: 2 | E20: =SUMIFS(转置表!O:O,转置表!L:L,B20,转置表!J:J,C20,转置表!M:M,D20) -> 19739 | F20: =SUMIFS(转置表!T:T,转置表!L:L,B20,转置表!J:J,C20,转置表!M:M,D20) -> 123.8125 | G20: =E20*H20 -> 41270.833 | H20: =10000/30*F20/E20 -> 2.090827
A21: =ROW()-4 -> 17 | B21: 水平井 | C21: 埕海 | D21: 2 | E21: =SUMIFS(转置表!O:O,转置表!L:L,B21,转置表!J:J,C21,转置表!M:M,D21) -> 4804 | F21: =SUMIFS(转置表!T:T,转置表!L:L,B21,转置表!J:J,C21,转置表!M:M,D21) -> 38.916667 | G21: =E21*H21 -> 12972.222 | H21: =10000/30*F21/E21 -> 2.700296
A22: =ROW()-4 -> 18 | B22: 水平井 | C22: 大港页岩油 | D22: 2 | E22: =SUMIFS(转置表!O:O,转置表!L:L,B22,转置表!J:J,C22,转置表!M:M,D22) -> 18574 | F22: =SUMIFS(转置表!T:T,转置表!L:L,B22,转置表!J:J,C22,转置表!M:M,D22) -> 100.52431 | G22: =E22*H22 -> 33508.102 | H22: =10000/30*F22/E22 -> 1.8040326
A23: =ROW()-4 -> 19 | B23: 水平井 | C23: 枣园 | D23: 2 | E23: =SUMIFS(转置表!O:O,转置表!L:L,B23,转置表!J:J,C23,转置表!M:M,D23) -> 8000 | F23: =SUMIFS(转置表!T:T,转置表!L:L,B23,转置表!J:J,C23,转置表!M:M,D23) -> 83.125 | G23: =E23*H23 -> 27708.333 | H23: =10000/30*F23/E23 -> 3.4635417
A24: =ROW()-4 -> 20 | B24: 定向井 | C24: 板桥 | D24: 3 | E24: =SUMIFS(转置表!O:O,转置表!L:L,B24,转置表!J:J,C24,转置表!M:M,D24) -> 18653 | F24: =SUMIFS(转置表!T:T,转置表!L:L,B24,转置表!J:J,C24,转置表!M:M,D24) -> 147 | G24: =E24*H24 -> 49000 | H24: =10000/30*F24/E24 -> 2.6269233
... A34: =ROW()-4 -> 30 | B34: 水平井 | C34: 埕海 | D34: 3 | E34: =SUMIFS(转置表!O:O,转置表!L:L,B34,转置表!J:J,C34,转置表!M:M,D34) -> 8218 | F34: =SUMIFS(转置表!T:T,转置表!L:L,B34,转置表!J:J,C34,转置表!M:M,D34) -> 62 | G34: =E34*H34 -> 20666.667 | H34: =10000/30*F34/E34 -> 2.5148049
A35: =ROW()-4 -> 31 | B35: 水平井 | C35: 大港页岩油 | D35: 3 | E35: =SUMIFS(转置表!O:O,转置表!L:L,B35,转置表!J:J,C35,转置表!M:M,D35) -> 43535 | F35: =SUMIFS(转置表!T:T,转置表!L:L,B35,转置表!J:J,C35,转置表!M:M,D35) -> 389 | G35: =E35*H35 -> 129666.67 | H35: =10000/30*F35/E35 -> 2.9784465 | I35: 华页1、官页5-5-1
A36: =ROW()-4 -> 32 | B36: 水平井 | C36: 唐东 | D36: 3 | E36: =SUMIFS(转置表!O:O,转置表!L:L,B36,转置表!J:J,C36,转置表!M:M,D36) -> 5842 | F36: =SUMIFS(转置表!T:T,转置表!L:L,B36,转置表!J:J,C36,转置表!M:M,D36) -> 46.71 | G36: =E36*H36 -> 15570 | H36: =10000/30*F36/E36 -> 2.6651832
A37: =ROW()-4 -> 33 | B37: 定向井 | C37: 板桥 | D37: 4 | E37: =SUMIFS(转置表!O:O,转置表!L:L,B37,转置表!J:J,C37,转置表!M:M,D37) -> 14474 | F37: =SUMIFS(转置表!T:T,转置表!L:L,B37,转置表!J:J,C37,转置表!M:M,D37) -> 152.77083 | G37: =E37*H37 -> 50923.611 | H37: =10000/30*F37/E37 -> 3.5182818
A38: 注：项修定额与维修系数挂钩。
B39: 定向井 | C39: 常探1 | D39: 3 | E39: 6082 | F39: 52.75 | H39: =10000/30*F39/E39 -> 2.8910446
B40: 定向井 | C40: 滨188X1 | D40: 3 | E40: 5220 | F40: 53.5 | H40: =10000/30*F40/E40 -> 3.4163474
B41: 定向井 | C41: 孔101-9 | D41: 2 | E41: 1761 | F41: 10 | H41: =10000/30*F41/E41 -> 1.8928639
B42: 定向井 | C42: 家29-30 | D42: 2 | E42: 2327 | F42: 14 | H42: =10000/30*F42/E42 -> 2.0054433
B43: 定向井 | C43: 官40-67 | D43: 2 | E43: 3092 | F43: 17 | H43: =10000/30*F43/E43 -> 1.8326865
B44: 水平井 | C44: 板70-20H | D44: 3 | E44: 2695 | F44: 25.5 | H44: =10000/30*F44/E44 -> 3.1539889
B45: 水平井 | C45: 板69-22H | D45: 3 | E45: 2720 | F45: 23.1 | H45: =10000/30*F45/E45 -> 2.8308824
B46: 定向井 | C46: 官40-61 | D46: 2 | E46: 3092 | F46: 18.5 | H46: =10000/30*F46/E46 -> 1.9943941
B47: 定向井 | C47: 塘39-6 | D47: 3 | E47: 4540 | F47: 27.5 | H47: =10000/30*F47/E47 -> 2.0190896
A49: 2.13日修订：取心定额按60%核算

Sheet 11生产水定额
A1: 附件1-11
A2: 大港油区生产水定额
G3: 单位：元/米
A4: 序号 | B4: 井型 | C4: 区块 | D4: 开次 | E4: 累计进尺 | F4: 累计费用 | G4: 米定额 | H4: 备注 | J4: 序号 | K4: 钻头尺寸 | L4: 单位 | M4: 井筒用水
A5: =ROW()-4 -> 1 | B5: 定向井 | C5: 板桥（＜2500米） | D5: 2 | E5: =SUMIFS(转置表!O:O,转置表!L:L,B5,转置表!J:J,C5,转置表!M:M,D5) -> 3957 | F5: 0
A6: =ROW()-4 -> 2 | B6: 定向井 | C6: 板桥（＜3500米） | D6: 2 | E6: =SUMIFS(转置表!O:O,转置表!L:L,B6,转置表!J:J,C6,转置表!M:M,D6) -> 44234 | F6: =104764.941604431+9954+11771+9125+8927+11297 -> 155838.94 | G6: =F6/E6 -> 3.5230579
A7: =ROW()-4 -> 3 | B7: 定向井 | C7: 板桥（≥3500米） | D7: 2 | E7: =SUMIFS(转置表!O:O,转置表!L:L,B7,转置表!J:J,C7,转置表!M:M,D7) -> 21858 | F7: 100586.49 | G7: =F7/E7 -> 4.6018159 | J7: 1 | K7: 660mm | L7: t | M7: 0.68
A8: =ROW()-4 -> 4 | B8: 定向井 | C8: 港东 | D8: 2 | E8: =SUMIFS(转置表!O:O,转置表!L:L,B8,转置表!J:J,C8,转置表!M:M,D8) -> 3835 | F8: 15207.5 | G8: =F8/E8 -> 3.9654498 | J8: 2 | K8: 444mm | L8: t | M8: 0.31
A9: =ROW()-4 -> 5 | B9: 定向井 | C9: 港西 | D9: 2 | E9: =SUMIFS(转置表!O:O,转置表!L:L,B9,转置表!J:J,C9,转置表!M:M,D9) -> 12133 | F9: 53404 | G9: =F9/E9 -> 4.4015495 | J9: 3 | K9: 346mm | L9: t | M9: 0.19
A10: =ROW()-4 -> 6 | B10: 定向井 | C10: 港中 | D10: 2 | E10: =SUMIFS(转置表!O:O,转置表!L:L,B10,转置表!J:J,C10,转置表!M:M,D10) -> 5497 | F10: 19671 | G10: =F10/E10 -> 3.5784974 | J10: 4 | K10: 311mm | L10: t | M10: 0.15
A11: =ROW()-4 -> 7 | B11: 定向井 | C11: 孔店 | D11: 2 | E11: =SUMIFS(转置表!O:O,转置表!L:L,B11,转置表!J:J,C11,转置表!M:M,D11) -> 3444 | F11: 0 | J11: 5 | K11: 245mm | L11: t | M11: 0.09
A12: =ROW()-4 -> 8 | B12: 定向井 | C12: 扣村 | D12: 2 | E12: =SUMIFS(转置表!O:O,转置表!L:L,B12,转置表!J:J,C12,转置表!M:M,D12) -> 2492 | F12: 0 | J12: 6 | K12: 241mm | L12: t | M12: 0.09
A13: =ROW()-4 -> 9 | B13: 定向井 | C13: 唐家河 | D13: 2 | E13: =SUMIFS(转置表!O:O,转置表!L:L,B13,转置表!J:J,C13,转置表!M:M,D13) -> 3321 | F13: 13390.5 | G13: =F13/E13 -> 4.0320687 | J13: 7 | K13: 216mm | L13: t | M13: 0.07
A14: =ROW()-4 -> 10 | B14: 定向井 | C14: 王官屯 | D14: 2 | E14: =SUMIFS(转置表!O:O,转置表!L:L,B14,转置表!J:J,C14,转置表!M:M,D14) -> 16455 | F14: 0 | J14: 8 | K14: 152mm | L14: t | M14: 0.04
A15: =ROW()-4 -> 11 | B15: 定向井 | C15: 王徐庄 | D15: 2 | E15: =SUMIFS(转置表!O:O,转置表!L:L,B15,转置表!J:J,C15,转置表!M:M,D15) -> 2468 | F15: 0 | J15: 9 | K15: 118mm | L15: t | M15: 0.02
A16: =ROW()-4 -> 12 | B16: 定向井 | C16: 新华 | D16: 2 | E16: =SUMIFS(转置表!O:O,转置表!L:L,B16,转置表!J:J,C16,转置表!M:M,D16) -> 9956 | F16: 0
A17: =ROW()-4 -> 13 | B17: 定向井 | C17: 羊二庄 | D17: 2 | E17: =SUMIFS(转置表!O:O,转置表!L:L,B17,转置表!J:J,C17,转置表!M:M,D17) -> 4402 | F17: 0
A18: =ROW()-4 -> 14 | B18: 定向井 | C18: 羊三木 | D18: 2 | E18: =SUMIFS(转置表!O:O,转置表!L:L,B18,转置表!J:J,C18,转置表!M:M,D18) -> 2775 | F18: 0
A19: =ROW()-4 -> 15 | B19: 定向井 | C19: 枣园 | D19: 2 | E19: =SUMIFS(转置表!O:O,转置表!L:L,B19,转置表!J:J,C19,转置表!M:M,D19) -> 10593 | F19: 0
A20: =ROW()-4 -> 16 | B20: 水平井 | C20: 板桥 | D20: 2 | E20: =SUMIFS(转置表!O:O,转置表!L:L,B20,转置表!J:J,C20,转置表!M:M,D20) -> 19739 | F20: 79872.964 | G20: =F20/E20 -> 4.0464544
A21: =ROW()-4 -> 17 | B21: 水平井 | C21: 埕海 | D21: 2 | E21: =SUMIFS(转置表!O:O,转置表!L:L,B21,转置表!J:J,C21,转置表!M:M,D21) -> 4804 | F21: 0
A22: =ROW()-4 -> 18 | B22: 水平井 | C22: 大港页岩油 | D22: 2 | E22: =SUMIFS(转置表!O:O,转置表!L:L,B22,转置表!J:J,C22,转置表!M:M,D22) -> 18574 | F22: 0
A23: =ROW()-4 -> 19 | B23: 水平井 | C23: 枣园 | D23: 2 | E23: =SUMIFS(转置表!O:O,转置表!L:L,B23,转置表!J:J,C23,转置表!M:M,D23) -> 8000 | F23: 0
A24: =ROW()-4 -> 20 | B24: 定向井 | C24: 板桥 | D24: 3 | E24: =SUMIFS(转置表!O:O,转置表!L:L,B24,转置表!J:J,C24,转置表!M:M,D24) -> 18653 | F24: 79632 | G24: =F24/E24 -> 4.2691256
A25: =ROW()-4 -> 21 | B25: 定向井 | C25: 埕海（＜4000米） | D25: 3 | E25: =SUMIFS(转置表!O:O,转置表!L:L,B25,转置表!J:J,C25,转置表!M:M,D25) -> 7594 | F25: 0
A26: =ROW()-4 -> 22 | B26: 定向井 | C26: 埕海（≥4000米） | D26: 3 | E26: =SUMIFS(转置表!O:O,转置表!L:L,B26,转置表!J:J,C26,转置表!M:M,D26) -> 23072 | F26: 0
A27: =ROW()-4 -> 23 | B27: 定向井 | C27: 大港页岩油 | D27: 3 | E27: =SUMIFS(转置表!O:O,转置表!L:L,B27,转置表!J:J,C27,转置表!M:M,D27) -> 3732 | F27: 0
A28: =ROW()-4 -> 24 | B28: 定向井 | C28: 港东 | D28: 3 | E28: =SUMIFS(转置表!O:O,转置表!L:L,B28,转置表!J:J,C28,转置表!M:M,D28) -> 8427 | F28: 0
A29: =ROW()-4 -> 25 | B29: 定向井 | C29: 歧口 | D29: 3 | E29: =SUMIFS(转置表!O:O,转置表!L:L,B29,转置表!J:J,C29,转置表!M:M,D29) -> 10314 | F29: 0 | K29: 4.82 | L29: =K29*E29 -> 49713.48
A30: =ROW()-4 -> 26 | B30: 定向井 | C30: 唐东（开发井） | D30: 3 | E30: =SUMIFS(转置表!O:O,转置表!L:L,B30,转置表!J:J,C30,转置表!M:M,D30) -> 30995 | F30: 83800.52 | G30: =F30/E30 -> 2.7036787 | K30: 4.82 | L30: =K30*E30 -> 149395.9
A31: =ROW()-4 -> 27 | B31: 定向井 | C31: 唐东（探评井） | D31: 3 | E31: =SUMIFS(转置表!O:O,转置表!L:L,B31,转置表!J:J,C31,转置表!M:M,D31) -> 27892 | F31: 100169.56 | G31: =F31/E31 -> 3.5913366 | K31: 5.93 | L31: =K31*E31 -> 165399.56
A32: =ROW()-4 -> 28 | B32: 定向井 | C32: 新华 | D32: 3 | E32: =SUMIFS(转置表!O:O,转置表!L:L,B32,转置表!J:J,C32,转置表!M:M,D32) -> 42074 | F32: 0
A33: =ROW()-4 -> 29 | B33: 水平井 | C33: 板桥 | D33: 3 | E33: =SUMIFS(转置表!O:O,转置表!L:L,B33,转置表!J:J,C33,转置表!M:M,D33) -> 0 | F33: 10169.057 | G33: =F33/E33 -> #DIV/0!
A34: =ROW()-4 -> 30 | B34: 水平井 | C34: 埕海 | D34: 3 | E34: =SUMIFS(转置表!O:O,转置表!L:L,B34,转置表!J:J,C34,转置表!M:M,D34) -> 8218 | F34: 0
A35: =ROW()-4 -> 31 | B35: 水平井 | C35: 大港页岩油 | D35: 3 | E35: =SUMIFS(转置表!O:O,转置表!L:L,B35,转置表!J:J,C35,转置表!M:M,D35) -> 43535 | F35: 0
A36: =ROW()-4 -> 32 | B36: 水平井 | C36: 唐东 | D36: 3 | E36: =SUMIFS(转置表!O:O,转置表!L:L,B36,转置表!J:J,C36,转置表!M:M,D36) -> 5842 | F36: 36624.232 | G36: =F36/E36 -> 6.2691256
A37: =ROW()-4 -> 33 | B37: 定向井 | C37: 板桥 | D37: 4 | E37: =SUMIFS(转置表!O:O,转置表!L:L,B37,转置表!J:J,C37,转置表!M:M,D37) -> 14474 | F37: 84135 | G37: =F37/E37 -> 5.8128368
A39: 2.13日修订：取心定额按60%核算

Sheet 12生活污水定额
A1: 附件1-12
A2: 大港油区生活污水定额
H3: 单位：元/米
A4: 序号 | B4: 井型 | C4: 区块 | D4: 开次 | E4: 累计井深 | F4: 累计钻完井周期 | G4: 累计费用 | H4: 米定额 | I4: 备注
A5: =ROW()-4 -> 1 | B5: 定向井 | C5: 板桥（＜2500米） | D5: 2 | E5: =SUMIFS(转置表!O:O,转置表!L:L,B5,转置表!J:J,C5,转置表!M:M,D5) -> 3957 | F5: =SUMIFS(转置表!T:T,转置表!L:L,B5,转置表!J:J,C5,转置表!M:M,D5) -> 25 | G5: =E5*H5 -> 8333.3333 | H5: =(100*100)/30*F5/E5 -> 2.1059725
A6: =ROW()-4 -> 2 | B6: 定向井 | C6: 板桥（＜3500米） | D6: 2 | E6: =SUMIFS(转置表!O:O,转置表!L:L,B6,转置表!J:J,C6,转置表!M:M,D6) -> 44234 | F6: =SUMIFS(转置表!T:T,转置表!L:L,B6,转置表!J:J,C6,转置表!M:M,D6) -> 264.85417 | G6: =E6*H6 -> 88284.722 | H6: =(100*100)/30*F6/E6 -> 1.9958566
A7: =ROW()-4 -> 3 | B7: 定向井 | C7: 板桥（≥3500米） | D7: 2 | E7: =SUMIFS(转置表!O:O,转置表!L:L,B7,转置表!J:J,C7,转置表!M:M,D7) -> 21858 | F7: =SUMIFS(转置表!T:T,转置表!L:L,B7,转置表!J:J,C7,转置表!M:M,D7) -> 182.66667 | G7: =E7*H7 -> 60888.889 | H7: =(100*100)/30*F7/E7 -> 2.7856569
A8: =ROW()-4 -> 4 | B8: 定向井 | C8: 港东 | D8: 2 | E8: =SUMIFS(转置表!O:O,转置表!L:L,B8,转置表!J:J,C8,转置表!M:M,D8) -> 3835 | F8: =SUMIFS(转置表!T:T,转置表!L:L,B8,转置表!J:J,C8,转置表!M:M,D8) -> 20.104167 | G8: =E8*H8 -> 6701.3889 | H8: =(100*100)/30*F8/E8 -> 1.7474287
A9: =ROW()-4 -> 5 | B9: 定向井 | C9: 港西 | D9: 2 | E9: =SUMIFS(转置表!O:O,转置表!L:L,B9,转置表!J:J,C9,转置表!M:M,D9) -> 12133 | F9: =SUMIFS(转置表!T:T,转置表!L:L,B9,转置表!J:J,C9,转置表!M:M,D9) -> 93 | G9: =E9*H9 -> 31000 | H9: =(100*100)/30*F9/E9 -> 2.5550152
A10: =ROW()-4 -> 6 | B10: 定向井 | C10: 港中 | D10: 2 | E10: =SUMIFS(转置表!O:O,转置表!L:L,B10,转置表!J:J,C10,转置表!M:M,D10) -> 5497 | F10: =SUMIFS(转置表!T:T,转置表!L:L,B10,转置表!J:J,C10,转置表!M:M,D10) -> 37 | G10: =E10*H10 -> 12333.333 | H10: =(100*100)/30*F10/E10 -> 2.2436481
A11: =ROW()-4 -> 7 | B11: 定向井 | C11: 孔店 | D11: 2 | E11: =SUMIFS(转置表!O:O,转置表!L:L,B11,转置表!J:J,C11,转置表!M:M,D11) -> 3444 | F11: =SUMIFS(转置表!T:T,转置表!L:L,B11,转置表!J:J,C11,转置表!M:M,D11) -> 30.8125 | G11: =E11*H11 -> 10270.833 | H11: =(100*100)/30*F11/E11 -> 2.9822396
A12: =ROW()-4 -> 8 | B12: 定向井 | C12: 扣村 | D12: 2 | E12: =SUMIFS(转置表!O:O,转置表!L:L,B12,转置表!J:J,C12,转置表!M:M,D12) -> 2492 | F12: =SUMIFS(转置表!T:T,转置表!L:L,B12,转置表!J:J,C12,转置表!M:M,D12) -> 12 | G12: =E12*H12 -> 4000 | H12: =(100*100)/30*F12/E12 -> 1.6051364 | I12: 扣301
A13: =ROW()-4 -> 9 | B13: 定向井 | C13: 唐家河 | D13: 2 | E13: =SUMIFS(转置表!O:O,转置表!L:L,B13,转置表!J:J,C13,转置表!M:M,D13) -> 3321 | F13: =SUMIFS(转置表!T:T,转置表!L:L,B13,转置表!J:J,C13,转置表!M:M,D13) -> 20.416667 | G13: =E13*H13 -> 6805.5556 | H13: =(100*100)/30*F13/E13 -> 2.0492489
A14: =ROW()-4 -> 10 | B14: 定向井 | C14: 王官屯 | D14: 2 | E14: =SUMIFS(转置表!O:O,转置表!L:L,B14,转置表!J:J,C14,转置表!M:M,D14) -> 16455 | F14: =SUMIFS(转置表!T:T,转置表!L:L,B14,转置表!J:J,C14,转置表!M:M,D14) -> 142.58333 | G14: =E14*H14 -> 47527.778 | H14: =(100*100)/30*F14/E14 -> 2.8883487
A15: =ROW()-4 -> 11 | B15: 定向井 | C15: 王徐庄 | D15: 2 | E15: =SUMIFS(转置表!O:O,转置表!L:L,B15,转置表!J:J,C15,转置表!M:M,D15) -> 2468 | F15: =SUMIFS(转置表!T:T,转置表!L:L,B15,转置表!J:J,C15,转置表!M:M,D15) -> 16 | G15: =E15*H15 -> 5333.3333 | H15: =(100*100)/30*F15/E15 -> 2.1609941
A16: =ROW()-4 -> 12 | B16: 定向井 | C16: 新华 | D16: 2 | E16: =SUMIFS(转置表!O:O,转置表!L:L,B16,转置表!J:J,C16,转置表!M:M,D16) -> 9956 | F16: =SUMIFS(转置表!T:T,转置表!L:L,B16,转置表!J:J,C16,转置表!M:M,D16) -> 72.791667 | G16: =E16*H16 -> 24263.889 | H16: =(100*100)/30*F16/E16 -> 2.4371122
A17: =ROW()-4 -> 13 | B17: 定向井 | C17: 羊二庄 | D17: 2 | E17: =SUMIFS(转置表!O:O,转置表!L:L,B17,转置表!J:J,C17,转置表!M:M,D17) -> 4402 | F17: =SUMIFS(转置表!T:T,转置表!L:L,B17,转置表!J:J,C17,转置表!M:M,D17) -> 22 | G17: =E17*H17 -> 7333.3333 | H17: =(100*100)/30*F17/E17 -> 1.6659094
A18: =ROW()-4 -> 14 | B18: 定向井 | C18: 羊三木 | D18: 2 | E18: =SUMIFS(转置表!O:O,转置表!L:L,B18,转置表!J:J,C18,转置表!M:M,D18) -> 2775 | F18: =SUMIFS(转置表!T:T,转置表!L:L,B18,转置表!J:J,C18,转置表!M:M,D18) -> 21 | G18: =E18*H18 -> 7000 | H18: =(100*100)/30*F18/E18 -> 2.5225225
A19: =ROW()-4 -> 15 | B19: 定向井 | C19: 枣园 | D19: 2 | E19: =SUMIFS(转置表!O:O,转置表!L:L,B19,转置表!J:J,C19,转置表!M:M,D19) -> 10593 | F19: =SUMIFS(转置表!T:T,转置表!L:L,B19,转置表!J:J,C19,转置表!M:M,D19) -> 71 | G19: =E19*H19 -> 23666.667 | H19: =(100*100)/30*F19/E19 -> 2.2341798
A20: =ROW()-4 -> 16 | B20: 水平井 | C20: 板桥 | D20: 2 | E20: =SUMIFS(转置表!O:O,转置表!L:L,B20,转置表!J:J,C20,转置表!M:M,D20) -> 19739 | F20: =SUMIFS(转置表!T:T,转置表!L:L,B20,转置表!J:J,C20,转置表!M:M,D20) -> 123.8125 | G20: =E20*H20 -> 41270.833 | H20: =(100*100)/30*F20/E20 -> 2.090827
A21: =ROW()-4 -> 17 | B21: 水平井 | C21: 埕海 | D21: 2 | E21: =SUMIFS(转置表!O:O,转置表!L:L,B21,转置表!J:J,C21,转置表!M:M,D21) -> 4804 | F21: =SUMIFS(转置表!T:T,转置表!L:L,B21,转置表!J:J,C21,转置表!M:M,D21) -> 38.916667 | G21: =E21*H21 -> 12972.222 | H21: =(100*100)/30*F21/E21 -> 2.700296
A22: =ROW()-4 -> 18 | B22: 水平井 | C22: 大港页岩油 | D22: 2 | E22: =SUMIFS(转置表!O:O,转置表!L:L,B22,转置表!J:J,C22,转置表!M:M,D22) -> 18574 | F22: =SUMIFS(转置表!T:T,转置表!L:L,B22,转置表!J:J,C22,转置表!M:M,D22) -> 100.52431 | G22: =E22*H22 -> 33508.102 | H22: =(100*100)/30*F22/E22 -> 1.8040326
A23: =ROW()-4 -> 19 | B23: 水平井 | C23: 枣园 | D23: 2 | E23: =SUMIFS(转置表!O:O,转置表!L:L,B23,转置表!J:J,C23,转置表!M:M,D23) -> 8000 | F23: =SUMIFS(转置表!T:T,转置表!L:L,B23,转置表!J:J,C23,转置表!M:M,D23) -> 83.125 | G23: =E23*H23 -> 27708.333 | H23: =(100*100)/30*F23/E23 -> 3.4635417
A24: =ROW()-4 -> 20 | B24: 定向井 | C24: 板桥 | D24: 3 | E24: =SUMIFS(转置表!O:O,转置表!L:L,B24,转置表!J:J,C24,转置表!M:M,D24) -> 18653 | F24: =SUMIFS(转置表!T:T,转置表!L:L,B24,转置表!J:J,C24,转置表!M:M,D24) -> 147 | G24: =E24*H24 -> 49000 | H24: =(100*100)/30*F24/E24 -> 2.6269233
... A34: =ROW()-4 -> 30 | B34: 水平井 | C34: 埕海 | D34: 3 | E34: =SUMIFS(转置表!O:O,转置表!L:L,B34,转置表!J:J,C34,转置表!M:M,D34) -> 8218 | F34: =SUMIFS(转置表!T:T,转置表!L:L,B34,转置表!J:J,C34,转置表!M:M,D34) -> 62 | G34: =E34*H34 -> 20666.667 | H34: =(100*100)/30*F34/E34 -> 2.5148049
A35: =ROW()-4 -> 31 | B35: 水平井 | C35: 大港页岩油 | D35: 3 | E35: =SUMIFS(转置表!O:O,转置表!L:L,B35,转置表!J:J,C35,转置表!M:M,D35) -> 43535 | F35: =SUMIFS(转置表!T:T,转置表!L:L,B35,转置表!J:J,C35,转置表!M:M,D35) -> 389 | G35: =E35*H35 -> 129666.67 | H35: =(100*100)/30*F35/E35 -> 2.9784465 | I35: 华页1、官页5-5-1
A36: =ROW()-4 -> 32 | B36: 水平井 | C36: 唐东 | D36: 3 | E36: =SUMIFS(转置表!O:O,转置表!L:L,B36,转置表!J:J,C36,转置表!M:M,D36) -> 5842 | F36: =SUMIFS(转置表!T:T,转置表!L:L,B36,转置表!J:J,C36,转置表!M:M,D36) -> 46.71 | G36: =E36*H36 -> 15570 | H36: =(100*100)/30*F36/E36 -> 2.6651832
A37: =ROW()-4 -> 33 | B37: 定向井 | C37: 板桥 | D37: 4 | E37: =SUMIFS(转置表!O:O,转置表!L:L,B37,转置表!J:J,C37,转置表!M:M,D37) -> 14474 | F37: =SUMIFS(转置表!T:T,转置表!L:L,B37,转置表!J:J,C37,转置表!M:M,D37) -> 152.77083 | G37: =E37*H37 -> 50923.611 | H37: =(100*100)/30*F37/E37 -> 3.5182818
B38: 定向井 | C38: 常探1 | D38: 3 | E38: 6082 | F38: 52.75 | H38: =(100*100)/30*F38/E38 -> 2.8910446
B39: 定向井 | C39: 滨188X1 | D39: 3 | E39: 5220 | F39: 53.5 | H39: =(100*100)/30*F39/E39 -> 3.4163474
B40: 定向井 | C40: 孔101-9 | D40: 2 | E40: 1761 | F40: 10 | H40: =(100*100)/30*F40/E40 -> 1.8928639
B41: 定向井 | C41: 家29-30 | D41: 2 | E41: 2327 | F41: 14 | H41: =(100*100)/30*F41/E41 -> 2.0054433
B42: 定向井 | C42: 官40-67 | D42: 2 | E42: 3092 | F42: 17 | H42: =(100*100)/30*F42/E42 -> 1.8326865
B43: 水平井 | C43: 板70-20H | D43: 3 | E43: 2695 | F43: 25.5 | H43: =(100*100)/30*F43/E43 -> 3.1539889
B44: 水平井 | C44: 板69-22H | D44: 3 | E44: 2720 | F44: 23.1 | H44: =(100*100)/30*F44/E44 -> 2.8308824
B45: 定向井 | C45: 官40-61 | D45: 2 | E45: 3092 | F45: 18.5 | H45: =(100*100)/30*F45/E45 -> 1.9943941
B46: 定向井 | C46: 塘39-6 | D46: 3 | E46: 4540 | F46: 27.5 | H46: =(100*100)/30*F46/E46 -> 2.0190896

Sheet 13土工膜定额
A1: 附件1-13
A2: 土工膜定额
G3: 单位：元/口井
A4: 序号 | B4: 工序 | C4: 机型 | D4: 单位 | E4: 数量（卷） | F4: 单价（元/公斤） | G4: 定额 | H4: 备注
A5: 1 | B5: 搬迁 | C5: 50型 | D5: 卷/井次 | E5: 11 | F5: 6.97 | G5: =E5*F5*150 -> 11500.5
A6: 2 | B6: 搬迁 | C6: 70型 | D6: 卷/井次 | E6: 12 | F6: 6.97 | G6: =E6*F6*150 -> 12546
A7: 3 | B7: 平移 | D7: 卷/井次 | E7: 4 | F7: 6.97 | G7: =E7*F7*150 -> 4182

Sheet 14钻机挂钩系数
A1: 附件1-14
A2: 钻机挂钩系数
A3: 序号 | B3: 队号 | C3: 钻机类型 | D3: 机型系数 | E3: 维修系数
A4: 1 | B4: 50639 | C4: 50LD | D4: 1.0232583 | E4: 1.5
A5: 2 | B5: 50537 | C5: 50J | D5: 0.68771345 | E5: 1.35
A6: 3 | B6: 50998 | C6: 50J | D6: 0.52873745 | E6: 1.35
A7: 4 | B7: 70520 | C7: 70LD | D7: 1.3726924 | E7: 1.5
A8: 5 | B8: 70111 | C8: 70D | D8: 0.90897065 | E8: 1.05
A9: 6 | B9: 70152 | C9: 70D | D9: 0.83591825 | E9: 1.05
A10: 7 | B10: 70316 | C10: 70D | D10: 0.8965547 | E10: 0.42
A11: 8 | B11: 70318 | C11: 70DB | D11: 1.0842563 | E11: 0.42
A12: 9 | B12: 70315 | C12: 70DB | D12: 0.9171607 | E12: 0.28
A13: 10 | B13: BH70302 | C13: 70DB | D13: 1.013156 | E13: 0.7
A14: 注：润滑油定额与机型系数挂钩；项修定额与维修系数挂钩。

Sheet 15区块平均日进尺
A1: 附件1-15
A2: 大港油区区块平均日进尺
G3: 单位：米/天
A4: 序号 | B4: 井型 | C4: 区块 | D4: 开次 | E4: 平均井深 | F4: 平均钻完井周期 | G4: 平均日进尺 | H4: 备注
A5: =ROW()-4 -> 1 | B5: 定向井 | C5: 板桥（＜2500米） | D5: 2 | E5: =SUMIFS(转置表!O:O,转置表!L:L,B5,转置表!J:J,C5,转置表!M:M,D5)/COUNTIFS(转置表!L:L,B5,转置表!J:J,C5,转置表!M:M,D5) -> 1978.5 | F5: =SUMIFS(转置表!T:T,转置表!L:L,B5,转置表!J:J,C5,转置表!M:M,D5)/COUNTIFS(转置表!L:L,B5,转置表!J:J,C5,转置表!M:M,D5) -> 12.5 | G5: =E5/F5 -> 158.28
A6: =ROW()-4 -> 2 | B6: 定向井 | C6: 板桥（＜3500米） | D6: 2 | E6: =SUMIFS(转置表!O:O,转置表!L:L,B6,转置表!J:J,C6,转置表!M:M,D6)/COUNTIFS(转置表!L:L,B6,转置表!J:J,C6,转置表!M:M,D6) -> 3159.5714 | F6: =SUMIFS(转置表!T:T,转置表!L:L,B6,转置表!J:J,C6,转置表!M:M,D6)/COUNTIFS(转置表!L:L,B6,转置表!J:J,C6,转置表!M:M,D6) -> 18.918155 | G6: =E6/F6 -> 167.01266
A7: =ROW()-4 -> 3 | B7: 定向井 | C7: 板桥（≥3500米） | D7: 2 | E7: =SUMIFS(转置表!O:O,转置表!L:L,B7,转置表!J:J,C7,转置表!M:M,D7)/COUNTIFS(转置表!L:L,B7,转置表!J:J,C7,转置表!M:M,D7) -> 3643 | F7: =SUMIFS(转置表!T:T,转置表!L:L,B7,转置表!J:J,C7,转置表!M:M,D7)/COUNTIFS(转置表!L:L,B7,转置表!J:J,C7,转置表!M:M,D7) -> 30.444444 | G7: =E7/F7 -> 119.66058
A8: =ROW()-4 -> 4 | B8: 定向井 | C8: 港东 | D8: 2 | E8: =SUMIFS(转置表!O:O,转置表!L:L,B8,转置表!J:J,C8,转置表!M:M,D8)/COUNTIFS(转置表!L:L,B8,转置表!J:J,C8,转置表!M:M,D8) -> 1917.5 | F8: =SUMIFS(转置表!T:T,转置表!L:L,B8,转置表!J:J,C8,转置表!M:M,D8)/COUNTIFS(转置表!L:L,B8,转置表!J:J,C8,转置表!M:M,D8) -> 10.052083 | G8: =E8/F8 -> 190.75648
A9: =ROW()-4 -> 5 | B9: 定向井 | C9: 港西 | D9: 2 | E9: =SUMIFS(转置表!O:O,转置表!L:L,B9,转置表!J:J,C9,转置表!M:M,D9)/COUNTIFS(转置表!L:L,B9,转置表!J:J,C9,转置表!M:M,D9) -> 1516.625 | F9: =SUMIFS(转置表!T:T,转置表!L:L,B9,转置表!J:J,C9,转置表!M:M,D9)/COUNTIFS(转置表!L:L,B9,转置表!J:J,C9,转置表!M:M,D9) -> 11.625 | G9: =E9/F9 -> 130.46237
A10: =ROW()-4 -> 6 | B10: 定向井 | C10: 港中 | D10: 2 | E10: =SUMIFS(转置表!O:O,转置表!L:L,B10,转置表!J:J,C10,转置表!M:M,D10)/COUNTIFS(转置表!L:L,B10,转置表!J:J,C10,转置表!M:M,D10) -> 2748.5 | F10: =SUMIFS(转置表!T:T,转置表!L:L,B10,转置表!J:J,C10,转置表!M:M,D10)/COUNTIFS(转置表!L:L,B10,转置表!J:J,C10,转置表!M:M,D10) -> 18.5 | G10: =E10/F10 -> 148.56757
A11: =ROW()-4 -> 7 | B11: 定向井 | C11: 孔店 | D11: 2 | E11: =SUMIFS(转置表!O:O,转置表!L:L,B11,转置表!J:J,C11,转置表!M:M,D11)/COUNTIFS(转置表!L:L,B11,转置表!J:J,C11,转置表!M:M,D11) -> 1722 | F11: =SUMIFS(转置表!T:T,转置表!L:L,B11,转置表!J:J,C11,转置表!M:M,D11)/COUNTIFS(转置表!L:L,B11,转置表!J:J,C11,转置表!M:M,D11) -> 15.40625 | G11: =E11/F11 -> 111.77282
A12: =ROW()-4 -> 8 | B12: 定向井 | C12: 扣村 | D12: 2 | E12: =SUMIFS(转置表!O:O,转置表!L:L,B12,转置表!J:J,C12,转置表!M:M,D12)/COUNTIFS(转置表!L:L,B12,转置表!J:J,C12,转置表!M:M,D12) -> 2492 | F12: =SUMIFS(转置表!T:T,转置表!L:L,B12,转置表!J:J,C12,转置表!M:M,D12)/COUNTIFS(转置表!L:L,B12,转置表!J:J,C12,转置表!M:M,D12) -> 12 | G12: =E12/F12 -> 207.66667 | H12: 扣301
A13: =ROW()-4 -> 9 | B13: 定向井 | C13: 唐家河 | D13: 2 | E13: =SUMIFS(转置表!O:O,转置表!L:L,B13,转置表!J:J,C13,转置表!M:M,D13)/COUNTIFS(转置表!L:L,B13,转置表!J:J,C13,转置表!M:M,D13) -> 3321 | F13: =SUMIFS(转置表!T:T,转置表!L:L,B13,转置表!J:J,C13,转置表!M:M,D13)/COUNTIFS(转置表!L:L,B13,转置表!J:J,C13,转置表!M:M,D13) -> 20.416667 | G13: =E13/F13 -> 162.66122
A14: =ROW()-4 -> 10 | B14: 定向井 | C14: 王官屯 | D14: 2 | E14: =SUMIFS(转置表!O:O,转置表!L:L,B14,转置表!J:J,C14,转置表!M:M,D14)/COUNTIFS(转置表!L:L,B14,转置表!J:J,C14,转置表!M:M,D14) -> 3291 | F14: =SUMIFS(转置表!T:T,转置表!L:L,B14,转置表!J:J,C14,转置表!M:M,D14)/COUNTIFS(转置表!L:L,B14,转置表!J:J,C14,转置表!M:M,D14) -> 28.516667 | G14: =E14/F14 -> 115.4062
A15: =ROW()-4 -> 11 | B15: 定向井 | C15: 王徐庄 | D15: 2 | E15: =SUMIFS(转置表!O:O,转置表!L:L,B15,转置表!J:J,C15,转置表!M:M,D15)/COUNTIFS(转置表!L:L,B15,转置表!J:J,C15,转置表!M:M,D15) -> 2468 | F15: =SUMIFS(转置表!T:T,转置表!L:L,B15,转置表!J:J,C15,转置表!M:M,D15)/COUNTIFS(转置表!L:L,B15,转置表!J:J,C15,转置表!M:M,D15) -> 16 | G15: =E15/F15 -> 154.25
A16: =ROW()-4 -> 12 | B16: 定向井 | C16: 新华 | D16: 2 | E16: =SUMIFS(转置表!O:O,转置表!L:L,B16,转置表!J:J,C16,转置表!M:M,D16)/COUNTIFS(转置表!L:L,B16,转置表!J:J,C16,转置表!M:M,D16) -> 4978 | F16: =SUMIFS(转置表!T:T,转置表!L:L,B16,转置表!J:J,C16,转置表!M:M,D16)/COUNTIFS(转置表!L:L,B16,转置表!J:J,C16,转置表!M:M,D16) -> 36.395833 | G16: =E16/F16 -> 136.7739
A17: =ROW()-4 -> 13 | B17: 定向井 | C17: 羊二庄 | D17: 2 | E17: =SUMIFS(转置表!O:O,转置表!L:L,B17,转置表!J:J,C17,转置表!M:M,D17)/COUNTIFS(转置表!L:L,B17,转置表!J:J,C17,转置表!M:M,D17) -> 2201 | F17: =SUMIFS(转置表!T:T,转置表!L:L,B17,转置表!J:J,C17,转置表!M:M,D17)/COUNTIFS(转置表!L:L,B17,转置表!J:J,C17,转置表!M:M,D17) -> 11 | G17: =E17/F17 -> 200.09091
A18: =ROW()-4 -> 14 | B18: 定向井 | C18: 羊三木 | D18: 2 | E18: =SUMIFS(转置表!O:O,转置表!L:L,B18,转置表!J:J,C18,转置表!M:M,D18)/COUNTIFS(转置表!L:L,B18,转置表!J:J,C18,转置表!M:M,D18) -> 2775 | F18: =SUMIFS(转置表!T:T,转置表!L:L,B18,转置表!J:J,C18,转置表!M:M,D18)/COUNTIFS(转置表!L:L,B18,转置表!J:J,C18,转置表!M:M,D18) -> 21 | G18: =E18/F18 -> 132.14286
A19: =ROW()-4 -> 15 | B19: 定向井 | C19: 枣园 | D19: 2 | E19: =SUMIFS(转置表!O:O,转置表!L:L,B19,转置表!J:J,C19,转置表!M:M,D19)/COUNTIFS(转置表!L:L,B19,转置表!J:J,C19,转置表!M:M,D19) -> 2648.25 | F19: =SUMIFS(转置表!T:T,转置表!L:L,B19,转置表!J:J,C19,转置表!M:M,D19)/COUNTIFS(转置表!L:L,B19,转置表!J:J,C19,转置表!M:M,D19) -> 17.75 | G19: =E19/F19 -> 149.19718
A20: =ROW()-4 -> 16 | B20: 水平井 | C20: 板桥 | D20: 2 | E20: =SUMIFS(转置表!O:O,转置表!L:L,B20,转置表!J:J,C20,转置表!M:M,D20)/COUNTIFS(转置表!L:L,B20,转置表!J:J,C20,转置表!M:M,D20) -> 2467.375 | F20: =SUMIFS(转置表!T:T,转置表!L:L,B20,转置表!J:J,C20,转置表!M:M,D20)/COUNTIFS(转置表!L:L,B20,转置表!J:J,C20,转置表!M:M,D20) -> 15.476563 | G20: =E20/F20 -> 159.42655
A21: =ROW()-4 -> 17 | B21: 水平井 | C21: 埕海 | D21: 2 | E21: =SUMIFS(转置表!O:O,转置表!L:L,B21,转置表!J:J,C21,转置表!M:M,D21)/COUNTIFS(转置表!L:L,B21,转置表!J:J,C21,转置表!M:M,D21) -> 4804 | F21: =SUMIFS(转置表!T:T,转置表!L:L,B21,转置表!J:J,C21,转置表!M:M,D21)/COUNTIFS(转置表!L:L,B21,转置表!J:J,C21,转置表!M:M,D21) -> 38.916667 | G21: =E21/F21 -> 123.44325 | H21: 庄海8Es-H18（开窗侧钻）
A22: =ROW()-4 -> 18 | B22: 水平井 | C22: 大港页岩油 | D22: 2 | E22: =SUMIFS(转置表!O:O,转置表!L:L,B22,转置表!J:J,C22,转置表!M:M,D22)/COUNTIFS(转置表!L:L,B22,转置表!J:J,C22,转置表!M:M,D22) -> 6191.3333 | F22: =SUMIFS(转置表!T:T,转置表!L:L,B22,转置表!J:J,C22,转置表!M:M,D22)/COUNTIFS(转置表!L:L,B22,转置表!J:J,C22,转置表!M:M,D22) -> 33.508102 | G22: =E22/F22 -> 184.77123
A23: =ROW()-4 -> 19 | B23: 水平井 | C23: 枣园 | D23: 2 | E23: =SUMIFS(转置表!O:O,转置表!L:L,B23,转置表!J:J,C23,转置表!M:M,D23)/COUNTIFS(转置表!L:L,B23,转置表!J:J,C23,转置表!M:M,D23) -> 4000 | F23: =SUMIFS(转置表!T:T,转置表!L:L,B23,转置表!J:J,C23,转置表!M:M,D23)/COUNTIFS(转置表!L:L,B23,转置表!J:J,C23,转置表!M:M,D23) -> 41.5625 | G23: =E23/F23 -> 96.240602
A24: =ROW()-4 -> 20 | B24: 定向井 | C24: 板桥 | D24: 3 | E24: =SUMIFS(转置表!O:O,转置表!L:L,B24,转置表!J:J,C24,转置表!M:M,D24)/COUNTIFS(转置表!L:L,B24,转置表!J:J,C24,转置表!M:M,D24) -> 3730.6 | F24: =SUMIFS(转置表!T:T,转置表!L:L,B24,转置表!J:J,C24,转置表!M:M,D24)/COUNTIFS(转置表!L:L,B24,转置表!J:J,C24,转置表!M:M,D24) -> 29.4 | G24: =E24/F24 -> 126.89116
A25: =ROW()-4 -> 21 | B25: 定向井 | C25: 埕海（＜4000米） | D25: 3 | E25: =SUMIFS(转置表!O:O,转置表!L:L,B25,转置表!J:J,C25,转置表!M:M,D25)/COUNTIFS(转置表!L:L,B25,转置表!J:J,C25,转置表!M:M,D25) -> 3797 | F25: =SUMIFS(转置表!T:T,转置表!L:L,B25,转置表!J:J,C25,转置表!M:M,D25)/COUNTIFS(转置表!L:L,B25,转置表!J:J,C25,转置表!M:M,D25) -> 21.46875 | G25: =E25/F25 -> 176.86172
A26: =ROW()-4 -> 22 | B26: 定向井 | C26: 埕海（≥4000米） | D26: 3 | E26: =SUMIFS(转置表!O:O,转置表!L:L,B26,转置表!J:J,C26,转置表!M:M,D26)/COUNTIFS(转置表!L:L,B26,转置表!J:J,C26,转置表!M:M,D26) -> 4614.4 | F26: =SUMIFS(转置表!T:T,转置表!L:L,B26,转置表!J:J,C26,转置表!M:M,D26)/COUNTIFS(转置表!L:L,B26,转置表!J:J,C26,转置表!M:M,D26) -> 30.758333 | G26: =E26/F26 -> 150.02113
A27: =ROW()-4 -> 23 | B27: 定向井 | C27: 大港页岩油 | D27: 3 | E27: =SUMIFS(转置表!O:O,转置表!L:L,B27,转置表!J:J,C27,转置表!M:M,D27)/COUNTIFS(转置表!L:L,B27,转置表!J:J,C27,转置表!M:M,D27) -> 3732 | F27: =SUMIFS(转置表!T:T,转置表!L:L,B27,转置表!J:J,C27,转置表!M:M,D27)/COUNTIFS(转置表!L:L,B27,转置表!J:J,C27,转置表!M:M,D27) -> 39 | G27: =E27/F27 -> 95.692308
A28: =ROW()-4 -> 24 | B28: 定向井 | C28: 港东 | D28: 3 | E28: =SUMIFS(转置表!O:O,转置表!L:L,B28,转置表!J:J,C28,转置表!M:M,D28)/COUNTIFS(转置表!L:L,B28,转置表!J:J,C28,转置表!M:M,D28) -> 4213.5 | F28: =SUMIFS(转置表!T:T,转置表!L:L,B28,转置表!J:J,C28,转置表!M:M,D28)/COUNTIFS(转置表!L:L,B28,转置表!J:J,C28,转置表!M:M,D28) -> 56.541667 | G28: =E28/F28 -> 74.520265
A29: =ROW()-4 -> 25 | B29: 定向井 | C29: 歧口 | D29: 3 | E29: =SUMIFS(转置表!O:O,转置表!L:L,B29,转置表!J:J,C29,转置表!M:M,D29)/COUNTIFS(转置表!L:L,B29,转置表!J:J,C29,转置表!M:M,D29) -> 5157 | F29: =SUMIFS(转置表!T:T,转置表!L:L,B29,转置表!J:J,C29,转置表!M:M,D29)/COUNTIFS(转置表!L:L,B29,转置表!J:J,C29,转置表!M:M,D29) -> 63 | G29: =E29/F29 -> 81.857143
A30: =ROW()-4 -> 26 | B30: 定向井 | C30: 唐东（开发井） | D30: 3 | E30: =SUMIFS(转置表!O:O,转置表!L:L,B30,转置表!J:J,C30,转置表!M:M,D30)/COUNTIFS(转置表!L:L,B30,转置表!J:J,C30,转置表!M:M,D30) -> 4427.8571 | F30: =SUMIFS(转置表!T:T,转置表!L:L,B30,转置表!J:J,C30,转置表!M:M,D30)/COUNTIFS(转置表!L:L,B30,转置表!J:J,C30,转置表!M:M,D30) -> 28.72619 | G30: =E30/F30 -> 154.14007
A31: =ROW()-4 -> 27 | B31: 定向井 | C31: 唐东（探评井） | D31: 3 | E31: =SUMIFS(转置表!O:O,转置表!L:L,B31,转置表!J:J,C31,转置表!M:M,D31)/COUNTIFS(转置表!L:L,B31,转置表!J:J,C31,转置表!M:M,D31) -> 5578.4 | F31: =SUMIFS(转置表!T:T,转置表!L:L,B31,转置表!J:J,C31,转置表!M:M,D31)/COUNTIFS(转置表!L:L,B31,转置表!J:J,C31,转置表!M:M,D31) -> 44.579167 | G31: =E31/F31 -> 125.13469
A32: =ROW()-4 -> 28 | B32: 定向井 | C32: 新华 | D32: 3 | E32: =SUMIFS(转置表!O:O,转置表!L:L,B32,转置表!J:J,C32,转置表!M:M,D32)/COUNTIFS(转置表!L:L,B32,转置表!J:J,C32,转置表!M:M,D32) -> 5259.25 | F32: =SUMIFS(转置表!T:T,转置表!L:L,B32,转置表!J:J,C32,转置表!M:M,D32)/COUNTIFS(转置表!L:L,B32,转置表!J:J,C32,转置表!M:M,D32) -> 47.216563 | G32: =E32/F32 -> 111.3857
A33: =ROW()-4 -> 29 | B33: 水平井 | C33: 板桥 | D33: 3 | E33: =SUMIFS(转置表!O:O,转置表!L:L,B33,转置表!J:J,C33,转置表!M:M,D33)/COUNTIFS(转置表!L:L,B33,转置表!J:J,C33,转置表!M:M,D33) -> #DIV/0! | F33: =SUMIFS(转置表!T:T,转置表!L:L,B33,转置表!J:J,C33,转置表!M:M,D33)/COUNTIFS(转置表!L:L,B33,转置表!J:J,C33,转置表!M:M,D33) -> #DIV/0! | G33: =E33/F33 -> #DIV/0!
A34: =ROW()-4 -> 30 | B34: 水平井 | C34: 埕海 | D34: 3 | E34: =SUMIFS(转置表!O:O,转置表!L:L,B34,转置表!J:J,C34,转置表!M:M,D34)/COUNTIFS(转置表!L:L,B34,转置表!J:J,C34,转置表!M:M,D34) -> 4109 | F34: =SUMIFS(转置表!T:T,转置表!L:L,B34,转置表!J:J,C34,转置表!M:M,D34)/COUNTIFS(转置表!L:L,B34,转置表!J:J,C34,转置表!M:M,D34) -> 31 | G34: =E34/F34 -> 132.54839
A35: =ROW()-4 -> 31 | B35: 水平井 | C35: 大港页岩油 | D35: 3 | E35: =SUMIFS(转置表!O:O,转置表!L:L,B35,转置表!J:J,C35,转置表!M:M,D35)/COUNTIFS(转置表!L:L,B35,转置表!J:J,C35,转置表!M:M,D35) -> 6219.2857 | F35: =SUMIFS(转置表!T:T,转置表!L:L,B35,转置表!J:J,C35,转置表!M:M,D35)/COUNTIFS(转置表!L:L,B35,转置表!J:J,C35,转置表!M:M,D35) -> 55.571429 | G35: =E35/F35 -> 111.91517 | H35: 华页1、官页5-5-1
A36: =ROW()-4 -> 32 | B36: 水平井 | C36: 唐东 | D36: 3 | E36: =SUMIFS(转置表!O:O,转置表!L:L,B36,转置表!J:J,C36,转置表!M:M,D36)/COUNTIFS(转置表!L:L,B36,转置表!J:J,C36,转置表!M:M,D36) -> 5842 | F36: =SUMIFS(转置表!T:T,转置表!L:L,B36,转置表!J:J,C36,转置表!M:M,D36)/COUNTIFS(转置表!L:L,B36,转置表!J:J,C36,转置表!M:M,D36) -> 46.71 | G36: =E36/F36 -> 125.06958
A37: =ROW()-4 -> 33 | B37: 定向井 | C37: 板桥 | D37: 4 | E37: =SUMIFS(转置表!O:O,转置表!L:L,B37,转置表!J:J,C37,转置表!M:M,D37)/COUNTIFS(转置表!L:L,B37,转置表!J:J,C37,转置表!M:M,D37) -> 4824.6667 | F37: =SUMIFS(转置表!T:T,转置表!L:L,B37,转置表!J:J,C37,转置表!M:M,D37)/COUNTIFS(转置表!L:L,B37,转置表!J:J,C37,转置表!M:M,D37) -> 50.923611 | G37: =E37/F37 -> 94.743216
B38: 定向井 | C38: 常探1 | D38: 3 | E38: 6082 | F38: 52.75 | G38: =E38/F38 -> 115.29858
B39: 定向井 | C39: 滨188X1 | D39: 3 | E39: 5220 | F39: 53.5 | G39: =E39/F39 -> 97.570093
B40: 定向井 | C40: 家29-30 | D40: 2 | E40: 2327 | F40: 14 | G40: =E40/F40 -> 166.21429
B41: 定向井 | C41: 官40-67 | D41: 2 | E41: 3092 | F41: 17 | G41: =E41/F41 -> 181.88235
B42: 水平井 | C42: 板70-20H | D42: 3 | E42: 2695 | F42: 25.5 | G42: =E42/F42 -> 105.68627
B43: 水平井 | C43: 板69-22H | D43: 3 | E43: 2720 | F43: 23.1 | G43: =E43/F43 -> 117.74892
B44: 定向井 | C44: 官40-61 | D44: 2 | E44: 3092 | F44: 18.5 | G44: =E44/F44 -> 167.13514
B45: 定向井 | C45: 塘39-6 | D45: 3 | E45: 4540 | F45: 27.5 | G45: =E45/F45 -> 165.09091

Sheet 16区块毛益率指标
A1: 附件1-16
A2: 大港油区区块毛益率指标
A4: 序号 | B4: 井型 | C4: 区块 | D4: 开次 | E4: 平均指标 | G4: 考核指标（110%） | H4: 考核指标（120%） | I4: 备注 | K4: 井数
A5: =ROW()-4 -> 1 | B5: 定向井 | C5: 板桥（＜2500米） | D5: 2 | K5: =COUNTIFS(转置表!L:L,B5,转置表!J:J,C5,转置表!M:M,D5) -> 2
A6: =ROW()-4 -> 2 | B6: 定向井 | C6: 板桥（＜3500米） | D6: 2 | E6: =SUMIFS(转置表!GC:GC,转置表!L:L,B6,转置表!J:J,C6,转置表!M:M,D6) -> 3244615.8 | F6: =SUMIFS(转置表!FY:FY,转置表!L:L,B6,转置表!J:J,C6,转置表!M:M,D6) -> 59347750 | G6: =E6*110% -> 3569077.4 | H6: =E6*120% -> 3893539 | K6: =COUNTIFS(转置表!L:L,B6,转置表!J:J,C6,转置表!M:M,D6) -> 14
A7: =ROW()-4 -> 3 | B7: 定向井 | C7: 板桥（≥3500米） | D7: 2 | E7: =SUMIFS(转置表!GC:GC,转置表!L:L,B7,转置表!J:J,C7,转置表!M:M,D7) -> 3090663.8 | F7: =SUMIFS(转置表!FY:FY,转置表!L:L,B7,转置表!J:J,C7,转置表!M:M,D7) -> 37340293 | G7: =E7*110% -> 3399730.2 | H7: =E7*120% -> 3708796.5 | K7: =COUNTIFS(转置表!L:L,B7,转置表!J:J,C7,转置表!M:M,D7) -> 6
A8: =ROW()-4 -> 4 | B8: 定向井 | C8: 港东 | D8: 2 | K8: =COUNTIFS(转置表!L:L,B8,转置表!J:J,C8,转置表!M:M,D8) -> 2
A9: =ROW()-4 -> 5 | B9: 定向井 | C9: 港西 | D9: 2 | E9: =SUMIFS(转置表!GC:GC,转置表!L:L,B9,转置表!J:J,C9,转置表!M:M,D9) -> 2453789.6 | F9: =SUMIFS(转置表!FY:FY,转置表!L:L,B9,转置表!J:J,C9,转置表!M:M,D9) -> 23277479 | G9: =E9*110% -> 2699168.5 | H9: =E9*120% -> 2944547.5 | K9: =COUNTIFS(转置表!L:L,B9,转置表!J:J,C9,转置表!M:M,D9) -> 8
A10: =ROW()-4 -> 6 | B10: 定向井 | C10: 港中 | D10: 2 | K10: =COUNTIFS(转置表!L:L,B10,转置表!J:J,C10,转置表!M:M,D10) -> 2
A11: =ROW()-4 -> 7 | B11: 定向井 | C11: 孔店 | D11: 2 | I11: 孔114X1单井 | K11: =COUNTIFS(转置表!L:L,B11,转置表!J:J,C11,转置表!M:M,D11) -> 2
A12: =ROW()-4 -> 8 | B12: 定向井 | C12: 扣村 | D12: 2 | K12: =COUNTIFS(转置表!L:L,B12,转置表!J:J,C12,转置表!M:M,D12) -> 1
A13: =ROW()-4 -> 9 | B13: 定向井 | C13: 唐家河 | D13: 2 | K13: =COUNTIFS(转置表!L:L,B13,转置表!J:J,C13,转置表!M:M,D13) -> 1
A14: =ROW()-4 -> 10 | B14: 定向井 | C14: 王官屯 | D14: 2 | E14: =SUMIFS(转置表!GC:GC,转置表!L:L,B14,转置表!J:J,C14,转置表!M:M,D14) -> 4627576.6 | F14: =SUMIFS(转置表!FY:FY,转置表!L:L,B14,转置表!J:J,C14,转置表!M:M,D14) -> 30068132 | G14: =E14*110% -> 5090334.3 | H14: =E14*120% -> 5553092 | K14: =COUNTIFS(转置表!L:L,B14,转置表!J:J,C14,转置表!M:M,D14) -> 5
A15: =ROW()-4 -> 11 | B15: 定向井 | C15: 王徐庄 | D15: 2 | K15: =COUNTIFS(转置表!L:L,B15,转置表!J:J,C15,转置表!M:M,D15) -> 1
A16: =ROW()-4 -> 12 | B16: 定向井 | C16: 新华 | D16: 2 | K16: =COUNTIFS(转置表!L:L,B16,转置表!J:J,C16,转置表!M:M,D16) -> 2
A17: =ROW()-4 -> 13 | B17: 定向井 | C17: 羊二庄 | D17: 2 | I17: 扣58X1单井 | K17: =COUNTIFS(转置表!L:L,B17,转置表!J:J,C17,转置表!M:M,D17) -> 2
A18: =ROW()-4 -> 14 | B18: 定向井 | C18: 羊三木 | D18: 2 | K18: =COUNTIFS(转置表!L:L,B18,转置表!J:J,C18,转置表!M:M,D18) -> 1
A19: =ROW()-4 -> 15 | B19: 定向井 | C19: 枣园 | D19: 2 | E19: =SUMIFS(转置表!GC:GC,转置表!L:L,B19,转置表!J:J,C19,转置表!M:M,D19) -> 1578394.2 | F19: =SUMIFS(转置表!FY:FY,转置表!L:L,B19,转置表!J:J,C19,转置表!M:M,D19) -> 17030646 | G19: =E19*110% -> 1736233.6 | H19: =E19*120% -> 1894073 | K19: =COUNTIFS(转置表!L:L,B19,转置表!J:J,C19,转置表!M:M,D19) -> 4
A20: =ROW()-4 -> 16 | B20: 水平井 | C20: 板桥 | D20: 2 | E20: =SUMIFS(转置表!GC:GC,转置表!L:L,B20,转置表!J:J,C20,转置表!M:M,D20) -> 5696073 | F20: =SUMIFS(转置表!FY:FY,转置表!L:L,B20,转置表!J:J,C20,转置表!M:M,D20) -> 34064343 | G20: =E20*110% -> 6265680.3 | H20: =E20*120% -> 6835287.6 | K20: =COUNTIFS(转置表!L:L,B20,转置表!J:J,C20,转置表!M:M,D20) -> 8
A21: =ROW()-4 -> 17 | B21: 水平井 | C21: 埕海 | D21: 2 | I21: 庄海8Es-H18（开窗侧钻） | K21: =COUNTIFS(转置表!L:L,B21,转置表!J:J,C21,转置表!M:M,D21) -> 1
A22: =ROW()-4 -> 18 | B22: 水平井 | C22: 大港页岩油 | D22: 2 | E22: =SUMIFS(转置表!GC:GC,转置表!L:L,B22,转置表!J:J,C22,转置表!M:M,D22) -> -1830656.7 | F22: =SUMIFS(转置表!FY:FY,转置表!L:L,B22,转置表!J:J,C22,转置表!M:M,D22) -> 29004677 | G22: =E22-E22*10% -> -1647591 | H22: =E22-E22*20% -> -1464525.4 | K22: =COUNTIFS(转置表!L:L,B22,转置表!J:J,C22,转置表!M:M,D22) -> 3
A23: =ROW()-4 -> 19 | B23: 水平井 | C23: 枣园 | D23: 2 | K23: =COUNTIFS(转置表!L:L,B23,转置表!J:J,C23,转置表!M:M,D23) -> 2
A24: =ROW()-4 -> 20 | B24: 定向井 | C24: 板桥 | D24: 3 | E24: =SUMIFS(转置表!GC:GC,转置表!L:L,B24,转置表!J:J,C24,转置表!M:M,D24) -> 4595113.9 | F24: =SUMIFS(转置表!FY:FY,转置表!L:L,B24,转置表!J:J,C24,转置表!M:M,D24) -> 45996967 | G24: =E24*110% -> 5054625.2 | H24: =E24*120% -> 5514136.6 | K24: =COUNTIFS(转置表!L:L,B24,转置表!J:J,C24,转置表!M:M,D24) -> 5
A25: =ROW()-4 -> 21 | B25: 定向井 | C25: 埕海（＜4000米） | D25: 3 | E25: =SUMIFS(转置表!GC:GC,转置表!L:L,B25,转置表!J:J,C25,转置表!M:M,D25) -> 6280277.6 | F25: =SUMIFS(转置表!FY:FY,转置表!L:L,B25,转置表!J:J,C25,转置表!M:M,D25) -> 18857453 | G25: =E25*110% -> 6908305.3 | H25: =E25*120% -> 7536333.1 | K25: =COUNTIFS(转置表!L:L,B25,转置表!J:J,C25,转置表!M:M,D25) -> 2
A26: =ROW()-4 -> 22 | B26: 定向井 | C26: 埕海（≥4000米） | D26: 3 | E26: =SUMIFS(转置表!GC:GC,转置表!L:L,B26,转置表!J:J,C26,转置表!M:M,D26) -> 34209204 | F26: =SUMIFS(转置表!FY:FY,转置表!L:L,B26,转置表!J:J,C26,转置表!M:M,D26) -> 80955952 | G26: =E26*110% -> 37630125 | H26: =E26*120% -> 41051045 | K26: =COUNTIFS(转置表!L:L,B26,转置表!J:J,C26,转置表!M:M,D26) -> 5
A27: =ROW()-4 -> 23 | B27: 定向井 | C27: 大港页岩油 | D27: 3 | K27: =COUNTIFS(转置表!L:L,B27,转置表!J:J,C27,转置表!M:M,D27) -> 1
A28: =ROW()-4 -> 24 | B28: 定向井 | C28: 港东 | D28: 3 | K28: =COUNTIFS(转置表!L:L,B28,转置表!J:J,C28,转置表!M:M,D28) -> 2
A29: =ROW()-4 -> 25 | B29: 定向井 | C29: 歧口 | D29: 3 | K29: =COUNTIFS(转置表!L:L,B29,转置表!J:J,C29,转置表!M:M,D29) -> 2
A30: =ROW()-4 -> 26 | B30: 定向井 | C30: 唐东（开发井） | D30: 3 | E30: =SUMIFS(转置表!GC:GC,转置表!L:L,B30,转置表!J:J,C30,转置表!M:M,D30) -> 19052482 | F30: =SUMIFS(转置表!FY:FY,转置表!L:L,B30,转置表!J:J,C30,转置表!M:M,D30) -> 82042278 | G30: =E30-E30*10% -> 17147234 | H30: =E30-E30*20% -> 15241986 | K30: =COUNTIFS(转置表!L:L,B30,转置表!J:J,C30,转置表!M:M,D30) -> 7
A31: =ROW()-4 -> 27 | B31: 定向井 | C31: 唐东（探评井） | D31: 3 | E31: =SUMIFS(转置表!GC:GC,转置表!L:L,B31,转置表!J:J,C31,转置表!M:M,D31) -> 5933178.9 | F31: =SUMIFS(转置表!FY:FY,转置表!L:L,B31,转置表!J:J,C31,转置表!M:M,D31) -> 77953922 | G31: =E31*110% -> 6526496.8 | H31: =E31*120% -> 7119814.7 | K31: =COUNTIFS(转置表!L:L,B31,转置表!J:J,C31,转置表!M:M,D31) -> 5
A32: =ROW()-4 -> 28 | B32: 定向井 | C32: 新华 | D32: 3 | E32: =SUMIFS(转置表!GC:GC,转置表!L:L,B32,转置表!J:J,C32,转置表!M:M,D32) -> 24342335 | F32: =SUMIFS(转置表!FY:FY,转置表!L:L,B32,转置表!J:J,C32,转置表!M:M,D32) -> 1.5713417e+08 | G32: =E32*110% -> 26776569 | H32: =E32*120% -> 29210802 | K32: =COUNTIFS(转置表!L:L,B32,转置表!J:J,C32,转置表!M:M,D32) -> 8
A33: =ROW()-4 -> 29 | B33: 水平井 | C33: 板桥 | D33: 3 | K33: =COUNTIFS(转置表!L:L,B33,转置表!J:J,C33,转置表!M:M,D33) -> 0
A34: =ROW()-4 -> 30 | B34: 水平井 | C34: 埕海 | D34: 3 | K34: =COUNTIFS(转置表!L:L,B34,转置表!J:J,C34,转置表!M:M,D34) -> 2
A35: =ROW()-4 -> 31 | B35: 水平井 | C35: 大港页岩油 | D35: 3 | E35: =SUMIFS(转置表!GC:GC,转置表!L:L,B35,转置表!J:J,C35,转置表!M:M,D35) -> 1368516.9 | F35: =SUMIFS(转置表!FY:FY,转置表!L:L,B35,转置表!J:J,C35,转置表!M:M,D35) -> 182709100 | G35: =E35*110% -> 1505368.6 | H35: =E35*120% -> 1642220.3 | K35: =COUNTIFS(转置表!L:L,B35,转置表!J:J,C35,转置表!M:M,D35) -> 7
A36: =ROW()-4 -> 32 | B36: 水平井 | C36: 唐东 | D36: 3 | K36: =COUNTIFS(转置表!L:L,B36,转置表!J:J,C36,转置表!M:M,D36) -> 1
A37: =ROW()-4 -> 33 | B37: 定向井 | C37: 板桥 | D37: 4 | E37: =SUMIFS(转置表!GC:GC,转置表!L:L,B37,转置表!J:J,C37,转置表!M:M,D37) -> 17977484 | F37: =SUMIFS(转置表!FY:FY,转置表!L:L,B37,转置表!J:J,C37,转置表!M:M,D37) -> 59828852 | G37: =E37*110% -> 19775233 | H37: =E37*120% -> 21572981 | K37: =COUNTIFS(转置表!L:L,B37,转置表!J:J,C37,转置表!M:M,D37) -> 3

Sheet 转置表
A1: 序号 | B1: 年份 | C1: 月份 | D1: 市场分布 | E1: 队号 | F1: 队长 | G1: 钻机类型 | H1: 甲方单位 | I1: 井号 | J1: 区块 | K1: 井别 | L1: 井型 | M1: 开次 | N1: 设计井深（米） | O1: 实际井深（米） | P1: 搬迁周期（天） | Q1: 平移周期（天） | R1: 钻井周期（天） | S1: 完井周期（天） | T1: 钻完井周期（天） | U1: 建井周期（天） | V1: 试油周期（天） | W1: 钻机月 | X1: 动用钻机（台月） | Y1: 形象收入（元） | Z1: 形象利润（元） | AA1: 总成本（元） | AB1: 一、固定成本 | AC1: 1.直接人工费 | AD1: （1）合同化.市场化职工 | AE1: （2）其他劳务费用 | AF1: 2.折旧费 | AG1: （1）固定资产折旧 | AH1: （2）所有权资产折旧 | AI1: 3.长摊费 | AJ1: （1）固控装置摊销 | AK1: （2）野营房摊销 | AL1: （3）其他长期摊销 | AM1: 4.使用权资产租赁 | AN1: （1）顶驱租赁费 | AO1: （2）钻机租赁费 | AP1: （3）发电机租赁费 | AQ1: （4）钻井泵租赁费 | AR1: （5）其他租赁费 | AS1: 5.项目部运行费用 | AT1: （1）项目人员费用 | AU1: （2）房租水电 | AV1: （3）车辆费用 | AW1: （4）办公费 | AX1: （5）其他费用 | AY1: 6.制造费 | AZ1: 二、变动成本 | BA1: （一）直接材料费 | BB1: 1.钻头 | BC1: （1）钻头采购 | BD1: （2）钻头服务 | BE1: （3）钻头修复 | BF1: 2.钻井液 | BG1: （1）渤钻泥浆服务 | BH1: （2）外部泥浆服务 | BI1: 3.润滑油 | BJ1: 4.柴油 | BK1: 5.网电费 | BL1: （1）电费 | BM1: （2）架线费 | BN1: 6.大宗材料 | BO1: 7.井控 | BP1: （1）井控摊销 | BQ1: （2）井控工具 | BR1: （3）井控装置 | BS1: （4）井控租赁 | BT1: 8.钻具 | BU1: （1）钻具摊销 | BV1: （2）钻具租赁 | BW1: （3）钻具损失 | BX1: （4）钻具修造、加工 | BY1: （二）机械使用费 | BZ1: 1.修理加工费 | CA1: （1）设备修理费 | CB1: （2）其他修理费 | CC1: （3）外委加工费 | CD1: 2.设备租赁费 | CE1: （1）顶驱 | CF1: （2）网电设备 | CG1: （3）动力外包 | CH1: （三）其他直接费用 | CI1: 1.运输费 | CJ1: （1）井场搬迁 | CK1: （2）平移整拖 | CL1: （3）钻机拆搬安 | CM1: （4）吊车/铲车/抓管机 | CN1: （5）井队值班车 | CO1: （6）其他运费 | CP1: 2.第三方用工费用 | CQ1: 3.环保费用 | CR1: （1）污水处理 | CS1: （2）垃圾处理 | CT1: （3）固废处理 | CU1: （4）危废处理 | CV1: （5）环评费用 | CW1: （6）完井环保 | CX1: （7）其他环保费 | CY1: 4.检测维保费 | CZ1: （1）计量器具 | DA1: （2）消防器材 | DB1: （3）正压式呼吸器 | DC1: （4）安全阀检测 | DD1: （5）资质检测费 | DE1: （6）设备探伤费 | DF1: （7）其他检测费（安全） | DG1: （8）其他检测费（物资） | DH1: 5.定向井服务费 | DI1: 6.提速服务费 | DJ1: （1）扭力冲击器 | DK1: （2）水力振荡器 | DL1: （3）垂直钻井 | DM1: （4）旋转导向 | DN1: （5）振荡螺杆 | DO1: （6）扭摆 | DP1: （7）其他提速工具 | DQ1: 7.钻井工具费 | DR1: （1）扩眼工具 | DS1: （2）取芯工具 | DT1: （3）震击器 | DU1: （4）减震器 | DV1: （5）刮壁器 | DW1: （6）分隔器 | DX1: （7）螺杆 | DY1: （8）其他钻井工具 | DZ1: 8.事故复杂处理费用 | EA1: （1）打捞服务 | EB1: （2）测卡服务 | EC1: （3）爆炸松扣 | ED1: （4）第三方堵漏 | EE1: （5）其他事故复杂服务 | EF1: 9.下套管服务费 | EG1: 10.口井资料费 | EH1: 11.欠平衡/控压 | EI1: 12.固井 | EJ1: 13.试压 | EK1: 14.录井 | EL1: 15.测井 | EM1: 16.钻前费用 | EN1: 17.外协费 | EO1: 18.水费 | EP1: （1）水费（市场） | EQ1: （2）水费（安全） | ER1: 19.伙食费 | ES1: 20.地区补贴 | ET1: 21.倒班路费 | EU1: 22.取证培训费 | EV1: 23.网络通讯费 | EW1: （1）微波网络费 | EX1: （2）卫星租赁费 | EY1: （3）其他通讯费 | EZ1: 24.井下作业 | FA1: （1）试油作业 | FB1: （2）试气作业 | FC1: （3）压裂作业 | FD1: （4）其他井下作业 | FE1: 25.冬防保温 | FF1: （1）自保温 | FG1: （2）第三方保温 | FH1: 26.泥浆不落地 | FI1: 27.套管 | FJ1: 28.套管头 | FK1: （1）套管头（技术） | FL1: （2）套管头（物资） | FM1: 29.其他费用 | FN1: （1）其他费用（市场） | FO1: （2）其他费用（技术） | FP1: （3）其他费用（物资） | FQ1: （4）其他费用（装备） | FR1: （5）其他费用（安全） | FS1: （6）其他费用（人事） | FT1: 30.安全计提 | FU1: 31.科研计提 | FV1: 32.税金 | FW1: *** | FX1: 经营数据 | FY1: 总收入（元） | FZ1: 总成本（元） | GA1: （一）固定成本（元） | GB1: （二）变动成本（元） | GC1: 毛益额（元） | GD1: 毛益率（%） | GE1: 净利润（元） | GF1: 利润率（%） | GG1: *** | GH1: 周期数据 | GI1: 砸导管时间 | GJ1: 搬安时间 | GK1: 平移时间 | GL1: 一开时间 | GM1: 一开完钻 | GN1: 一开固井完 | GO1: 二开时间 | GP1: 二开完钻 | GQ1: 二开固井完 | GR1: 三开时间 | GS1: 三开完钻 | GT1: 三开固井完 | GU1: 四开时间 | GV1: 四开完钻 | GW1: 四开固井完 | GX1: 五开时间 | GY1: 五开完钻 | GZ1: 五开固井完 | HA1: 完钻时间 | HB1: 完井时间 | HC1: *** | HD1: 人力数据 | HE1: 人员情况（总数） | HF1: 合同化人数 | HG1: 市场化人数 | HH1: 业务外包人数 | HI1: *** | HJ1: 时效数据 | HK1: 纯钻 | HL1: 起下钻 | HM1: 接单根 | HN1: 扩划眼 | HO1: 换钻头 | HP1: 循环 | HQ1: 固井 | HR1: 辅助 | HU1: 实际耗电量
A2: =ROW()-1 -> 1 | B2: 2024 | C2: 4月 | D2: 大港 | E2: 50998 | F2: 杨朔 | G2: ZJ50J | H2: 大港采油四厂 | I2: 板111-22 | J2: 板桥 | K2: 开发井 | L2: 定向井 | M2: 3 | N2: 3508 | O2: 3521 | P2: 5 | Q2: 0 | R2: 17 | S2: 8 | T2: 25 | U2: 30 | V2: 0 | W2: 0.83333333 | X2: 1 | Y2: 8344914 | Z2: 23830.413 | AA2: 8321083.6 | AB2: 765429.19 | AC2: 325000 | AD2: 325000 | AE2: 0 | AF2: 28620.882 | AG2: 28620.882 | AH2: 0 | AI2: 1808.3042 | AJ2: 1382.0508 | AK2: 426.25333 | AL2: 0 | AM2: 0 | AN2: 0 | AO2: 0 | AP2: 0 | AQ2: 0 | AR2: 0 | AS2: 0 | AT2: 0 | AU2: 0 | AV2: 0 | AW2: 0 | AX2: 0 | AY2: 410000 | AZ2: 7555654.4 | BA2: 2502086.4 | BB2: 128997.87 | BC2: 128997.87 | BD2: 0 | BE2: 0 | BF2: 937414 | BG2: 937414 | BH2: 0 | BI2: 0 | BJ2: 609258 | BK2: 17227.07 | BL2: 17227.07 | BM2: 0 | BN2: 421336.26 | BO2: 126130.15 | BP2: 40000 | BQ2: 0 | BR2: 0 | BS2: 86130.15 | BT2: 261723.03 | BU2: 221823 | BV2: 39900.03 | BW2: 0 | BX2: 0 | BY2: 434253.2 | BZ2: 175146.5 | CA2: 70253.63 | CB2: 2956.29 | CC2: 101936.58 | CD2: 259106.7 | CE2: 0 | CF2: 0 | CG2: 259106.7 | CH2: 4619314.8 | CI2: 291386 | CJ2: 0 | CK2: 0 | CL2: 63577 | CM2: 64692 | CN2: 36424 | CO2: 126693 | CP2: 405000 | CQ2: 18866.87 | CR2: 4264.65 | CS2: 12952.22 | CT2: 0 | CU2: 850 | CV2: 0 | CW2: 0 | CX2: 800 | CY2: 12086.26 | CZ2: 6648.3333 | DA2: 0 | DB2: 583.33 | DC2: 346.66667 | DD2: 0 | DE2: 0 | DF2: 4507.93 | DG2: 0 | DH2: 428960 | DI2: 88515 | DJ2: 0 | DK2: 88515 | DL2: 0 | DM2: 0 | DN2: 0 | DO2: 0 | DP2: 0 | DQ2: 0 | DR2: 0 | DS2: 0 | DT2: 0 | DU2: 0 | DV2: 0 | DW2: 0 | DX2: 0 | DY2: 0 | DZ2: 0 | EA2: 0 | EB2: 0 | EC2: 0 | ED2: 0 | EE2: 0 | EF2: 48654 | EG2: 0 | EH2: 9863 | EI2: 845471.41 | EJ2: 0 | EK2: 0 | EL2: 0 | EM2: 0 | EN2: 0 | EO2: 18012 | EP2: 0 | EQ2: 18012 | ER2: 32400 | ES2: 0 | ET2: 0 | EU2: 0 | EV2: 100 | EW2: 0 | EX2: 0 | EY2: 100 | EZ2: 0 | FA2: 0 | FB2: 0 | FC2: 0 | FD2: 0 | FE2: 0 | FF2: 0 | FG2: 0 | FH2: 0 | FI2: 2027903.3 | FJ2: 123667.65 | FK2: 123667.65 | FL2: 0 | FM2: 9737.03 | FN2: 0 | FO2: 0 | FP2: 0 | FQ2: 0 | FR2: 9737.03 | FS2: 0 | FT2: 66759.312 | FU2: 166898.28 | FV2: 25034.742 | FY2: 8344914 | FZ2: 8321083.6 | GA2: 765429.19 | GB2: 7555654.4 | GC2: 789259.6 | GD2: 0.094579716 | GE2: 23830.413 | GF2: 0.0028556811 | GJ2: 45362 | GL2: 45367 | GO2: 45370 | GR2: 45379 | GU2: - - | HA2: 45384 | HB2: 45392 | HE2: 40 | HF2: 5 | HG2: 8 | HH2: 27 | HK2: 130 | HL2: 23 | HM2: 74 | HN2: 0 | HO2: 0 | HP2: 0 | HQ2: 217 | HR2: 154
A3: =ROW()-1 -> 2 | B3: 2024 | C3: 11月 | D3: 大港 | E3: 50528 | F3: 李军 | G3: ZJ50D | H3: 大港采油四厂 | I3: 板111-23 | J3: 板桥（＜3500米） | K3: 开发井 | L3: 定向井 | M3: 2 | N3: 3326 | O3: 3335 | P3: 11 | Q3: 0 | R3: 13 | S3: 10 | T3: 23 | U3: 34 | V3: 0 | W3: 0.76666667 | X3: 1.1333333 | Y3: 5102526 | Z3: -492703.7 | AA3: 5595229.7 | AB3: 913467 | AC3: 396666.67 | AD3: 396666.67 | AE3: 0 | AF3: 38013.093 | AG3: 38013.093 | AH3: 0 | AI3: 14120.569 | AJ3: 6250.135 | AK3: 5729.5827 | AL3: 2140.8516 | AM3: 0 | AN3: 0 | AO3: 0 | AP3: 0 | AQ3: 0 | AR3: 0 | AS3: 0 | AT3: 0 | AU3: 0 | AV3: 0 | AW3: 0 | AX3: 0 | AY3: 464666.67 | AZ3: 4681762.7 | BA3: 1524206.2 | BB3: 101825.83 | BC3: 101825.83 | BD3: 0 | BE3: 0 | BF3: 377885 | BG3: 377885 | BH3: 0 | BI3: 0 | BJ3: 573755 | BK3: 15066.74 | BL3: 15066.74 | BM3: 0 | BN3: 95680.181 | BO3: 110302.01 | BP3: 36800 | BQ3: 0 | BR3: 0 | BS3: 73502.01 | BT3: 249691.44 | BU3: 210105 | BV3: 39586.44 | BW3: 0 | BX3: 0 | BY3: 31423.31 | BZ3: 31423.31 | CA3: 4701.73 | CB3: 7349.77 | CC3: 19371.81 | CD3: 0 | CE3: 0 | CF3: 0 | CG3: 0 | CH3: 3126133.2 | CI3: 313011 | CJ3: 0 | CK3: 0 | CL3: 121338 | CM3: 66985 | CN3: 28741 | CO3: 95947 | CP3: 391000 | CQ3: 16892.01 | CR3: 4619.1 | CS3: 10884.91 | CT3: 0 | CU3: 588 | CV3: 0 | CW3: 0 | CX3: 800 | CY3: 85925.18 | CZ3: 1686.25 | DA3: 0 | DB3: 400 | DC3: 36.666667 | DD3: 0 | DE3: 81600 | DF3: 2202.2633 | DG3: 0 | DH3: 242147 | DI3: 108578.4 | DJ3: 0 | DK3: 108578.4 | DL3: 0 | DM3: 0 | DN3: 0 | DO3: 0 | DP3: 0 | DQ3: 0 | DR3: 0 | DS3: 0 | DT3: 0 | DU3: 0 | DV3: 0 | DW3: 0 | DX3: 0 | DY3: 0 | DZ3: 0 | EA3: 0 | EB3: 0 | EC3: 0 | ED3: 0 | EE3: 0 | EF3: 30950 | EG3: 0 | EH3: 14415 | EI3: 672590.89 | EJ3: 0 | EK3: 0 | EL3: 0 | EM3: 0 | EN3: 0 | EO3: 14220 | EP3: 0 | EQ3: 14220 | ER3: 33966 | ES3: 0 | ET3: 0 | EU3: 1140 | EV3: 113.33333 | EW3: 0 | EX3: 0 | EY3: 113.33333 | EZ3: 0 | FA3: 0 | FB3: 0 | FC3: 0 | FD3: 0 | FE3: 0 | FF3: 0 | FG3: 0 | FH3: 0 | FI3: 991555.26 | FJ3: 44270.45 | FK3: 44270.45 | FL3: 0 | FM3: 7180.3633 | FN3: 0 | FO3: 0 | FP3: 0 | FQ3: 0 | FR3: 7180.3633 | FS3: 0 | FT3: 40820.208 | FU3: 102050.52 | FV3: 15307.578 | FY3: 5102526 | FZ3: 5595229.7 | GA3: 913467 | GB3: 4681762.7 | GC3: 420763.29 | GD3: 0.082461763 | GE3: -492703.7 | GF3: -0.096560743 | GJ3: 45576 | GL3: 45587 | GO3: 45591 | GR3: - - | GU3: - - | HA3: 45600 | HB3: 45610 | HE3: 37 | HF3: 3 | HG3: 11 | HH3: 23 | HK3: 158 | HL3: 45 | HM3: 19 | HN3: 9 | HO3: 0 | HP3: 13 | HQ3: 165 | HR3: 152
A4: =ROW()-1 -> 3 | B4: 2024 | C4: 11月 | D4: 大港 | E4: 70520 | F4: 罗健 | G4: ZJ70D | H4: 大港采油四厂 | I4: 板15-17 | J4: 板桥 | K4: 开发井 | L4: 定向井 | M4: 3 | N4: 3711 | O4: 3785 | P4: 12 | Q4: 0 | R4: 20 | S4: 6 | T4: 26 | U4: 38 | V4: 0 | W4: 0.86666667 | X4: 1.2666667 | Y4: 8730383 | Z4: -452257.37 | AA4: 9182640.4 | AB4: 1207980.3 | AC4: 633333.33 | AD4: 633333.33 | AE4: 0 | AF4: 37862.687 | AG4: 37862.687 | AH4: 0 | AI4: 17450.959 | AJ4: 12894.003 | AK4: 4363.9042 | AL4: 193.05161 | AM4: 0 | AN4: 0 | AO4: 0 | AP4: 0 | AQ4: 0 | AR4: 0 | AS4: 0 | AT4: 0 | AU4: 0 | AV4: 0 | AW4: 0 | AX4: 0 | AY4: 519333.33 | AZ4: 7974660.1 | BA4: 2046379.7 | BB4: 128997.87 | BC4: 128997.87 | BD4: 0 | BE4: 0 | BF4: 427001 | BG4: 427001 | BH4: 0 | BI4: 23930.424 | BJ4: 287196 | BK4: 455442.06 | BL4: 170842.06 | BM4: 284600 | BN4: 313825.45 | BO4: 124027.19 | BP4: 41600 | BQ4: 0 | BR4: 0 | BS4: 82427.19 | BT4: 285959.74 | BU4: 238455 | BV4: 47504.74 | BW4: 0 | BX4: 0 | BY4: 580334.64 | BZ4: 341418.38 | CA4: 53315.27 | CB4: 17013.16 | CC4: 271089.95 | CD4: 238916.26 | CE4: 159459.34 | CF4: 79456.92 | CG4: 0 | CH4: 5347945.7 | CI4: 738788 | CJ4: 0 | CK4: 0 | CL4: 554370 | CM4: 67044 | CN4: 12199 | CO4: 105175 | CP4: 456000 | CQ4: 17253.877 | CR4: 5685.33 | CS4: 9367.69 | CT4: 0 | CU4: 458 | CV4: 0 | CW4: 0 | CX4: 1742.8571 | CY4: 12145.927 | CZ4: 4873.7857 | DA4: 0 | DB4: 417.79 | DC4: 138.57143 | DD4: 0 | DE4: 0 | DF4: 6715.78 | DG4: 0 | DH4: 455930 | DI4: 85109.3 | DJ4: 0 | DK4: 85109.3 | DL4: 0 | DM4: 0 | DN4: 0 | DO4: 0 | DP4: 0 | DQ4: 0 | DR4: 0 | DS4: 0 | DT4: 0 | DU4: 0 | DV4: 0 | DW4: 0 | DX4: 0 | DY4: 0 | DZ4: 0 | EA4: 0 | EB4: 0 | EC4: 0 | ED4: 0 | EE4: 0 | EF4: 140307 | EG4: 0 | EH4: 12898 | EI4: 1101813.9 | EJ4: 0 | EK4: 0 | EL4: 0 | EM4: 0 | EN4: 0 | EO4: 13035 | EP4: 0 | EQ4: 13035 | ER4: 45144 | ES4: 0 | ET4: 0 | EU4: 1140 | EV4: 126.66667 | EW4: 0 | EX4: 0 | EY4: 126.66667 | EZ4: 0 | FA4: 0 | FB4: 0 | FC4: 0 | FD4: 0 | FE4: 0 | FF4: 0 | FG4: 0 | FH4: 0 | FI4: 1859140 | FJ4: 123667.65 | FK4: 123667.65 | FL4: 0 | FM4: 14804.429 | FN4: 0 | FO4: 0 | FP4: 0 | FQ4: 0 | FR4: 14804.429 | FS4: 0 | FT4: 69843.064 | FU4: 174607.66 | FV4: 26191.149 | FY4: 8730383 | FZ4: 9182640.4 | GA4: 1207980.3 | GB4: 7974660.1 | GC4: 755722.95 | GD4: 0.086562405 | GE4: -452257.37 | GF4: -0.051802695 | GJ4: 45575 | GL4: 45587 | GO4: 45589 | GR4: 45596 | GU4: - - | HA4: 45607 | HB4: 45613 | HE4: 44 | HF4: 7 | HG4: 13 | HH4: 24 | HK4: 159 | HL4: 64 | HM4: 21 | HN4: 36 | HO4: 2 | HP4: 35 | HQ4: 236 | HR4: 70
A5: =ROW()-1 -> 4 | B5: 2024 | C5: 7月 | D5: 大港 | E5: 50998 | F5: 杨朔 | G5: ZJ50J | H5: 大港采油四厂 | I5: 板16-11 | J5: 板桥 | K5: 开发井 | L5: 定向井 | M5: 3 | N5: 3476 | O5: 3535 | P5: 8 | Q5: 0 | R5: 22 | S5: 6 | T5: 28 | U5: 36 | V5: 0 | W5: 0.93333333 | X5: 1.2 | Y5: 9292033 | Z5: 106506.98 | AA5: 9185526 | AB5: 1068515 | AC5: 540000 | AD5: 540000 | AE5: 0 | AF5: 34345.058 | AG5: 34345.058 | AH5: 0 | AI5: 2169.965 | AJ5: 1658.461 | AK5: 511.504 | AL5: 0 | AM5: 0 | AN5: 0 | AO5: 0 | AP5: 0 | AQ5: 0 | AR5: 0 | AS5: 0 | AT5: 0 | AU5: 0 | AV5: 0 | AW5: 0 | AX5: 0 | AY5: 492000 | AZ5: 8117011 | BA5: 1647237.1 | BB5: 168745.69 | BC5: 168745.69 | BD5: 0 | BE5: 0 | BF5: 492272 | BG5: 492272 | BH5: 0 | BI5: 14414.436 | BJ5: 0 | BK5: 365662.62 | BL5: 208862.62 | BM5: 156800 | BN5: 207560.48 | BO5: 131287.26 | BP5: 44800 | BQ5: 0 | BR5: 0 | BS5: 86487.26 | BT5: 267294.64 | BU5: 222705 | BV5: 44589.64 | BW5: 0 | BX5: 0 | BY5: 456770.87 | BZ5: 386455.01 | CA5: 261990.63 | CB5: 55956.75 | CC5: 68507.63 | CD5: 70315.86 | CE5: 0 | CF5: 70315.86 | CG5: 0 | CH5: 6013003 | CI5: 330740 | CJ5: 0 | CK5: 0 | CL5: 57845 | CM5: 114892 | CN5: 35864 | CO5: 122139 | CP5: 342000 | CQ5: 21747.03 | CR5: 6396.98 | CS5: 13700.05 | CT5: 0 | CU5: 850 | CV5: 0 | CW5: 0 | CX5: 800 | CY5: 112386.26 | CZ5: 6648.3333 | DA5: 0 | DB5: 583.33 | DC5: 346.66667 | DD5: 57900 | DE5: 42400 | DF5: 4507.93 | DG5: 0 | DH5: 442527 | DI5: 78432.7 | DJ5: 0 | DK5: 78432.7 | DL5: 0 | DM5: 0 | DN5: 0 | DO5: 0 | DP5: 0 | DQ5: 0 | DR5: 0 | DS5: 0 | DT5: 0 | DU5: 0 | DV5: 0 | DW5: 0 | DX5: 0 | DY5: 0 | DZ5: 0 | EA5: 0 | EB5: 0 | EC5: 0 | ED5: 0 | EE5: 0 | EF5: 140271 | EG5: 0 | EH5: 11381 | EI5: 1116968.8 | EJ5: 0 | EK5: 0 | EL5: 141886 | EM5: 0 | EN5: 0 | EO5: 15721 | EP5: 0 | EQ5: 15721 | ER5: 35964 | ES5: 0 | ET5: 0 | EU5: 0 | EV5: 120 | EW5: 0 | EX5: 0 | EY5: 120 | EZ5: 0 | FA5: 0 | FB5: 0 | FC5: 0 | FD5: 0 | FE5: 0 | FF5: 0 | FG5: 0 | FH5: 0 | FI5: 2648891.1 | FJ5: 276177.02 | FK5: 276177.02 | FL5: 0 | FM5: 9737.03 | FN5: 0 | FO5: 0 | FP5: 0 | FQ5: 0 | FR5: 9737.03 | FS5: 0 | FT5: 74336.264 | FU5: 185840.66 | FV5: 27876.099 | FY5: 9292033 | FZ5: 9185526 | GA5: 1068515 | GB5: 8117011 | GC5: 1175022 | GD5: 0.12645478 | GE5: 106506.98 | GF5: 0.011462183 | GJ5: 45468 | GL5: 45476 | GO5: 45478 | GR5: 45489 | GU5: - - | HA5: 45498 | HB5: 45504 | HE5: 37 | HF5: 6 | HG5: 12 | HH5: 19 | HK5: 152 | HL5: 79 | HM5: 69 | HN5: 18 | HO5: 0 | HP5: 37 | HQ5: 220 | HR5: 109
A6: =ROW()-1 -> 5 | B6: 2024 | C6: 1月 | D6: 大港 | E6: 50998 | F6: 杨朔 | G6: ZJ50J | H6: 大港采油四厂 | I6: 板16-12 | J6: 板桥（≥3500米） | K6: 开发井 | L6: 定向井 | M6: 2 | N6: 3650 | O6: 3670 | P6: 18 | Q6: 0 | R6: 29 | S6: 12 | T6: 41 | U6: 59 | V6: 0 | W6: 1.3666667 | X6: 1.9666667 | Y6: 6006436 | Z6: -2492323.1 | AA6: 8498759.1 | AB6: 1898677.4 | AC6: 1032500 | AD6: 1032500 | AE6: 0 | AF6: 56287.734 | AG6: 56287.734 | AH6: 0 | AI6: 3556.3315 | AJ6: 2718.0333 | AK6: 838.29822 | AL6: 0 | AM6: 0 | AN6: 0 | AO6: 0 | AP6: 0 | AQ6: 0 | AR6: 0 | AS6: 0 | AT6: 0 | AU6: 0 | AV6: 0 | AW6: 0 | AX6: 0 | AY6: 806333.33 | AZ6: 6600081.7 | BA6: 2208286.5 | BB6: 40269.247 | BC6: 14336.287 | BD6: 25932.96 | BE6: 0 | BF6: 422004 | BG6: 422004 | BH6: 0 | BI6: 15405.876 | BJ6: 1102073 | BK6: 4820.8 | BL6: 4820.8 | BM6: 0 | BN6: 151923.15 | BO6: 148675.18 | BP6: 65600 | BQ6: 0 | BR6: 0 | BS6: 83075.18 | BT6: 323115.23 | BU6: 231210 | BV6: 91905.23 | BW6: 0 | BX6: 0 | BY6: 200520.74 | BZ6: 10973.99 | CA6: 3274.34 | CB6: 0 | CC6: 7699.65 | CD6: 189546.75 | CE6: 0 | CF6: 0 | CG6: 189546.75 | CH6: 4191274.5 | CI6: 561072 | CJ6: 0 | CK6: 0 | CL6: 270848 | CM6: 84673 | CN6: 53027 | CO6: 152524 | CP6: 560500 | CQ6: 6557.85 | CR6: 2843.1 | CS6: 2064.75 | CT6: 0 | CU6: 850 | CV6: 0 | CW6: 0 | CX6: 800 | CY6: 12086.26 | CZ6: 6648.3333 | DA6: 0 | DB6: 583.33 | DC6: 346.66667 | DD6: 0 | DE6: 0 | DF6: 4507.93 | DG6: 0 | DH6: 528444 | DI6: 167462 | DJ6: 0 | DK6: 167462 | DL6: 0 | DM6: 0 | DN6: 0 | DO6: 0 | DP6: 0 | DQ6: 75480 | DR6: 0 | DS6: 0 | DT6: 0 | DU6: 0 | DV6: 0 | DW6: 0 | DX6: 0 | DY6: 75480 | DZ6: 0 | EA6: 0 | EB6: 0 | EC6: 0 | ED6: 0 | EE6: 0 | EF6: 38225 | EG6: 0 | EH6: 20813 | EI6: 774421.62 | EJ6: 0 | EK6: 0 | EL6: 0 | EM6: 0 | EN6: 0 | EO6: 22199 | EP6: 0 | EQ6: 22199 | ER6: 63720 | ES6: 0 | ET6: 0 | EU6: 1380 | EV6: 196.66667 | EW6: 0 | EX6: 0 | EY6: 196.66667 | EZ6: 0 | FA6: 0 | FB6: 0 | FC6: 0 | FD6: 0 | FE6: 0 | FF6: 0 | FG6: 0 | FH6: 0 | FI6: 1121568.5 | FJ6: 41212.04 | FK6: 41212.04 | FL6: 0 | FM6: 9737.03 | FN6: 0 | FO6: 0 | FP6: 0 | FQ6: 0 | FR6: 9737.03 | FS6: 0 | FT6: 48051.488 | FU6: 120128.72 | FV6: 18019.308 | FY6: 6006436 | FZ6: 8498759.1 | GA6: 1898677.4 | GB6: 6600081.7 | GC6: -593645.71 | GD6: -0.098834935 | GE6: -2492323.1 | GF6: -0.41494209 | GJ6: 45244 | GL6: 45262 | GO6: 45273 | GR6: - - | GU6: - - | HA6: 45291 | HB6: 45303 | HE6: 40 | HF6: 10 | HG6: 11 | HH6: 19 | HK6: 248 | HL6: 147 | HM6: 146 | HN6: 0 | HO6: 0 | HP6: 0 | HQ6: 127 | HR6: 168
A7: =ROW()-1 -> 6 | B7: 2024 | C7: 2月 | D7: 大港 | E7: 50998 | F7: 杨朔 | G7: ZJ50J | H7: 大港采油四厂 | I7: 板17-10 | J7: 板桥（≥3500米） | K7: 开发井 | L7: 定向井 | M7: 2 | N7: 3737 | O7: 3765 | P7: 6 | Q7: 0 | R7: 26 | S7: 7 | T7: 33 | U7: 39 | V7: 0 | W7: 1.1 | X7: 1.3 | Y7: 6691628 | Z7: -1955376.5 | AA7: 8647004.5 | AB7: 1255057.9 | AC7: 682500 | AD7: 682500 | AE7: 0 | AF7: 37207.146 | AG7: 37207.146 | AH7: 0 | AI7: 2350.7954 | AJ7: 1796.6661 | AK7: 554.12933 | AL7: 0 | AM7: 0 | AN7: 0 | AO7: 0 | AP7: 0 | AQ7: 0 | AR7: 0 | AS7: 0 | AT7: 0 | AU7: 0 | AV7: 0 | AW7: 0 | AX7: 0 | AY7: 533000 | AZ7: 7391946.6 | BA7: 3173170.4 | BB7: 53522.122 | BC7: 53522.122 | BD7: 0 | BE7: 0 | BF7: 368435 | BG7: 368435 | BH7: 0 | BI7: 0 | BJ7: 1156402 | BK7: 1119818 | BL7: 442918.02 | BM7: 676900 | BN7: 36688.96 | BO7: 128814.15 | BP7: 52800 | BQ7: 0 | BR7: 0 | BS7: 76014.15 | BT7: 309490.17 | BU7: 237195 | BV7: 62295.17 | BW7: 0 | BX7: 10000 | BY7: 356015.65 | BZ7: 89688.58 | CA7: 43958.24 | CB7: 26919.11 | CC7: 18811.23 | CD7: 266327.07 | CE7: 0 | CF7: 62879.52 | CG7: 203447.55 | CH7: 3862760.5 | CI7: 228107 | CJ7: 0 | CK7: 0 | CL7: 34905 | CM7: 46010 | CN7: 30402 | CO7: 116790 | CP7: 370500 | CQ7: 14598.63 | CR7: 4975.43 | CS7: 7973.2 | CT7: 0 | CU7: 850 | CV7: 0 | CW7: 0 | CX7: 800 | CY7: 12086.26 | CZ7: 6648.3333 | DA7: 0 | DB7: 583.33 | DC7: 346.66667 | DD7: 0 | DE7: 0 | DF7: 4507.93 | DG7: 0 | DH7: 350036 | DI7: 268708.3 | DJ7: 0 | DK7: 38778 | DL7: 0 | DM7: 0 | DN7: 0 | DO7: 120000 | DP7: 109930.3 | DQ7: 80355.08 | DR7: 0 | DS7: 68755.08 | DT7: 0 | DU7: 0 | DV7: 0 | DW7: 0 | DX7: 0 | DY7: 11600 | DZ7: 0 | EA7: 0 | EB7: 0 | EC7: 0 | ED7: 0 | EE7: 0 | EF7: 37835 | EG7: 0 | EH7: 20485 | EI7: 794571.97 | EJ7: 0 | EK7: 0 | EL7: 0 | EM7: 0 | EN7: 0 | EO7: 18012 | EP7: 0 | EQ7: 18012 | ER7: 42120 | ES7: 0 | ET7: 0 | EU7: 1080 | EV7: 130 | EW7: 0 | EX7: 0 | EY7: 130 | EZ7: 0 | FA7: 0 | FB7: 0 | FC7: 0 | FD7: 0 | FE7: 132635 | FF7: 0 | FG7: 132635 | FH7: 0 | FI7: 1233110.7 | FJ7: 41212.04 | FK7: 41212.04 | FL7: 0 | FM7: 9737.03 | FN7: 0 | FO7: 0 | FP7: 0 | FQ7: 0 | FR7: 9737.03 | FS7: 0 | FT7: 53533.024 | FU7: 133832.56 | FV7: 20074.884 | FY7: 6691628 | FZ7: 8647004.5 | GA7: 1255057.9 | GB7: 7391946.6 | GC7: -700318.56 | GD7: -0.10465593 | GE7: -1955376.5 | GF7: -0.29221237 | GJ7: 45309 | GL7: 45315 | GO7: 45321 | GR7: - - | GU7: - - | HA7: 45341 | HB7: 45348 | HE7: 40 | HF7: 10 | HG7: 11 | HH7: 19 | HK7: 210 | HL7: 137 | HM7: 146 | HN7: 0 | HO7: 0 | HP7: 0 | HQ7: 182 | HR7: 110
A8: =ROW()-1 -> 7 | B8: 2024 | C8: 3月 | D8: 大港 | E8: BHZ70003 | F8: 张朝相 | G8: ZJ70D | H8: 大港采油四厂 | I8: 板17-12 | J8: 板桥（＜3500米） | K8: 开发井 | L8: 定向井 | M8: 2 | N8: 3444 | O8: 3462 | P8: 11 | Q8: 0 | R8: 13 | S8: 6 | T8: 19 | U8: 30 | V8: 0 | W8: 0.63333333 | X8: 1 | Y8: 5035639 | Z8: -2283630.7 | AA8: 7319269.7 | AB8: 1218910.5 | AC8: 300000 | AD8: 300000 | AE8: 0 | AF8: 238366.6 | AG8: 135489.06 | AH8: 102877.54 | AI8: 10916.962 | AJ8: 3246.2783 | AK8: 3228.205 | AL8: 4442.4783 | AM8: 259626.89 | AN8: 84387.378 | AO8: 0 | AP8: 115176.99 | AQ8: 60062.52 | AR8: 0 | AS8: 0 | AT8: 0 | AU8: 0 | AV8: 0 | AW8: 0 | AX8: 0 | AY8: 410000 | AZ8: 6100359.2 | BA8: 2775382.2 | BB8: 139616.29 | BC8: 139616.29 | BD8: 0 | BE8: 0 | BF8: 348742 | BG8: 348742 | BH8: 0 | BI8: 11978.064 | BJ8: 604318 | BK8: 1227648.9 | BL8: 435848.91 | BM8: 791800 | BN8: 64528.099 | BO8: 117609.19 | BP8: 30400 | BQ8: 0 | BR8: 0 | BS8: 87209.19 | BT8: 260941.69 | BU8: 218106 | BV8: 32835.69 | BW8: 0 | BX8: 10000 | BY8: 126636.25 | BZ8: 80999.45 | CA8: 67160.98 | CB8: 12064.66 | CC8: 1773.81 | CD8: 45636.8 | CE8: 0 | CF8: 45636.8 | CG8: 0 | CH8: 3198340.8 | CI8: 387579 | CJ8: 0 | CK8: 0 | CL8: 205357 | CM8: 89062 | CN8: 35678 | CO8: 57482 | CP8: 345000 | CQ8: 17923.91 | CR8: 3909.27 | CS8: 11548.14 | CT8: 0 | CU8: 1266.5 | CV8: 0 | CW8: 0 | CX8: 1200 | CY8: 67519.566 | CZ8: 5783.875 | DA8: 0 | DB8: 455.1875 | DC8: 270 | DD8: 57900 | DE8: 0 | DF8: 3110.5035 | DG8: 0 | DH8: 204563 | DI8: 0 | DJ8: 0 | DK8: 0 | DL8: 0 | DM8: 0 | DN8: 0 | DO8: 0 | DP8: 0 | DQ8: 182571.6 | DR8: 0 | DS8: 0 | DT8: 0 | DU8: 0 | DV8: 0 | DW8: 0 | DX8: 0 | DY8: 182571.6 | DZ8: 0 | EA8: 0 | EB8: 0 | EC8: 0 | ED8: 0 | EE8: 0 | EF8: 32860 | EG8: 0 | EH8: 11381 | EI8: 619688.75 | EJ8: 0 | EK8: 0 | EL8: 0 | EM8: 0 | EN8: 0 | EO8: 7465.5 | EP8: 0 | EQ8: 7465.5 | ER8: 28350 | ES8: 0 | ET8: 0 | EU8: 5000 | EV8: 100 | EW8: 0 | EX8: 0 | EY8: 100 | EZ8: 0 | FA8: 0 | FB8: 0 | FC8: 0 | FD8: 0 | FE8: 0 | FF8: 0 | FG8: 0 | FH8: 0 | FI8: 1079538.2 | FJ8: 44270.45 | FK8: 44270.45 | FL8: 0 | FM8: 8425 | FN8: 0 | FO8: 0 | FP8: 0 | FQ8: 0 | FR8: 8425 | FS8: 0 | FT8: 40285.112 | FU8: 100712.78 | FV8: 15106.917 | FY8: 5035639 | FZ8: 7319269.7 | GA8: 1218910.5 | GB8: 6100359.2 | GC8: -1064720.2 | GD8: -0.21143697 | GE8: -2283630.7 | GF8: -0.45349373 | GJ8: 45351 | GL8: 45362 | GO8: 45366 | GR8: - - | GU8: - - | HA8: 45375 | HB8: 45381 | HE8: 35 | HF8: 4 | HG8: 8 | HH8: 23 | HK8: 136 | HL8: 34 | HM8: 66 | HN8: 0 | HO8: 0 | HP8: 0 | HQ8: 167 | HR8: 47
A9: =ROW()-1 -> 8 | B9: 2024 | C9: 12月 | D9: 大港 | E9: 70318 | F9: 肖康 | G9: ZJ70D | H9: 大港采油四厂 | I9: 板17-17 | J9: 板桥（≥3500米） | K9: 开发井 | L9: 定向井 | M9: 2 | N9: 3592 | O9: 3603 | P9: 21 | Q9: 0 | R9: 16 | S9: 8 | T9: 24 | U9: 45 | V9: 0 | W9: 0.8 | X9: 1.5 | Y9: 5533617 | Z9: -943771.22 | AA9: 6477388.2 | AB9: 1326634.7 | AC9: 525000 | AD9: 525000 | AE9: 0 | AF9: 56818.495 | AG9: 56818.495 | AH9: 0 | AI9: 3235.125 | AJ9: 2616.375 | AK9: 618.75 | AL9: 0 | AM9: 126581.07 | AN9: 126581.07 | AO9: 0 | AP9: 0 | AQ9: 0 | AR9: 0 | AS9: 0 | AT9: 0 | AU9: 0 | AV9: 0 | AW9: 0 | AX9: 0 | AY9: 615000 | AZ9: 5150753.5 | BA9: 1573517.8 | BB9: 69521.414 | BC9: 69521.414 | BD9: 0 | BE9: 0 | BF9: 335063 | BG9: 335063 | BH9: 0 | BI9: 5827.464 | BJ9: 188890 | BK9: 416323.43 | BL9: 173723.43 | BM9: 242600 | BN9: 172428.24 | BO9: 116015.85 | BP9: 38400 | BQ9: 0 | BR9: 0 | BS9: 77615.85 | BT9: 269448.38 | BU9: 226989 | BV9: 42459.38 | BW9: 0 | BX9: 0 | BY9: 47535.65 | BZ9: 29252.77 | CA9: 6991.42 | CB9: 21818.44 | CC9: 442.91 | CD9: 18282.88 | CE9: 0 | CF9: 18282.88 | CG9: 0 | CH9: 3529700.1 | CI9: 653192 | CJ9: 0 | CK9: 0 | CL9: 424261 | CM9: 64809 | CN9: 40241 | CO9: 123881 | CP9: 517500 | CQ9: 20115.83 | CR9: 4620 | CS9: 13485.83 | CT9: 0 | CU9: 1050 | CV9: 0 | CW9: 0 | CX9: 960 | CY9: 10305.03 | CZ9: 3026.7 | DA9: 0 | DB9: 633.962 | DC9: 240 | DD9: 0 | DE9: 0 | DF9: 6404.368 | DG9: 0 | DH9: 282789 | DI9: 139938 | DJ9: 0 | DK9: 139938 | DL9: 0 | DM9: 0 | DN9: 0 | DO9: 0 | DP9: 0 | DQ9: 0 | DR9: 0 | DS9: 0 | DT9: 0 | DU9: 0 | DV9: 0 | DW9: 0 | DX9: 0 | DY9: 0 | DZ9: 0 | EA9: 0 | EB9: 0 | EC9: 0 | ED9: 0 | EE9: 0 | EF9: 125641 | EG9: 0 | EH9: 0 | EI9: 435106.47 | EJ9: 0 | EK9: 0 | EL9: 0 | EM9: 0 | EN9: 0 | EO9: 16037 | EP9: 0 | EQ9: 16037 | ER9: 44955 | ES9: 0 | ET9: 0 | EU9: 540 | EV9: 222 | EW9: 0 | EX9: 0 | EY9: 222 | EZ9: 0 | FA9: 0 | FB9: 0 | FC9: 0 | FD9: 0 | FE9: 45000 | FF9: 0 | FG9: 45000 | FH9: 0 | FI9: 991475.2 | FJ9: 44270.45 | FK9: 44270.45 | FL9: 0 | FM9: 31071 | FN9: 0 | FO9: 0 | FP9: 0 | FQ9: 0 | FR9: 31071 | FS9: 0 | FT9: 44268.936 | FU9: 110672.34 | FV9: 16600.851 | FY9: 5533617 | FZ9: 6477388.2 | GA9: 1326634.7 | GB9: 5150753.5 | GC9: 382863.46 | GD9: 0.069188645 | GE9: -943771.22 | GF9: -0.17055232 | GJ9: 45587 | GL9: 45608 | GO9: 45612 | GR9: - - | GU9: - - | HA9: 45624 | HB9: 45632 | HE9: 37 | HF9: 3 | HG9: 11 | HH9: 23 | HK9: 195 | HL9: 30 | HM9: 19 | HN9: 26 | HO9: 0 | HP9: 8 | HQ9: 160 | HR9: 137
A10: =ROW()-1 -> 9 | B10: 2024 | C10: 12月 | D10: 大港 | E10: 50528 | F10: 李军 | G10: ZJ50J | H10: 大港勘探事业部 | I10: 板171X1 | J10: 板桥（≥3500米） | K10: 评价井 | L10: 定向井 | M10: 2 | N10: 3605 | O10: 3560 | P10: 8 | Q10: 0 | R10: 19 | S10: 11 | T10: 30 | U10: 38 | V10: 0 | W10: 1 | X10: 1.2666667 | Y10: 6133129 | Z10: -263420.2 | AA10: 6396549.2 | AB10: 1020933.7 | AC10: 443333.33 | AD10: 443333.33 | AE10: 0 | AF10: 42485.221 | AG10: 42485.221 | AH10: 0 | AI10: 15781.813 | AJ10: 6985.445 | AK10: 6403.6513 | AL10: 2392.7164 | AM10: 0 | AN10: 0 | AO10: 0 | AP10: 0 | AQ10: 0 | AR10: 0 | AS10: 0 | AT10: 0 | AU10: 0 | AV10: 0 | AW10: 0 | AX10: 0 | AY10: 519333.33 | AZ10: 5375615.5 | BA10: 1815965.1 | BB10: 101825.83 | BC10: 101825.83 | BD10: 0 | BE10: 0 | BF10: 396810 | BG10: 396810 | BH10: 0 | BI10: 0 | BJ10: 838261 | BK10: 27062.33 | BL10: 27062.33 | BM10: 0 | BN10: 55694.52 | BO10: 123828.69 | BP10: 48000 | BQ10: 0 | BR10: 0 | BS10: 75828.69 | BT10: 272482.74 | BU10: 224280 | BV10: 48202.74 | BW10: 0 | BX10: 0 | BY10: 27695.69 | BZ10: 27695.69 | CA10: 3370.68 | CB10: 12852.97 | CC10: 11472.04 | CD10: 0 | CE10: 0 | CF10: 0 | CG10: 0 | CH10: 3531954.7 | CI10: 228704 | CJ10: 0 | CK10: 0 | CL10: 109982 | CM10: 24726 | CN10: 14964 | CO10: 79032 | CP10: 437000 | CQ10: 18068.94 | CR10: 4264.66 | CS10: 12416.28 | CT10: 0 | CU10: 588 | CV10: 0 | CW10: 0 | CX10: 800 | CY10: 4325.18 | CZ10: 1686.25 | DA10: 0 | DB10: 400 | DC10: 36.666667 | DD10: 0 | DE10: 0 | DF10: 2202.2633 | DG10: 0 | DH10: 370466 | DI10: 138083.4 | DJ10: 0 | DK10: 138083.4 | DL10: 0 | DM10: 0 | DN10: 0 | DO10: 0 | DP10: 0 | DQ10: 0 | DR10: 0 | DS10: 0 | DT10: 0 | DU10: 0 | DV10: 0 | DW10: 0 | DX10: 0 | DY10: 0 | DZ10: 0 | EA10: 0 | EB10: 0 | EC10: 0 | ED10: 0 | EE10: 0 | EF10: 32410 | EG10: 0 | EH10: 0 | EI10: 808952.86 | EJ10: 0 | EK10: 0 | EL10: 56744 | EM10: 0 | EN10: 0 | EO10: 14694 | EP10: 0 | EQ10: 14694 | ER10: 37962 | ES10: 0 | ET10: 0 | EU10: 0 | EV10: 126.66667 | EW10: 0 | EX10: 0 | EY10: 126.66667 | EZ10: 0 | FA10: 0 | FB10: 0 | FC10: 0 | FD10: 0 | FE10: 68000 | FF10: 0 | FG10: 68000 | FH10: 0 | FI10: 1074839.8 | FJ10: 44270.45 | FK10: 44270.45 | FL10: 0 | FM10: 7180.3633 | FN10: 0 | FO10: 0 | FP10: 0 | FQ10: 0 | FR10: 7180.3633 | FS10: 0 | FT10: 49065.032 | FU10: 122662.58 | FV10: 18399.387 | FY10: 6133129 | FZ10: 6396549.2 | GA10: 1020933.7 | GB10: 5375615.5 | GC10: 757513.5 | GD10: 0.12351175 | GE10: -263420.2 | GF10: -0.042950377 | GJ10: 45614 | GL10: 45622 | GO10: 45626 | GR10: - - | GU10: - - | HA10: 45641 | HB10: 45652 | HE10: 37 | HF10: 3 | HG10: 11 | HH10: 23 | HK10: 237 | HL10: 51 | HM10: 25 | HN10: 47 | HO10: 2 | HP10: 24 | HQ10: 240 | HR10: 102
A11: =ROW()-1 -> 10 | B11: 2024 | C11: 2月 | D11: 大港 | E11: 70520 | F11: 罗健 | G11: ZJ70D | H11: 大港采油四厂 | I11: 板19-42 | J11: 板桥（＜3500米） | K11: 开发井 | L11: 定向井 | M11: 2 | N11: 3390 | O11: 3472 | P11: 0 | Q11: 0 | R11: 18 | S11: 10 | T11: 28 | U11: 28 | V11: 0 | W11: 0.93333333 | X11: 0.93333333 | Y11: 5046544 | Z11: -1498994.6 | AA11: 6545538.6 | AB11: 876946.78 | AC11: 443333.33 | AD11: 443333.33 | AE11: 0 | AF11: 34873.527 | AG11: 34873.527 | AH11: 0 | AI11: 16073.251 | AJ11: 11876.055 | AK11: 4019.3854 | AL11: 177.81069 | AM11: 0 | AN11: 0 | AO11: 0 | AP11: 0 | AQ11: 0 | AR11: 0 | AS11: 0 | AT11: 0 | AU11: 0 | AV11: 0 | AW11: 0 | AX11: 0 | AY11: 382666.67 | AZ11: 5668591.8 | BA11: 2192017 | BB11: 53522.122 | BC11: 53522.122 | BD11: 0 | BE11: 0 | BF11: 377940 | BG11: 377940 | BH11: 0 | BI11: 12396.672 | BJ11: 940537 | BK11: 323233.23 | BL11: 44033.23 | BM11: 279200 | BN11: 92928.381 | BO11: 121960.63 | BP11: 44800 | BQ11: 0 | BR11: 0 | BS11: 77160.63 | BT11: 269498.93 | BU11: 218736 | BV11: 50762.93 | BW11: 0 | BX11: 0 | BY11: 264680.27 | BZ11: 126470.15 | CA11: 27535.99 | CB11: 24044.61 | CC11: 74889.55 | CD11: 138210.12 | CE11: 138210.12 | CF11: 0 | CG11: 0 | CH11: 3211894.6 | CI11: 443320 | CJ11: 0 | CK11: 0 | CL11: 188448 | CM11: 74472 | CN11: 32063 | CO11: 148337 | CP11: 364000 | CQ11: 13840.797 | CR11: 1776.94 | CS11: 9863 | CT11: 0 | CU11: 458 | CV11: 0 | CW11: 0 | CX11: 1742.8571 | CY11: 17345.927 | CZ11: 4873.7857 | DA11: 0 | DB11: 417.79 | DC11: 138.57143 | DD11: 0 | DE11: 5200 | DF11: 6715.78 | DG11: 0 | DH11: 239024 | DI11: 117615.4 | DJ11: 0 | DK11: 117615.4 | DL11: 0 | DM11: 0 | DN11: 0 | DO11: 0 | DP11: 0 | DQ11: 0 | DR11: 0 | DS11: 0 | DT11: 0 | DU11: 0 | DV11: 0 | DW11: 0 | DX11: 0 | DY11: 0 | DZ11: 0 | EA11: 0 | EB11: 0 | EC11: 0 | ED11: 0 | EE11: 0 | EF11: 31818 | EG11: 0 | EH11: 18209 | EI11: 408974.6 | EJ11: 0 | EK11: 0 | EL11: 0 | EM11: 0 | EN11: 170000 | EO11: 20737.5 | EP11: 0 | EQ11: 20737.5 | ER11: 34020 | ES11: 0 | ET11: 0 | EU11: 4500 | EV11: 93.333333 | EW11: 0 | EX11: 0 | EY11: 93.333333 | EZ11: 0 | FA11: 0 | FB11: 0 | FC11: 0 | FD11: 0 | FE11: 121304 | FF11: 0 | FG11: 121304 | FH11: 0 | FI11: 994632.67 | FJ11: 41212.04 | FK11: 41212.04 | FL11: 0 | FM11: 14804.429 | FN11: 0 | FO11: 0 | FP11: 0 | FQ11: 0 | FR11: 14804.429 | FS11: 0 | FT11: 40372.352 | FU11: 100930.88 | FV11: 15139.632 | FY11: 5046544 | FZ11: 6545538.6 | GA11: 876946.78 | GB11: 5668591.8 | GC11: -622047.79 | GD11: -0.12326214 | GE11: -1498994.6 | GF11: -0.29703389 | GJ11: 45305 | GL11: 45312 | GO11: 45316 | GR11: - - | GU11: - - | HA11: 45330 | HB11: 45340 | HE11: 45 | HF11: 5 | HG11: 14 | HH11: 26 | HK11: 213 | HL11: 61 | HM11: 87 | HN11: 0 | HO11: 0 | HP11: 0 | HQ11: 163 | HR11: 137
A12: =ROW()-1 -> 11 | B12: 2024 | C12: 3月 | D12: 大港 | E12: 50528 | F12: 李军 | G12: ZJ50J | H12: 大港采油四厂 | I12: 板22-7 | J12: 板桥（≥3500米） | K12: 开发井 | L12: 定向井 | M12: 2 | N12: 3722 | O12: 3737 | P12: 6 | Q12: 0 | R12: 24 | S12: 6 | T12: 30 | U12: 36 | V12: 0 | W12: 1 | X12: 1.2 | Y12: 7938979 | Z12: 1252145.4 | AA12: 6686833.6 | AB12: 967200.35 | AC12: 420000 | AD12: 420000 | AE12: 0 | AF12: 40249.157 | AG12: 40249.157 | AH12: 0 | AI12: 14951.191 | AJ12: 6617.79 | AK12: 6066.617 | AL12: 2266.784 | AM12: 0 | AN12: 0 | AO12: 0 | AP12: 0 | AQ12: 0 | AR12: 0 | AS12: 0 | AT12: 0 | AU12: 0 | AV12: 0 | AW12: 0 | AX12: 0 | AY12: 492000 | AZ12: 5719633.2 | BA12: 1720797.1 | BB12: 146436.99 | BC12: 146436.99 | BD12: 0 | BE12: 0 | BF12: 322170 | BG12: 322170 | BH12: 0 | BI12: 33225.984 | BJ12: 400582 | BK12: 343090.51 | BL12: 120480.1 | BM12: 222610.41 | BN12: 73766.46 | BO12: 124047.87 | BP12: 48000 | BQ12: 0 | BR12: 0 | BS12: 76047.87 | BT12: 277477.31 | BU12: 235431 | BV12: 42046.31 | BW12: 0 | BX12: 0 | BY12: 322831.32 | BZ12: 313750.25 | CA12: 261405.9 | CB12: 25670.06 | CC12: 26674.29 | CD12: 9081.07 | CE12: 0 | CF12: 9081.07 | CG12: 0 | CH12: 3676004.8 | CI12: 355549 | CJ12: 0 | CK12: 0 | CL12: 174499 | CM12: 77828 | CN12: 28976 | CO12: 74246 | CP12: 414000 | CQ12: 20545.76 | CR12: 4264.66 | CS12: 14893.1 | CT12: 0 | CU12: 588 | CV12: 0 | CW12: 0 | CX12: 800 | CY12: 25625.18 | CZ12: 1686.25 | DA12: 0 | DB12: 400 | DC12: 36.666667 | DD12: 0 | DE12: 21300 | DF12: 2202.2633 | DG12: 0 | DH12: 202152 | DI12: 113535.2 | DJ12: 0 | DK12: 113535.2 | DL12: 0 | DM12: 0 | DN12: 0 | DO12: 0 | DP12: 0 | DQ12: 0 | DR12: 0 | DS12: 0 | DT12: 0 | DU12: 0 | DV12: 0 | DW12: 0 | DX12: 0 | DY12: 0 | DZ12: 0 | EA12: 0 | EB12: 0 | EC12: 0 | ED12: 0 | EE12: 0 | EF12: 37272 | EG12: 0 | EH12: 0 | EI12: 712484.7 | EJ12: 0 | EK12: 0 | EL12: 0 | EM12: 0 | EN12: 75180 | EO12: 14141 | EP12: 0 | EQ12: 14141 | ER12: 35964 | ES12: 0 | ET12: 0 | EU12: 0 | EV12: 120 | EW12: 0 | EX12: 0 | EY12: 120 | EZ12: 0 | FA12: 0 | FB12: 0 | FC12: 0 | FD12: 0 | FE12: 151587 | FF12: 0 | FG12: 151587 | FH12: 0 | FI12: 1220289.8 | FJ12: 44270.45 | FK12: 44270.45 | FL12: 0 | FM12: 7180.3633 | FN12: 0 | FO12: 0 | FP12: 0 | FQ12: 0 | FR12: 7180.3633 | FS12: 0 | FT12: 63511.832 | FU12: 158779.58 | FV12: 23816.937 | FY12: 7938979 | FZ12: 6686833.6 | GA12: 967200.35 | GB12: 5719633.2 | GC12: 2219345.8 | GD12: 0.27955053 | GE12: 1252145.4 | GF12: 0.15772122 | GJ12: 45344 | GL12: 45350 | GO12: 45363 | GR12: - - | GU12: - - | HA12: 45374 | HB12: 45380 | HE12: 37 | HF12: 2 | HG12: 12 | HH12: 23 | HK12: 154 | HL12: 70 | HM12: 79 | HN12: 0 | HO12: 0 | HP12: 0 | HQ12: 152 | HR12: 54
A13: =ROW()-1 -> 12 | B13: 2024 | C13: 2月 | D13: 大港 | E13: BHZ70003 | F13: 张朝相 | G13: ZJ70D | H13: 大港采油四厂 | I13: 板22-8 | J13: 板桥 | K13: 开发井 | L13: 定向井 | M13: 3 | N13: 3818 | O13: 3894 | P13: 13 | Q13: 0 | R13: 21 | S13: 8 | T13: 29 | U13: 42 | V13: 0 | W13: 0.96666667 | X13: 1.4 | Y13: 10245520 | Z13: 54155.521 | AA13: 10191364 | AB13: 1496139.3 | AC13: 455000 | AD13: 455000 | AE13: 0 | AF13: 333713.25 | AG13: 189684.68 | AH13: 144028.56 | AI13: 15283.746 | AJ13: 4544.7897 | AK13: 4519.487 | AL13: 6219.4697 | AM13: 118142.33 | AN13: 118142.33 | AO13: 0 | AP13: 0 | AQ13: 0 | AR13: 0 | AS13: 0 | AT13: 0 | AU13: 0 | AV13: 0 | AW13: 0 | AX13: 0 | AY13: 574000 | AZ13: 8695225.2 | BA13: 2949997.2 | BB13: 248572.03 | BC13: 248572.03 | BD13: 0 | BE13: 0 | BF13: 535472 | BG13: 535472 | BH13: 0 | BI13: 68189.04 | BJ13: 1050608 | BK13: 34426.69 | BL13: 34426.69 | BM13: 0 | BN13: 579252.25 | BO13: 139904.39 | BP13: 46400 | BQ13: 0 | BR13: 0 | BS13: 93504.39 | BT13: 293572.79 | BU13: 245322 | BV13: 48250.79 | BW13: 0 | BX13: 0 | BY13: 576998.75 | BZ13: 576998.75 | CA13: 67115.56 | CB13: 335715.55 | CC13: 174167.64 | CD13: 0 | CE13: 0 | CF13: 0 | CG13: 0 | CH13: 5168229.2 | CI13: 631611 | CJ13: 0 | CK13: 0 | CL13: 225142 | CM13: 230954 | CN13: 37052 | CO13: 138463 | CP13: 504000 | CQ13: 14827.25 | CR13: 3553.88 | CS13: 8806.87 | CT13: 0 | CU13: 1266.5 | CV13: 0 | CW13: 0 | CX13: 1200 | CY13: 9619.566 | CZ13: 5783.875 | DA13: 0 | DB13: 455.1875 | DC13: 270 | DD13: 0 | DE13: 0 | DF13: 3110.5035 | DG13: 0 | DH13: 299718 | DI13: 104127.4 | DJ13: 0 | DK13: 104127.4 | DL13: 0 | DM13: 0 | DN13: 0 | DO13: 0 | DP13: 0 | DQ13: 0 | DR13: 0 | DS13: 0 | DT13: 0 | DU13: 0 | DV13: 0 | DW13: 0 | DX13: 0 | DY13: 0 | DZ13: 0 | EA13: 0 | EB13: 0 | EC13: 0 | ED13: 0 | EE13: 0 | EF13: 51209 | EG13: 0 | EH13: 12139 | EI13: 738660.43 | EJ13: 0 | EK13: 0 | EL13: 0 | EM13: 0 | EN13: 160000 | EO13: 18723 | EP13: 0 | EQ13: 18723 | ER13: 41958 | ES13: 0 | ET13: 0 | EU13: 3600 | EV13: 140 | EW13: 0 | EX13: 0 | EY13: 140 | EZ13: 0 | FA13: 0 | FB13: 0 | FC13: 0 | FD13: 0 | FE13: 118708 | FF13: 0 | FG13: 118708 | FH13: 0 | FI13: 1995653.2 | FJ13: 137499.29 | FK13: 137499.29 | FL13: 0 | FM13: 8425 | FN13: 0 | FO13: 0 | FP13: 0 | FQ13: 0 | FR13: 8425 | FS13: 0 | FT13: 81964.16 | FU13: 204910.4 | FV13: 30736.56 | FY13: 10245520 | FZ13: 10191364 | GA13: 1496139.3 | GB13: 8695225.2 | GC13: 1550294.8 | GD13: 0.15131441 | GE13: 54155.521 | GF13: 0.0052857757 | GJ13: 45304 | GL13: 45317 | GO13: 45321 | GR13: 45330 | GU13: - - | HA13: 45338 | HB13: 45346 | HE13: 37 | HF13: 5 | HG13: 8 | HH13: 24 | HK13: 185 | HL13: 34 | HM13: 76 | HN13: 0 | HO13: 0 | HP13: 0 | HQ13: 279 | HR13: 121
A14: =ROW()-1 -> 13 | B14: 2024 | C14: 1月 | D14: 大港 | E14: 50528 | F14: 李军 | G14: ZJ50J | H14: 大港采油四厂 | I14: 板22-9 | J14: 板桥 | K14: 开发井 | L14: 定向井 | M14: 3 | N14: 3853 | O14: 3918 | P14: 9 | Q14: 0 | R14: 32 | S14: 7 | T14: 39 | U14: 48 | V14: 0 | W14: 1.3 | X14: 1.6 | Y14: 9384117 | Z14: -964786 | AA14: 10348903 | AB14: 1289600.5 | AC14: 560000 | AD14: 560000 | AE14: 0 | AF14: 53665.543 | AG14: 53665.543 | AH14: 0 | AI14: 19934.921 | AJ14: 8823.72 | AK14: 8088.8227 | AL14: 3022.3787 | AM14: 0 | AN14: 0 | AO14: 0 | AP14: 0 | AQ14: 0 | AR14: 0 | AS14: 0 | AT14: 0 | AU14: 0 | AV14: 0 | AW14: 0 | AX14: 0 | AY14: 656000 | AZ14: 9059302.5 | BA14: 3277016.1 | BB14: 148955.64 | BC14: 120969.56 | BD14: 27986.08 | BE14: 0 | BF14: 601477 | BG14: 601477 | BH14: 0 | BI14: 15499.512 | BJ14: 1444721 | BK14: 41678.4 | BL14: 41678.4 | BM14: 0 | BN14: 541923.55 | BO14: 161066.78 | BP14: 62400 | BQ14: 0 | BR14: 0 | BS14: 98666.78 | BT14: 321694.25 | BU14: 246834 | BV14: 74860.25 | BW14: 0 | BX14: 0 | BY14: 217211.76 | BZ14: 217211.76 | CA14: 33515.93 | CB14: 16924.72 | CC14: 166771.11 | CD14: 0 | CE14: 0 | CF14: 0 | CG14: 0 | CH14: 5565074.6 | CI14: 558931 | CJ14: 0 | CK14: 0 | CL14: 124328 | CM14: 204557 | CN14: 61277 | CO14: 168769 | CP14: 576000 | CQ14: 14657.85 | CR14: 4264.66 | CS14: 9005.19 | CT14: 0 | CU14: 588 | CV14: 0 | CW14: 0 | CX14: 800 | CY14: 36225.18 | CZ14: 1686.25 | DA14: 0 | DB14: 400 | DC14: 36.666667 | DD14: 0 | DE14: 31900 | DF14: 2202.2633 | DG14: 0 | DH14: 709601 | DI14: 166522.9 | DJ14: 0 | DK14: 0 | DL14: 0 | DM14: 0 | DN14: 0 | DO14: 120000 | DP14: 46522.9 | DQ14: 0 | DR14: 0 | DS14: 0 | DT14: 0 | DU14: 0 | DV14: 0 | DW14: 0 | DX14: 0 | DY14: 0 | DZ14: 0 | EA14: 0 | EB14: 0 | EC14: 0 | ED14: 0 | EE14: 0 | EF14: 55525 | EG14: 0 | EH14: 19148 | EI14: 924179.35 | EJ14: 0 | EK14: 0 | EL14: 80110 | EM14: 0 | EN14: 0 | EO14: 14141 | EP14: 0 | EQ14: 14141 | ER14: 49248 | ES14: 0 | ET14: 0 | EU14: 0 | EV14: 160 | EW14: 0 | EX14: 0 | EY14: 160 | EZ14: 0 | FA14: 0 | FB14: 0 | FC14: 0 | FD14: 0 | FE14: 0 | FF14: 0 | FG14: 0 | FH14: 0 | FI14: 1938869.7 | FJ14: 123667.65 | FK14: 123667.65 | FL14: 0 | FM14: 7180.3633 | FN14: 0 | FO14: 0 | FP14: 0 | FQ14: 0 | FR14: 7180.3633 | FS14: 0 | FT14: 75072.936 | FU14: 187682.34 | FV14: 28152.351 | FY14: 9384117 | FZ14: 10348903 | GA14: 1289600.5 | GB14: 9059302.5 | GC14: 324814.47 | GD14: 0.034613216 | GE14: -964786 | GF14: -0.10281053 | GJ14: 45264 | GL14: 45273 | GO14: 45277 | GR14: 45289 | GU14: - - | HA14: 45305 | HB14: 45312 | HE14: 38 | HF14: 2 | HG14: 12 | HH14: 24 | HK14: 200 | HL14: 71 | HM14: 261 | HN14: 0 | HO14: 0 | HP14: 0 | HQ14: 293 | HR14: 118
A15: =ROW()-1 -> 14 | B15: 2024 | C15: 9月 | D15: 大港 | E15: 50528 | F15: 李军 | G15: ZJ50J | H15: 大港采油四厂 | I15: 板67-2 | J15: 板桥（＜2500米） | K15: 评价井 | L15: 定向井 | M15: 2 | N15: 2043 | O15: 2110 | P15: 11 | Q15: 0 | R15: 8 | S15: 8 | T15: 16 | U15: 27 | V15: 0 | W15: 0.53333333 | X15: 0.9 | Y15: 3100000 | Z15: -1677172.5 | AA15: 4777172.5 | AB15: 725400.26 | AC15: 315000 | AD15: 315000 | AE15: 0 | AF15: 30186.868 | AG15: 30186.868 | AH15: 0 | AI15: 11213.393 | AJ15: 4963.3425 | AK15: 4549.9627 | AL15: 1700.088 | AM15: 0 | AN15: 0 | AO15: 0 | AP15: 0 | AQ15: 0 | AR15: 0 | AS15: 0 | AT15: 0 | AU15: 0 | AV15: 0 | AW15: 0 | AX15: 0 | AY15: 369000 | AZ15: 4051772.2 | BA15: 1631870.2 | BB15: 126579.82 | BC15: 126579.82 | BD15: 0 | BE15: 0 | BF15: 243749 | BG15: 243749 | BH15: 0 | BI15: 15479.454 | BJ15: 350216 | BK15: 10516.85 | BL15: 10516.85 | BM15: 0 | BN15: 637455.19 | BO15: 115017.85 | BP15: 25600 | BQ15: 0 | BR15: 0 | BS15: 89417.85 | BT15: 132856.08 | BU15: 113940 | BV15: 18916.08 | BW15: 0 | BX15: 0 | BY15: 310386 | BZ15: 310386 | CA15: 226578.49 | CB15: 55096.46 | CC15: 28711.05 | CD15: 0 | CE15: 0 | CF15: 0 | CG15: 0 | CH15: 2109516 | CI15: 254299 | CJ15: 0 | CK15: 0 | CL15: 102640 | CM15: 76701 | CN15: 29453 | CO15: 45505 | CP15: 310500 | CQ15: 9650.94 | CR15: 3553.88 | CS15: 4709.06 | CT15: 0 | CU15: 588 | CV15: 0 | CW15: 0 | CX15: 800 | CY15: 4325.18 | CZ15: 1686.25 | DA15: 0 | DB15: 400 | DC15: 36.666667 | DD15: 0 | DE15: 0 | DF15: 2202.2633 | DG15: 0 | DH15: 354680 | DI15: 0 | DJ15: 0 | DK15: 0 | DL15: 0 | DM15: 0 | DN15: 0 | DO15: 0 | DP15: 0 | DQ15: 0 | DR15: 0 | DS15: 0 | DT15: 0 | DU15: 0 | DV15: 0 | DW15: 0 | DX15: 0 | DY15: 0 | DZ15: 0 | EA15: 0 | EB15: 0 | EC15: 0 | ED15: 0 | EE15: 0 | EF15: 20070 | EG15: 0 | EH15: 9104 | EI15: 327911.04 | EJ15: 0 | EK15: 0 | EL15: 0 | EM15: 52318 | EN15: 0 | EO15: 8887.5 | EP15: 0 | EQ15: 8887.5 | ER15: 26973 | ES15: 0 | ET15: 0 | EU15: 0 | EV15: 90 | EW15: 0 | EX15: 0 | EY15: 90 | EZ15: 0 | FA15: 0 | FB15: 0 | FC15: 0 | FD15: 0 | FE15: 0 | FF15: 0 | FG15: 0 | FH15: 0 | FI15: 583156.49 | FJ15: 44270.45 | FK15: 44270.45 | FL15: 0 | FM15: 7180.3633 | FN15: 0 | FO15: 0 | FP15: 0 | FQ15: 0 | FR15: 7180.3633 | FS15: 0 | FT15: 24800 | FU15: 62000 | FV15: 9300 | FY15: 3100000 | FZ15: 4777172.5 | GA15: 725400.26 | GB15: 4051772.2 | GC15: -951772.21 | GD15: -0.30702329 | GE15: -1677172.5 | GF15: -0.54102338 | GJ15: 45538 | GL15: 45549 | GO15: 45552 | GR15: - - | GU15: - - | HA15: 45557 | HB15: 45565 | HE15: 37 | HF15: 2 | HG15: 12 | HH15: 23 | HK15: 74 | HL15: 26 | HM15: 12 | HN15: 8 | HO15: 2 | HP15: 24 | HQ15: 128 | HR15: 109
A16: =ROW()-1 -> 15 | B16: 2024 | C16: 2月 | D16: 大港 | E16: 50528 | F16: 李军 | G16: ZJ50J | H16: 大港采油四厂 | I16: 板南3-20H | J16: 板桥 | K16: 开发井 | L16: 水平井 | M16: 2 | N16: 2216 | O16: 2270 | P16: 5 | Q16: 0 | R16: 9 | S16: 4 | T16: 13 | U16: 18 | V16: 0 | W16: 0.43333333 | X16: 0.6 | Y16: 3780959 | Z16: -77578.354 | AA16: 3858537.4 | AB16: 483600.17 | AC16: 210000 | AD16: 210000 | AE16: 0 | AF16: 20124.578 | AG16: 20124.578 | AH16: 0 | AI16: 7475.5955 | AJ16: 3308.895 | AK16: 3033.3085 | AL16: 1133.392 | AM16: 0 | AN16: 0 | AO16: 0 | AP16: 0 | AQ16: 0 | AR16: 0 | AS16: 0 | AT16: 0 | AU16: 0 | AV16: 0 | AW16: 0 | AX16: 0 | AY16: 246000 | AZ16: 3374937.2 | BA16: 1406987.1 | BB16: 57153.978 | BC16: 57153.978 | BD16: 0 | BE16: 0 | BF16: 667275 | BG16: 667275 | BH16: 0 | BI16: 0 | BJ16: 380042 | BK16: 18407.96 | BL16: 18407.96 | BM16: 0 | BN16: 25698.44 | BO16: 99663.49 | BP16: 20800 | BQ16: 0 | BR16: 0 | BS16: 78863.49 | BT16: 158746.28 | BU16: 143010 | BV16: 15736.28 | BW16: 0 | BX16: 0 | BY16: 73652.15 | BZ16: 73652.15 | CA16: 49698.49 | CB16: 17874.05 | CC16: 6079.61 | CD16: 0 | CE16: 0 | CF16: 0 | CG16: 0 | CH16: 1894297.9 | CI16: 188734 | CJ16: 0 | CK16: 0 | CL16: 95797 | CM16: 54703 | CN16: 2614 | CO16: 35620 | CP16: 207000 | CQ16: 10638.18 | CR16: 3553.88 | CS16: 5694.3 | CT16: 0 | CU16: 590 | CV16: 0 | CW16: 0 | CX16: 800 | CY16: 4325.18 | CZ16: 1686.25 | DA16: 0 | DB16: 400 | DC16: 36.666667 | DD16: 0 | DE16: 0 | DF16: 2202.2633 | DG16: 0 | DH16: 274073 | DI16: 82738.34 | DJ16: 0 | DK16: 48287.04 | DL16: 0 | DM16: 0 | DN16: 0 | DO16: 0 | DP16: 34451.3 | DQ16: 0 | DR16: 0 | DS16: 0 | DT16: 0 | DU16: 0 | DV16: 0 | DW16: 0 | DX16: 0 | DY16: 0 | DZ16: 0 | EA16: 0 | EB16: 0 | EC16: 0 | ED16: 0 | EE16: 0 | EF16: 20933 | EG16: 0 | EH16: 7587 | EI16: 239325.83 | EJ16: 0 | EK16: 0 | EL16: 0 | EM16: 52318 | EN16: 0 | EO16: 6636 | EP16: 0 | EQ16: 6636 | ER16: 17982 | ES16: 0 | ET16: 0 | EU16: 0 | EV16: 60 | EW16: 0 | EX16: 0 | EY16: 60 | EZ16: 0 | FA16: 0 | FB16: 0 | FC16: 0 | FD16: 0 | FE16: 0 | FF16: 0 | FG16: 0 | FH16: 0 | FI16: 613286.81 | FJ16: 44270.45 | FK16: 44270.45 | FL16: 0 | FM16: 7180.3633 | FN16: 0 | FO16: 0 | FP16: 0 | FQ16: 0 | FR16: 7180.3633 | FS16: 0 | FT16: 30247.672 | FU16: 75619.18 | FV16: 11342.877 | FY16: 3780959 | FZ16: 3858537.4 | GA16: 483600.17 | GB16: 3374937.2 | GC16: 406021.82 | GD16: 0.10738594 | GE16: -77578.354 | GF16: -0.020518169 | GJ16: 45316 | GL16: 45321 | GO16: 45324 | GR16: - - | GU16: - - | HA16: 45330 | HB16: 45334 | HE16: 37 | HF16: 2 | HG16: 12 | HH16: 23 | HK16: 71 | HL16: 32 | HM16: 61 | HN16: 0 | HO16: 0 | HP16: 0 | HQ16: 117 | HR16: 14
A17: =ROW()-1 -> 16 | B17: 2024 | C17: 3月 | D17: 大港 | E17: 70520 | F17: 罗健 | G17: ZJ70D | H17: 大港采油四厂 | I17: 板南3-21 | J17: 板桥（＜2500米） | K17: 开发井 | L17: 定向井 | M17: 2 | N17: 1833 | O17: 1847 | P17: 5 | Q17: 0 | R17: 5 | S17: 4 | T17: 9 | U17: 14 | V17: 0 | W17: 0.3 | X17: 0.46666667 | Y17: 2338602 | Z17: -1219054.8 | AA17: 3557656.8 | AB17: 474755.11 | AC17: 221666.67 | AD17: 221666.67 | AE17: 0 | AF17: 13949.411 | AG17: 13949.411 | AH17: 0 | AI17: 6429.3005 | AJ17: 4750.4221 | AK17: 1607.7542 | AL17: 71.124278 | AM17: 41376.401 | AN17: 0 | AO17: 0 | AP17: 0 | AQ17: 41376.401 | AR17: 0 | AS17: 0 | AT17: 0 | AU17: 0 | AV17: 0 | AW17: 0 | AX17: 0 | AY17: 191333.33 | AZ17: 3082901.6 | BA17: 1115555.5 | BB17: 58721.414 | BC17: 58721.414 | BD17: 0 | BE17: 0 | BF17: 237317 | BG17: 237317 | BH17: 0 | BI17: 33462.936 | BJ17: 311389 | BK17: 21485.22 | BL17: 21485.22 | BM17: 0 | BN17: 257176.01 | BO17: 87992.73 | BP17: 14400 | BQ17: 0 | BR17: 0 | BS17: 73592.73 | BT17: 108011.2 | BU17: 99738 | BV17: 8273.2 | BW17: 0 | BX17: 0 | BY17: 500928.72 | BZ17: 65804.25 | CA17: 18595.49 | CB17: 4982.29 | CC17: 42226.47 | CD17: 435124.47 | CE17: 435124.47 | CF17: 0 | CG17: 0 | CH17: 1466417.4 | CI17: 337726 | CJ17: 0 | CK17: 0 | CL17: 188448 | CM17: 76516 | CN17: 29689 | CO17: 43073 | CP17: 182000 | CQ17: 16552.067 | CR17: 1421.55 | CS17: 12929.66 | CT17: 0 | CU17: 458 | CV17: 0 | CW17: 0 | CX17: 1742.8571 | CY17: 31145.927 | CZ17: 4873.7857 | DA17: 0 | DB17: 417.79 | DC17: 138.57143 | DD17: 0 | DE17: 19000 | DF17: 6715.78 | DG17: 0 | DH17: 107517 | DI17: 0 | DJ17: 0 | DK17: 0 | DL17: 0 | DM17: 0 | DN17: 0 | DO17: 0 | DP17: 0 | DQ17: 0 | DR17: 0 | DS17: 0 | DT17: 0 | DU17: 0 | DV17: 0 | DW17: 0 | DX17: 0 | DY17: 0 | DZ17: 0 | EA17: 0 | EB17: 0 | EC17: 0 | ED17: 0 | EE17: 0 | EF17: 17563 | EG17: 0 | EH17: 5311 | EI17: 175677.92 | EJ17: 0 | EK17: 0 | EL17: 0 | EM17: 0 | EN17: 0 | EO17: 9717 | EP17: 0 | EQ17: 9717 | ER17: 17010 | ES17: 0 | ET17: 0 | EU17: 0 | EV17: 46.666667 | EW17: 0 | EX17: 0 | EY17: 46.666667 | EZ17: 0 | FA17: 0 | FB17: 0 | FC17: 0 | FD17: 0 | FE17: 0 | FF17: 0 | FG17: 0 | FH17: 0 | FI17: 437637.7 | FJ17: 41212.04 | FK17: 41212.04 | FL17: 0 | FM17: 14804.429 | FN17: 0 | FO17: 0 | FP17: 0 | FQ17: 0 | FR17: 14804.429 | FS17: 0 | FT17: 18708.816 | FU17: 46772.04 | FV17: 7015.806 | FY17: 2338602 | FZ17: 3557656.8 | GA17: 474755.11 | GB17: 3082901.6 | GC17: -744299.64 | GD17: -0.31826692 | GE17: -1219054.8 | GF17: -0.521275 | GJ17: 45344 | GL17: 45349 | GO17: 45351 | GR17: - - | GU17: - - | HA17: 45354 | HB17: 45358 | HE17: 45 | HF17: 5 | HG17: 14 | HH17: 26 | HK17: 35 | HL17: 29 | HM17: 24 | HN17: 0 | HO17: 0 | HP17: 0 | HQ17: 103 | HR17: 17
A18: =ROW()-1 -> 17 | B18: 2024 | C18: 11月 | D18: 大港 | E18: BHZ70003 | F18: 张朝相 | G18: ZJ70D | H18: 大港勘探事业部 | I18: 板深18-16 | J18: 板桥 | K18: 评价井 | L18: 定向井 | M18: 4 | N18: 5265 | O18: 5196 | P18: 27 | Q18: 0 | R18: 55 | S18: 1 | T18: 56 | U18: 83 | V18: 0 | W18: 1.8666667 | X18: 2.7666667 | Y18: 18104717 | Z18: 845170.44 | AA18: 17259547 | AB18: 3450698.1 | AC18: 968333.33 | AD18: 968333.33 | AE18: 0 | AF18: 659480.94 | AG18: 374853.06 | AH18: 284627.87 | AI18: 30203.594 | AJ18: 8981.3701 | AK18: 8931.3672 | AL18: 12290.857 | AM18: 658346.87 | AN18: 233471.74 | AO18: 0 | AP18: 424875.12 | AQ18: 0 | AR18: 0 | AS18: 0 | AT18: 0 | AU18: 0 | AV18: 0 | AW18: 0 | AX18: 0 | AY18: 1134333.3 | AZ18: 13808848 | BA18: 5060870.1 | BB18: 376012.03 | BC18: 376012.03 | BD18: 0 | BE18: 0 | BF18: 1145553 | BG18: 1145553 | BH18: 0 | BI18: 33831.972 | BJ18: 1825225 | BK18: 16629.68 | BL18: 16629.68 | BM18: 0 | BN18: 801750.26 | BO18: 217765.72 | BP18: 89600 | BQ18: 0 | BR18: 0 | BS18: 128165.72 | BT18: 644102.48 | BU18: 540384 | BV18: 103718.48 | BW18: 0 | BX18: 0 | BY18: 273246.21 | BZ18: 273246.21 | CA18: 210567.08 | CB18: 46007.72 | CC18: 16671.41 | CD18: 0 | CE18: 0 | CF18: 0 | CG18: 0 | CH18: 8474732.1 | CI18: 653009 | CJ18: 0 | CK18: 0 | CL18: 220741 | CM18: 246517 | CN18: 24466 | CO18: 161285 | CP18: 1079000 | CQ18: 33983.22 | CR18: 4974.66 | CS18: 26542.06 | CT18: 0 | CU18: 1266.5 | CV18: 0 | CW18: 0 | CX18: 1200 | CY18: 9619.566 | CZ18: 5783.875 | DA18: 0 | DB18: 455.1875 | DC18: 270 | DD18: 0 | DE18: 0 | DF18: 3110.5035 | DG18: 0 | DH18: 208215 | DI18: 146626.2 | DJ18: 0 | DK18: 146626.2 | DL18: 0 | DM18: 0 | DN18: 0 | DO18: 0 | DP18: 0 | DQ18: 0 | DR18: 0 | DS18: 0 | DT18: 0 | DU18: 0 | DV18: 0 | DW18: 0 | DX18: 0 | DY18: 0 | DZ18: 0 | EA18: 0 | EB18: 0 | EC18: 0 | ED18: 0 | EE18: 0 | EF18: 104952 | EG18: 0 | EH18: 189993.36 | EI18: 1066810.4 | EJ18: 0 | EK18: 0 | EL18: 0 | EM18: 0 | EN18: 0 | EO18: 29585.5 | EP18: 0 | EQ18: 29585.5 | ER18: 89640 | ES18: 0 | ET18: 0 | EU18: 600 | EV18: 276.66667 | EW18: 0 | EX18: 0 | EY18: 276.66667 | EZ18: 0 | FA18: 0 | FB18: 0 | FC18: 0 | FD18: 0 | FE18: 0 | FF18: 0 | FG18: 0 | FH18: 0 | FI18: 4169970.1 | FJ18: 122779.8 | FK18: 122779.8 | FL18: 0 | FM18: 8425 | FN18: 0 | FO18: 0 | FP18: 0 | FQ18: 0 | FR18: 8425 | FS18: 0 | FT18: 144837.74 | FU18: 362094.34 | FV18: 54314.151 | FY18: 18104717 | FZ18: 17259547 | GA18: 3450698.1 | GB18: 13808848 | GC18: 4295868.5 | GD18: 0.23727896 | GE18: 845170.44 | GF18: 0.046682334 | GJ18: 45522 | GL18: 45549 | GO18: 45552 | GR18: 45564 | GU18: 45600 | HA18: 45604 | HB18: 45605 | HE18: 40 | HF18: 4 | HG18: 10 | HH18: 26 | HK18: 348 | HL18: 141 | HM18: 37 | HN18: 67 | HO18: 3 | HP18: 94 | HQ18: 488 | HR18: 175
A19: =ROW()-1 -> 18 | B19: 2024 | C19: 6月 | D19: 大港 | E19: BHZ70003 | F19: 张朝相 | G19: ZJ70D | H19: 大港采油四厂 | I19: 板深20-19 | J19: 板桥 | K19: 开发井 | L19: 定向井 | M19: 4 | N19: 4792 | O19: 4688 | P19: 11 | Q19: 0 | R19: 45 | S19: 4 | T19: 49 | U19: 60 | V19: 0 | W19: 1.6333333 | X19: 2 | Y19: 20757609 | Z19: 4520529.5 | AA19: 16237079 | AB19: 2394480.5 | AC19: 600000 | AD19: 600000 | AE19: 0 | AF19: 476733.21 | AG19: 270978.12 | AH19: 205755.09 | AI19: 21833.923 | AJ19: 6492.5567 | AK19: 6456.41 | AL19: 8884.9567 | AM19: 475913.4 | AN19: 168774.76 | AO19: 0 | AP19: 307138.64 | AQ19: 0 | AR19: 0 | AS19: 0 | AT19: 0 | AU19: 0 | AV19: 0 | AW19: 0 | AX19: 0 | AY19: 820000 | AZ19: 13842599 | BA19: 4123068.7 | BB19: 495782.39 | BC19: 495782.39 | BD19: 0 | BE19: 0 | BF19: 1447566 | BG19: 1447566 | BH19: 0 | BI19: 16790.22 | BJ19: 525642 | BK19: 411011.54 | BL19: 411011.54 | BM19: 0 | BN19: 325203.85 | BO19: 313662.28 | BP19: 78400 | BQ19: 0 | BR19: 0 | BS19: 235262.28 | BT19: 587410.41 | BU19: 487552 | BV19: 99858.41 | BW19: 0 | BX19: 0 | BY19: 289421.02 | BZ19: 249574.62 | CA19: 169431.11 | CB19: 11741.73 | CC19: 68401.78 | CD19: 39846.4 | CE19: 0 | CF19: 39846.4 | CG19: 0 | CH19: 9430109.3 | CI19: 545566 | CJ19: 0 | CK19: 0 | CL19: 275873 | CM19: 95606 | CN19: 3089 | CO19: 170998 | CP19: 750000 | CQ19: 33790.36 | CR19: 9240.09 | CS19: 22083.77 | CT19: 0 | CU19: 1266.5 | CV19: 0 | CW19: 0 | CX19: 1200 | CY19: 88507.566 | CZ19: 5783.875 | DA19: 0 | DB19: 455.1875 | DC19: 270 | DD19: 57900 | DE19: 0 | DF19: 24098.503 | DG19: 0 | DH19: 602224 | DI19: 84434.9 | DJ19: 0 | DK19: 0 | DL19: 0 | DM19: 0 | DN19: 0 | DO19: 0 | DP19: 84434.9 | DQ19: 0 | DR19: 0 | DS19: 0 | DT19: 0 | DU19: 0 | DV19: 0 | DW19: 0 | DX19: 0 | DY19: 0 | DZ19: 0 | EA19: 0 | EB19: 0 | EC19: 0 | ED19: 0 | EE19: 0 | EF19: 58843 | EG19: 0 | EH19: 227240.54 | EI19: 1900722.3 | EJ19: 0 | EK19: 0 | EL19: 0 | EM19: 0 | EN19: 0 | EO19: 26544 | EP19: 0 | EQ19: 26544 | ER19: 59940 | ES19: 0 | ET19: 0 | EU19: 600 | EV19: 200 | EW19: 0 | EX19: 0 | EY19: 200 | EZ19: 0 | FA19: 0 | FB19: 0 | FC19: 0 | FD19: 0 | FE19: 0 | FF19: 0 | FG19: 0 | FH19: 0 | FI19: 4120335 | FJ19: 279250.72 | FK19: 279250.72 | FL19: 0 | FM19: 8425 | FN19: 0 | FO19: 0 | FP19: 0 | FQ19: 0 | FR19: 8425 | FS19: 0 | FT19: 166060.87 | FU19: 415152.18 | FV19: 62272.827 | FY19: 20757609 | FZ19: 16237079 | GA19: 2394480.5 | GB19: 13842599 | GC19: 6915010 | GD19: 0.33313134 | GE19: 4520529.5 | GF19: 0.21777698 | GJ19: 45399 | GL19: 45410 | GO19: 45413 | GR19: 45422 | GU19: 45454 | HA19: 45455 | HB19: 45459 | HE19: 37 | HF19: 4 | HG19: 8 | HH19: 25 | HK19: 284 | HL19: 194 | HM19: 214 | HN19: 0 | HO19: 0 | HP19: 0 | HQ19: 336 | HR19: 141
A20: =ROW()-1 -> 19 | B20: 2024 | C20: 9月 | D20: 大港 | E20: 50639 | F20: 刘亚东 | G20: ZJ50J | H20: 大港勘探事业部 | I20: 滨156X1 | J20: 港东 | K20: 评价井 | L20: 定向井 | M20: 3 | N20: 3184 | O20: 3197 | P20: 8 | Q20: 0 | R20: 25 | S20: 7 | T20: 32 | U20: 40 | V20: 0 | W20: 1.0666667 | X20: 1.3333333 | Y20: 9473594 | Z20: 113827.96 | AA20: 9359766 | AB20: 1412579.3 | AC20: 800000 | AD20: 800000 | AE20: 0 | AF20: 49780.828 | AG20: 49780.828 | AH20: 0 | AI20: 16131.831 | AJ20: 5983.5256 | AK20: 5674.3622 | AL20: 4473.9433 | AM20: 0 | AN20: 0 | AO20: 0 | AP20: 0 | AQ20: 0 | AR20: 0 | AS20: 0 | AT20: 0 | AU20: 0 | AV20: 0 | AW20: 0 | AX20: 0 | AY20: 546666.67 | AZ20: 7947186.7 | BA20: 1876409.5 | BB20: 51610.619 | BC20: 51610.619 | BD20: 0 | BE20: 0 | BF20: 584111 | BG20: 584111 | BH20: 0 | BI20: 9787.9914 | BJ20: 98709 | BK20: 549228.35 | BL20: 304728.35 | BM20: 244500 | BN20: 189763.72 | BO20: 143828.74 | BP20: 51200 | BQ20: 0 | BR20: 0 | BS20: 92628.74 | BT20: 249370.11 | BU20: 201411 | BV20: 47959.11 | BW20: 0 | BX20: 0 | BY20: 362364.07 | BZ20: 164504.92 | CA20: 23376.09 | CB20: 73439.19 | CC20: 67689.64 | CD20: 197859.15 | CE20: 124932.58 | CF20: 72926.57 | CG20: 0 | CH20: 5708413.1 | CI20: 484552 | CJ20: 0 | CK20: 0 | CL20: 103449 | CM20: 213446 | CN20: 4990 | CO20: 162667 | CP20: 320000 | CQ20: 23467.083 | CR20: 7107.76 | CS20: 15252.18 | CT20: 0 | CU20: 250 | CV20: 0 | CW20: 0 | CX20: 857.14286 | CY20: 8452.0769 | CZ20: 5465.5 | DA20: 0 | DB20: 414 | DC20: 47.142857 | DD20: 0 | DE20: 0 | DF20: 2525.434 | DG20: 0 | DH20: 710998 | DI20: 0 | DJ20: 0 | DK20: 0 | DL20: 0 | DM20: 0 | DN20: 0 | DO20: 0 | DP20: 0 | DQ20: 0 | DR20: 0 | DS20: 0 | DT20: 0 | DU20: 0 | DV20: 0 | DW20: 0 | DX20: 0 | DY20: 0 | DZ20: 0 | EA20: 0 | EB20: 0 | EC20: 0 | ED20: 0 | EE20: 0 | EF20: 48039 | EG20: 0 | EH20: 126605.38 | EI20: 1439056.9 | EJ20: 0 | EK20: 0 | EL20: 25514 | EM20: 0 | EN20: 0 | EO20: 5214 | EP20: 0 | EQ20: 5214 | ER20: 43200 | ES20: 0 | ET20: 0 | EU20: 840 | EV20: 133.33333 | EW20: 0 | EX20: 0 | EY20: 133.33333 | EZ20: 0 | FA20: 0 | FB20: 0 | FC20: 0 | FD20: 0 | FE20: 0 | FF20: 0 | FG20: 0 | FH20: 0 | FI20: 2003435.2 | FJ20: 123667.65 | FK20: 123667.65 | FL20: 0 | FM20: 51557.143 | FN20: 0 | FO20: 0 | FP20: 0 | FQ20: 0 | FR20: 51557.143 | FS20: 0 | FT20: 75788.752 | FU20: 189471.88 | FV20: 28420.782 | FY20: 9473594 | FZ20: 9359766 | GA20: 1412579.3 | GB20: 7947186.7 | GC20: 1526407.3 | GD20: 0.1611223 | GE20: 113827.96 | GF20: 0.012015288 | GJ20: 45520 | GL20: 45528 | GO20: 45534 | GR20: 45547 | GU20: - - | HA20: 45553 | HB20: 45560 | HE20: 40 | HF20: 10 | HG20: 14 | HH20: 16 | HK20: 143 | HL20: 21 | HM20: 38 | HN20: 32 | HO20: 0 | HP20: 26 | HQ20: 364 | HR20: 148
A21: =ROW()-1 -> 20 | B21: 2024 | C21: 12月 | D21: 大港 | E21: 40573 | F21: 李仁义 | G21: ZJ40J | H21: 大港采油一厂 | I21: 滨161X1 | J21: 港东 | K21: 评价井 | L21: 定向井 | M21: 2 | N21: 1997 | O21: 1997 | P21: 5 | Q21: 0 | R21: 6 | S21: 3 | T21: 9 | U21: 14 | V21: 0 | W21: 0.3 | X21: 0.46666667 | Y21: 2250179 | Z21: 77266.094 | AA21: 2172912.9 | AB21: 349039.08 | AC21: 151666.67 | AD21: 151666.67 | AE21: 0 | AF21: 4379.718 | AG21: 4379.718 | AH21: 0 | AI21: 1659.3574 | AJ21: 1188.3301 | AK21: 0 | AL21: 471.02728 | AM21: 0 | AN21: 0 | AO21: 0 | AP21: 0 | AQ21: 0 | AR21: 0 | AS21: 0 | AT21: 0 | AU21: 0 | AV21: 0 | AW21: 0 | AX21: 0 | AY21: 191333.33 | AZ21: 1823873.8 | BA21: 679011.54 | BB21: 34271.694 | BC21: 34271.694 | BD21: 0 | BE21: 0 | BF21: 201547 | BG21: 201547 | BH21: 0 | BI21: 12042.324 | BJ21: 188890 | BK21: 12263.68 | BL21: 12263.68 | BM21: 0 | BN21: 25515.76 | BO21: 86637.51 | BP21: 14400 | BQ21: 0 | BR21: 0 | BS21: 72237.51 | BT21: 117843.57 | BU21: 107838 | BV21: 10005.57 | BW21: 0 | BX21: 0 | BY21: 17166.83 | BZ21: 17166.83 | CA21: 1106.24 | CB21: 15473.35 | CC21: 587.24 | CD21: 0 | CE21: 0 | CF21: 0 | CG21: 0 | CH21: 1127695.5 | CI21: 261033 | CJ21: 0 | CK21: 0 | CL21: 128233 | CM21: 46453 | CN21: 22801 | CO21: 63546 | CP21: 168000 | CQ21: 9449 | CR21: 710 | CS21: 8052 | CT21: 0 | CU21: 187 | CV21: 0 | CW21: 0 | CX21: 500 | CY21: 46091.387 | CZ21: 23491.5 | DA21: 0 | DB21: 200 | DC21: 82.5 | DD21: 0 | DE21: 0 | DF21: 22317.387 | DG21: 0 | DH21: 142003 | DI21: 0 | DJ21: 0 | DK21: 0 | DL21: 0 | DM21: 0 | DN21: 0 | DO21: 0 | DP21: 0 | DQ21: 0 | DR21: 0 | DS21: 0 | DT21: 0 | DU21: 0 | DV21: 0 | DW21: 0 | DX21: 0 | DY21: 0 | DZ21: 0 | EA21: 0 | EB21: 0 | EC21: 0 | ED21: 0 | EE21: 0 | EF21: 5058 | EG21: 0 | EH21: 0 | EI21: 110867.9 | EJ21: 0 | EK21: 0 | EL21: 0 | EM21: 45835 | EN21: 0 | EO21: 5332.5 | EP21: 0 | EQ21: 5332.5 | ER21: 13986 | ES21: 0 | ET21: 0 | EU21: 0 | EV21: 46.666667 | EW21: 0 | EX21: 0 | EY21: 46.666667 | EZ21: 0 | FA21: 0 | FB21: 0 | FC21: 0 | FD21: 0 | FE21: 45000 | FF21: 0 | FG21: 45000 | FH21: 0 | FI21: 161212.92 | FJ21: 41212.04 | FK21: 41212.04 | FL21: 0 | FM21: 2812.5 | FN21: 0 | FO21: 0 | FP21: 0 | FQ21: 0 | FR21: 2812.5 | FS21: 0 | FT21: 18001.432 | FU21: 45003.58 | FV21: 6750.537 | FY21: 2250179 | FZ21: 2172912.9 | GA21: 349039.08 | GB21: 1823873.8 | GC21: 426305.17 | GD21: 0.18945389 | GE21: 77266.094 | GF21: 0.034337755 | GJ21: 45615 | GL21: 45620 | GO21: 45622 | GR21: - - | GU21: - - | HA21: 45626 | HB21: 45629 | HE21: 37 | HF21: 4 | HG21: 9 | HH21: 24 | HK21: 41 | HL21: 9 | HM21: 24 | HN21: 4 | HO21: 0 | HP21: 13 | HQ21: 91 | HR21: 39
A22: =ROW()-1 -> 21 | B22: 2024 | C22: 6月 | D22: 大港 | E22: 70520 | F22: 罗健 | G22: ZJ70D | H22: 大港勘探事业部 | I22: 滨海26 | J22: 歧口 | K22: 预探井 | L22: 定向井 | M22: 3 | N22: 5148 | O22: 5175 | P22: 8 | Q22: 0 | R22: 49 | S22: 14 | T22: 63 | U22: 71 | V22: 0 | W22: 2.1 | X22: 2.3666667 | Y22: 15579265 | Z22: 413934.44 | AA22: 15165331 | AB22: 2197849.2 | AC22: 1124166.7 | AD22: 1124166.7 | AE22: 0 | AF22: 70743.442 | AG22: 70743.442 | AH22: 0 | AI22: 32605.738 | AJ22: 24091.426 | AK22: 8153.6104 | AL22: 360.70169 | AM22: 0 | AN22: 0 | AO22: 0 | AP22: 0 | AQ22: 0 | AR22: 0 | AS22: 0 | AT22: 0 | AU22: 0 | AV22: 0 | AW22: 0 | AX22: 0 | AY22: 970333.33 | AZ22: 12967481 | BA22: 4311708.8 | BB22: 571130.55 | BC22: 571130.55 | BD22: 0 | BE22: 0 | BF22: 1531414 | BG22: 1531414 | BH22: 0 | BI22: 34272.612 | BJ22: 103363 | BK22: 902962.77 | BL22: 600210.48 | BM22: 302752.29 | BN22: 251561.06 | BO22: 269729.7 | BP22: 100800 | BQ22: 0 | BR22: 0 | BS22: 168929.7 | BT22: 647275.14 | BU22: 538200 | BV22: 109075.14 | BW22: 0 | BX22: 0 | BY22: 751408.44 | BZ22: 127986.13 | CA22: 27240.35 | CB22: 9106.62 | CC22: 91639.16 | CD22: 623422.31 | CE22: 415748.93 | CF22: 207673.38 | CG22: 0 | CH22: 7904364.1 | CI22: 709974 | CJ22: 0 | CK22: 0 | CL22: 370368 | CM22: 89945 | CN22: 63178 | CO22: 186483 | CP22: 923000 | CQ22: 32148.337 | CR22: 2843.1 | CS22: 27104.38 | CT22: 0 | CU22: 458 | CV22: 0 | CW22: 0 | CX22: 1742.8571 | CY22: 14645.927 | CZ22: 4873.7857 | DA22: 0 | DB22: 417.79 | DC22: 138.57143 | DD22: 0 | DE22: 2500 | DF22: 6715.78 | DG22: 0 | DH22: 732857 | DI22: 141665.33 | DJ22: 0 | DK22: 141665.33 | DL22: 0 | DM22: 0 | DN22: 0 | DO22: 0 | DP22: 0 | DQ22: 28906.42 | DR22: 0 | DS22: 0 | DT22: 0 | DU22: 0 | DV22: 0 | DW22: 0 | DX22: 0 | DY22: 28906.42 | DZ22: 0 | EA22: 0 | EB22: 0 | EC22: 0 | ED22: 0 | EE22: 0 | EF22: 55829 | EG22: 0 | EH22: 376816.52 | EI22: 967169.53 | EJ22: 0 | EK22: 0 | EL22: 151498 | EM22: 0 | EN22: 0 | EO22: 29862 | EP22: 0 | EQ22: 29862 | ER22: 86265 | ES22: 0 | ET22: 0 | EU22: 5640 | EV22: 236.66667 | EW22: 0 | EX22: 0 | EY22: 236.66667 | EZ22: 0 | FA22: 0 | FB22: 0 | FC22: 0 | FD22: 0 | FE22: 0 | FF22: 0 | FG22: 0 | FH22: 0 | FI22: 3020760.7 | FJ22: 129328.06 | FK22: 129328.06 | FL22: 0 | FM22: 14804.429 | FN22: 0 | FO22: 0 | FP22: 0 | FQ22: 0 | FR22: 14804.429 | FS22: 0 | FT22: 124634.12 | FU22: 311585.3 | FV22: 46737.795 | FY22: 15579265 | FZ22: 15165331 | GA22: 2197849.2 | GB22: 12967481 | GC22: 2611783.6 | GD22: 0.16764485 | GE22: 413934.44 | GF22: 0.026569574 | GJ22: 45386 | GL22: 45394 | GO22: 45397 | GR22: 45418 | GU22: - - | HA22: 45443 | HB22: 45457 | HE22: 45 | HF22: 5 | HG22: 14 | HH22: 26 | HK22: 349 | HL22: 489 | HM22: 263 | HN22: 0 | HO22: 0 | HP22: 0 | HQ22: 333 | HR22: 89
A23: =ROW()-1 -> 22 | B23: 2024 | C23: 1月 | D23: 大港 | E23: BH70301 | F23: 杨俊峰 | G23: ZJ70D | H23: 大港勘探事业部 | I23: 滨探1 | J23: 歧口 | K23: 预探井 | L23: 定向井 | M23: 3 | N23: 5181 | O23: 5139 | P23: 9 | Q23: 0 | R23: 44 | S23: 19 | T23: 63 | U23: 72 | V23: 0 | W23: 2.1 | X23: 2.4 | Y23: 26644694 | Z23: 4091463.5 | AA23: 22553230 | AB23: 4403916.5 | AC23: 1200000 | AD23: 1200000 | AE23: 0 | AF23: 779595.82 | AG23: 30646.79 | AH23: 748949.03 | AI23: 60091.894 | AJ23: 30105.18 | AK23: 15744.628 | AL23: 14242.086 | AM23: 1380228.8 | AN23: 202529.71 | AO23: 1177699.1 | AP23: 0 | AQ23: 0 | AR23: 0 | AS23: 0 | AT23: 0 | AU23: 0 | AV23: 0 | AW23: 0 | AX23: 0 | AY23: 984000 | AZ23: 18149314 | BA23: 4842334.7 | BB23: 409320 | BC23: 409320 | BD23: 0 | BE23: 0 | BF23: 2070388 | BG23: 2070388 | BH23: 0 | BI23: 1743.2064 | BJ23: 218283 | BK23: 592035.43 | BL23: 274660.66 | BM23: 317374.77 | BN23: 701567.38 | BO23: 205350.48 | BP23: 100800 | BQ23: 0 | BR23: 0 | BS23: 104550.48 | BT23: 643647.2 | BU23: 534456 | BV23: 109191.2 | BW23: 0 | BX23: 0 | BY23: 478656.71 | BZ23: 60051.55 | CA23: 36601.86 | CB23: 1053 | CC23: 22396.69 | CD23: 418605.16 | CE23: 0 | CF23: 43009.69 | CG23: 375595.47 | CH23: 12828323 | CI23: 1118869 | CJ23: 0 | CK23: 0 | CL23: 641522 | CM23: 168791 | CN23: 100471 | CO23: 208085 | CP23: 972000 | CQ23: 56538.168 | CR23: 5253.3 | CS23: 7936.97 | CT23: 0 | CU23: 1312.5 | CV23: 0 | CW23: 0 | CX23: 42035.398 | CY23: 35993.341 | CZ23: 10177.875 | DA23: 0 | DB23: 925 | DC23: 185 | DD23: 0 | DE23: 15800 | DF23: 8905.466 | DG23: 0 | DH23: 2090594 | DI23: 105150.5 | DJ23: 0 | DK23: 0 | DL23: 0 | DM23: 0 | DN23: 0 | DO23: 0 | DP23: 105150.5 | DQ23: 0 | DR23: 0 | DS23: 0 | DT23: 0 | DU23: 0 | DV23: 0 | DW23: 0 | DX23: 0 | DY23: 0 | DZ23: 0 | EA23: 0 | EB23: 0 | EC23: 0 | ED23: 0 | EE23: 0 | EF23: 55141 | EG23: 0 | EH23: 520474.78 | EI23: 2964677.4 | EJ23: 0 | EK23: 0 | EL23: 0 | EM23: 0 | EN23: 80000 | EO23: 63049 | EP23: 63049 | EQ23: 0 | ER23: 91368 | ES23: 0 | ET23: 0 | EU23: 1080 | EV23: 240 | EW23: 0 | EX23: 0 | EY23: 240 | EZ23: 0 | FA23: 0 | FB23: 0 | FC23: 0 | FD23: 0 | FE23: 99049 | FF23: 0 | FG23: 99049 | FH23: 0 | FI23: 3579056.5 | FJ23: 135981.34 | FK23: 135981.34 | FL23: 0 | FM23: 33075 | FN23: 0 | FO23: 0 | FP23: 0 | FQ23: 0 | FR23: 33075 | FS23: 0 | FT23: 213157.55 | FU23: 532893.88 | FV23: 79934.082 | FY23: 26644694 | FZ23: 22553230 | GA23: 4403916.5 | GB23: 18149314 | GC23: 8495380 | GD23: 0.31883947 | GE23: 4091463.5 | GF23: 0.15355641 | GJ23: 45241 | GL23: 45250 | GO23: 45256 | GR23: 45279 | GU23: - - | HA23: 45294 | HB23: 45313 | HE23: 47 | HF23: 4 | HG23: 16 | HH23: 27 | HK23: 273 | HL23: 155 | HM23: 212 | HN23: 0 | HO23: 0 | HP23: 0 | HQ23: 453 | HR23: 417
